Workbook
Name AGOSTO: #REF!
Name AGOSTO: #REF!
Name AGOSTO: #REF!
Name AGOSTO: #REF!
Name AGOSTO: #REF!
Name AGOSTO: #REF!
Name AGOSTO: #REF!
Name AGOSTO: #REF!
Name AGOSTO: #REF!
Name AGOSTO: #REF!
Name AGOSTO: #REF!
Name AGOSTO: #REF!
Name AGOSTO: #REF!
Name AGOSTO: #REF!
Name AGOSTO: #REF!
Name WinCal4: #REF!
Name WinCal4: #REF!
Name WinCal4: #REF!
Name WinCal4: #REF!
Name WinCal4: #REF!
Name WinCal4: #REF!
Name WinCal4: #REF!
Name WinCal4: #REF!
Name WinCal4: #REF!
Name WinCal4: #REF!
Name WinCal4: #REF!
Name WinCal4: #REF!
Name WinCal4: #REF!
Name WinCal4: #REF!
Name WinCal4: #REF!
Name WinCal5: #REF!
Name WinCal5: #REF!
Name WinCal5: #REF!
Name WinCal5: #REF!
Name WinCal5: #REF!
Name WinCal5: #REF!
Name WinCal5: #REF!
Name WinCal5: #REF!
Name WinCal5: #REF!
Name WinCal5: #REF!
Name WinCal5: #REF!
Name WinCal5: #REF!
Name WinCal5: #REF!
Name WinCal5: #REF!
Name WinCal5: #REF!
Name WinCalendar_Calendar_4: #REF!
Name WinCalendar_Calendar_4: #REF!
Name WinCalendar_Calendar_4: #REF!
Name WinCalendar_Calendar_4: #REF!
Name WinCalendar_Calendar_4: #REF!
Name WinCalendar_Calendar_4: #REF!
Name WinCalendar_Calendar_4: #REF!
Name WinCalendar_Calendar_4: #REF!
Name WinCalendar_Calendar_4: #REF!
Name WinCalendar_Calendar_4: #REF!
Name WinCalendar_Calendar_4: #REF!
Name WinCalendar_Calendar_4: #REF!
Name WinCalendar_Calendar_4: #REF!
Name WinCalendar_Calendar_4: #REF!
Name WinCalendar_Calendar_4: #REF!

Sheet 2026_RECEITA_BRASANTOS
B1: BRASANTOS SERVIÇOS ESPECIALIZADOS
B2: RECEITA
B4: CNAE-Fiscal: | D4: N812140000 _ LIMPEZA EM PREDIOS E EM DOMICILIOS
B5: ATIVIDADE MUNICIPIO: | D5: 710 - 7.10 - Limpeza, manutenção e conservação de vias e logradouros
B7: ANO: | C7: 2026
B8: CLIENTE: | C8: BRASANTOS | E8: REGIME DE TRIBUTAÇÃO: | F8: LUCRO PRESUMIDO
B9: CNPJ: | C9: 23.372.953.0001-86
B10: ENDEREÇO: | C10: ÁGUAS CLARAS
B11: TOTAL | C11: =E254 -> 92319
B13: COMP | C13: NF | D13: CLIENTE | E13: VALOR TOTAL DOS SERVIÇOS | F13: MATERIAS | G13: EQUIPAMENTOS | H13: VALE TRANSPORTE | Q13: VALE ALIMENTAÇÃO | Z13: UNIFORME | AI13: TOTAL BASE RETENÇÃO INSS | AJ13: BASE CÁCULO INSS | AK13: RETENÇÃO DESTACADO NA NF | AR13: TOTAL RETENÇÃO NF | AS13: VALOR LIQUIDO DA NOTA FISCAL
H14: 44H/S | L14: 12 X 36 | P14: TOTAL | Q14: 44H/S | U14: 12 X 36 | Y14: TOTAL | Z14: 44H/S | AD14: 12 X 36 | AH14: TOTAL | AK14: GPS 2632 | AL14: IRRJ 2089 | AM14: CSLL 2372 | AN14: COFINS 2172 | AO14: PIS 8109 | AP14: ISSQN 1732 | AQ14: TOTAL
H15: QTDE | I15: $ UNIT | J15: DIAS | K15: TOTAL | L15: QTDE | M15: $ UNIT | N15: DIAS | O15: TOTAL | Q15: QTDE | R15: $ UNIT | S15: DIAS | T15: TOTAL | U15: QTDE | V15: $ UNIT | W15: DIAS | X15: TOTAL | Z15: QTDE | AA15: $ UNIT | AB15: ANO | AC15: TOTAL | AD15: QTDE | AE15: $ UNIT | AF15: ANO | AG15: TOTAL | AJ15: % | AK15: 0.11 | AL15: 0.01 | AM15: 0.01 | AN15: 0.03 | AO15: 0.0065 | AP15: 0.05 | AQ15: =SUBTOTAL(9,AL15:AP15) -> 0.1065 | AR15: =AK15+AQ15 -> 0.2165
B17: 01/24 | C17: 152 | D17: AHSERC | E17: 5458 | F17: 774.5 | G17: 326.16667 | H17: 1 | I17: 16 | J17: 26 | K17: =H17*I17*J17 -> 416 | L17: 0 | M17: 0 | N17: 0 | O17: =L17*M17*N17 -> 0 | P17: =K17+O17 -> 416 | Q17: 1 | R17: 40.5 | S17: 26 | T17: =Q17*R17*S17 -> 1053 | U17: 0 | V17: 0 | W17: 0 | X17: =U17*V17*W17 -> 0 | Y17: =T17+X17 -> 1053 | Z17: 1 | AA17: 80 | AB17: 1 | AC17: =Z17*AA17*AB17 -> 80 | AD17: 0 | AE17: 0 | AF17: 0 | AG17: =AD17*AE17*AF17 -> 0 | AH17: =AC17+AG17 -> 80 | AI17: =F17+G17+P17+Y17+AH17 -> 2649.6667 | AJ17: =AI17/E17 -> 0.48546476 | AK17: 308.91667 | AL17: 54.58 | AM17: 54.58 | AN17: 163.74 | AO17: 35.477 | AP17: 272.9 | AQ17: =SUM(AL17:AP17) -> 581.277 | AR17: =AK17+AQ17 -> 890.19367 | AS17: =E17-AR17 -> 4567.8063
B18: 01/24 | C18: 153 | D18: RIO PARANÃ | E18: 14796 | F18: 2186.2 | G18: 0 | H18: 1 | I18: 16 | J18: 26 | K18: =H18*I18*J18 -> 416 | L18: 2 | M18: 16 | N18: 16 | O18: =L18*M18*N18 -> 512 | P18: =K18+O18 -> 928 | Q18: 1 | R18: 40.5 | S18: 26 | T18: =Q18*R18*S18 -> 1053 | U18: 2 | V18: 40.5 | W18: 16 | X18: =U18*V18*W18 -> 1296 | Y18: =T18+X18 -> 2349 | Z18: 1 | AA18: 80 | AB18: 1 | AC18: =Z18*AA18*AB18 -> 80 | AD18: 2 | AE18: 80 | AF18: 1 | AG18: =AD18*AE18*AF18 -> 160 | AH18: =AC18+AG18 -> 240 | AI18: =F18+G18+P18+Y18+AH18 -> 5703.2 | AJ18: =AI18/E18 -> 0.38545553 | AK18: 1000.208 | AL18: 147.96 | AM18: 147.96 | AN18: 443.88 | AO18: 96.174 | AP18: 739.8 | AQ18: =SUM(AL18:AP18) -> 1575.774 | AR18: =AK18+AQ18 -> 2575.982 | AS18: =E18-AR18 -> 12220.018
B19: 01/24 | C19: 154 | D19: VANESSA | E19: 4800 | F19: 781.45 | G19: 0 | H19: 1 | I19: 16 | J19: 26 | K19: =H19*I19*J19 -> 416 | L19: 0 | M19: 0 | N19: 0 | O19: =L19*M19*N19 -> 0 | P19: =K19+O19 -> 416 | Q19: 1 | R19: 40.5 | S19: 26 | T19: =Q19*R19*S19 -> 1053 | U19: 0 | V19: 0 | W19: 0 | X19: =U19*V19*W19 -> 0 | Y19: =T19+X19 -> 1053 | Z19: 1 | AA19: 80 | AB19: 1 | AC19: =Z19*AA19*AB19 -> 80 | AD19: 0 | AE19: 0 | AF19: 0 | AG19: =AD19*AE19*AF19 -> 0 | AH19: =AC19+AG19 -> 80 | AI19: =F19+G19+P19+Y19+AH19 -> 2330.45 | AJ19: =AI19/E19 -> 0.48551042 | AK19: 271.6505 | AL19: 48 | AM19: 48 | AN19: 144 | AO19: 31.2 | AP19: 240 | AQ19: =SUM(AL19:AP19) -> 511.2 | AR19: =AK19+AQ19 -> 782.8505 | AS19: =E19-AR19 -> 4017.1495
B20: 01/24 | C20: 155 | D20: ATLANTIS | E20: 24300 | F20: 3221.55 | G20: 0 | H20: 3 | I20: 16 | J20: 26 | K20: =H20*I20*J20 -> 1248 | L20: 2 | M20: 16 | N20: =16+4 -> 20 | O20: =L20*M20*N20 -> 640 | P20: =K20+O20 -> 1888 | Q20: 3 | R20: 40.5 | S20: 26 | T20: =Q20*R20*S20 -> 3159 | U20: 2 | V20: 40.5 | W20: =16+4 -> 20 | X20: =U20*V20*W20 -> 1620 | Y20: =T20+X20 -> 4779 | Z20: 3 | AA20: 60 | AB20: 1 | AC20: =Z20*AA20*AB20 -> 180 | AD20: 3 | AE20: 90 | AF20: 1 | AG20: =AD20*AE20*AF20 -> 270 | AH20: =AC20+AG20 -> 450 | AI20: =F20+G20+P20+Y20+AH20 -> 10338.55 | AJ20: =AI20/E20 -> 0.42545473 | AK20: 1535.7595 | AL20: 243 | AM20: 243 | AN20: 729 | AO20: 157.95 | AP20: 1215 | AQ20: =SUM(AL20:AP20) -> 2587.95 | AR20: =AK20+AQ20 -> 4123.7095 | AS20: =E20-AR20 -> 20176.29
B21: 01/24 | C21: 156 | D21: QUATRO ESTAÇÕES 509 | E21: 5199 | F21: 833.1 | G21: 0 | H21: 1 | I21: 16 | J21: 26 | K21: =H21*I21*J21 -> 416 | L21: 0 | M21: 0 | N21: 0 | O21: =L21*M21*N21 -> 0 | P21: =K21+O21 -> 416 | Q21: 1 | R21: 40.5 | S21: 26 | T21: =Q21*R21*S21 -> 1053 | U21: 0 | V21: 0 | W21: 0 | X21: =U21*V21*W21 -> 0 | Y21: =T21+X21 -> 1053 | Z21: 1 | AA21: 80 | AB21: 1 | AC21: =Z21*AA21*AB21 -> 80 | AD21: 0 | AE21: 0 | AF21: 0 | AG21: =AD21*AE21*AF21 -> 0 | AH21: =AC21+AG21 -> 80 | AI21: =F21+G21+P21+Y21+AH21 -> 2382.1 | AJ21: =AI21/E21 -> 0.45818427 | AK21: 309.859 | AL21: 51.99 | AM21: 51.99 | AN21: 155.97 | AO21: 33.7935 | AP21: 259.95 | AQ21: =SUM(AL21:AP21) -> 553.6935 | AR21: =AK21+AQ21 -> 863.5525 | AS21: =E21-AR21 -> 4335.4475
B22: 01/24 | C22: 157 | D22: QUATRO ESTAÇÕES 507 | E22: 5377 | F22: 914.6 | G22: 0 | H22: 1 | I22: 16 | J22: 26 | K22: =H22*I22*J22 -> 416 | L22: 0 | M22: 0 | N22: 0 | O22: =L22*M22*N22 -> 0 | P22: =K22+O22 -> 416 | Q22: 1 | R22: 40.5 | S22: 26 | T22: =Q22*R22*S22 -> 1053 | U22: 0 | V22: 0 | W22: 0 | X22: =U22*V22*W22 -> 0 | Y22: =T22+X22 -> 1053 | Z22: 1 | AA22: 80 | AB22: 1 | AC22: =Z22*AA22*AB22 -> 80 | AD22: 0 | AE22: 0 | AF22: 0 | AG22: =AD22*AE22*AF22 -> 0 | AH22: =AC22+AG22 -> 80 | AI22: =F22+G22+P22+Y22+AH22 -> 2463.6 | AJ22: =AI22/E22 -> 0.4581737 | AK22: 320.474 | AL22: 53.77 | AM22: 53.77 | AN22: 161.31 | AO22: 34.9505 | AP22: 268.85 | AQ22: =SUM(AL22:AP22) -> 572.6505 | AR22: =AK22+AQ22 -> 893.1245 | AS22: =E22-AR22 -> 4483.8755
B23: 01/24 | C23: 158 | D23: TAJ MAHAL | E23: 33786.42 | F23: 2796.15 | G23: 0 | H23: 1 | I23: 10 | J23: 26 | K23: =H23*I23*J23 -> 260 | L23: 2 | M23: 19.25 | N23: 16 | O23: =L23*M23*N23 -> 616 | P23: =K23+O23 -> 876 | Q23: 4 | R23: 18.2 | S23: 22 | T23: =Q23*R23*S23 -> 1601.6 | U23: 2 | V23: 18.2 | W23: 15.5 | X23: =U23*V23*W23 -> 564.2 | Y23: =T23+X23 -> 2165.8 | Z23: 4 | AA23: =90/12 -> 7.5 | AB23: 2 | AC23: =Z23*AA23*AB23 -> 60 | AD23: 2 | AE23: =90/12 -> 7.5 | AF23: 2 | AG23: =AD23*AE23*AF23 -> 30 | AH23: =AC23+AG23 -> 90 | AI23: =F23+G23+P23+Y23+AH23 -> 5927.95 | AJ23: =AI23/E23 -> 0.17545363 | AK23: 3064.4317 | AL23: 337.8642 | AM23: 337.8642 | AN23: 1013.5926 | AO23: 219.61173 | AP23: 0 | AQ23: =SUM(AL23:AP23) -> 1908.9327 | AR23: =AK23+AQ23 -> 4973.3644 | AS23: =E23-AR23 -> 28813.056
B24: 01/24 | C24: 159 | D24: DIRECIONAL_ ÁGUA BRANCA_SOBRADINHO | E24: 23824.9 | F24: 0 | G24: 0 | H24: 0 | I24: 0 | J24: 0 | K24: =H24*I24*J24 -> 0 | L24: 0 | M24: 0 | N24: 0 | O24: =L24*M24*N24 -> 0 | P24: =K24+O24 -> 0 | Q24: 0 | R24: 0 | S24: 0 | T24: =Q24*R24*S24 -> 0 | U24: 0 | V24: 0 | W24: 0 | X24: =U24*V24*W24 -> 0 | Y24: =T24+X24 -> 0 | Z24: 0 | AA24: 0 | AB24: 0 | AC24: =Z24*AA24*AB24 -> 0 | AD24: 0 | AE24: 0 | AF24: 0 | AG24: =AD24*AE24*AF24 -> 0 | AH24: =AC24+AG24 -> 0 | AI24: =F24+G24+P24+Y24+AH24 -> 0 | AJ24: =AI24/E24 -> 0 | AK24: 2620.739 | AL24: 357.37 | AM24: 238.249 | AN24: 714.747 | AO24: 154.86185 | AP24: 0 | AQ24: =SUM(AL24:AP24) -> 1465.2278 | AR24: =AK24+AQ24 -> 4085.9668 | AS24: =E24-AR24 -> 19738.933
B25: 01/24 | C25: 160 | D25: DIRECIONAL_ ITAGUATINS_SAMAMBAIA | E25: 4018.49 | F25: 0 | G25: 0 | H25: 0 | I25: 0 | J25: 0 | K25: =H25*I25*J25 -> 0 | L25: 0 | M25: 0 | N25: 0 | O25: =L25*M25*N25 -> 0 | P25: =K25+O25 -> 0 | Q25: 0 | R25: 0 | S25: 0 | T25: =Q25*R25*S25 -> 0 | U25: 0 | V25: 0 | W25: 0 | X25: =U25*V25*W25 -> 0 | Y25: =T25+X25 -> 0 | Z25: 0 | AA25: 0 | AB25: 0 | AC25: =Z25*AA25*AB25 -> 0 | AD25: 0 | AE25: 0 | AF25: 0 | AG25: =AD25*AE25*AF25 -> 0 | AH25: =AC25+AG25 -> 0 | AI25: =F25+G25+P25+Y25+AH25 -> 0 | AJ25: =AI25/E25 -> 0 | AK25: 442.0339 | AL25: 60.28 | AM25: 40.1849 | AN25: 120.5547 | AO25: 26.120185 | AP25: 200.9245 | AQ25: =SUM(AL25:AP25) -> 448.06428 | AR25: =AK25+AQ25 -> 890.09818 | AS25: =E25-AR25 -> 3128.3918
B26: 01/24 | C26: 162 | D26: DIRECIONAL_TAGUATINGA_SANTA MARIA | E26: 3891.25 | F26: 0 | G26: 0 | H26: 0 | I26: 0 | J26: 0 | K26: =H26*I26*J26 -> 0 | L26: 0 | M26: 0 | N26: 0 | O26: =L26*M26*N26 -> 0 | P26: =K26+O26 -> 0 | Q26: 0 | R26: 0 | S26: 0 | T26: =Q26*R26*S26 -> 0 | U26: 0 | V26: 0 | W26: 0 | X26: =U26*V26*W26 -> 0 | Y26: =T26+X26 -> 0 | Z26: 0 | AA26: 0 | AB26: 0 | AC26: =Z26*AA26*AB26 -> 0 | AD26: 0 | AE26: 0 | AF26: 0 | AG26: =AD26*AE26*AF26 -> 0 | AH26: =AC26+AG26 -> 0 | AI26: =F26+G26+P26+Y26+AH26 -> 0 | AJ26: =AI26/E26 -> 0 | AK26: 428.0375 | AL26: 58.37 | AM26: 38.9125 | AN26: 116.7375 | AO26: 25.293125 | AP26: 0 | AQ26: =SUM(AL26:AP26) -> 239.31312 | AR26: =AK26+AQ26 -> 667.35063 | AS26: =E26-AR26 -> 3223.8994
B27: 01/24 | C27: 161 | D27: DIRECIONAL_ITAPEMA_PLANALTINA | E27: 4104.1 | F27: 0 | G27: 0 | H27: 0 | I27: 0 | J27: 0 | K27: =H27*I27*J27 -> 0 | L27: 0 | M27: 0 | N27: 0 | O27: =L27*M27*N27 -> 0 | P27: =K27+O27 -> 0 | Q27: 0 | R27: 0 | S27: 0 | T27: =Q27*R27*S27 -> 0 | U27: 0 | V27: 0 | W27: 0 | X27: =U27*V27*W27 -> 0 | Y27: =T27+X27 -> 0 | Z27: 0 | AA27: 0 | AB27: 0 | AC27: =Z27*AA27*AB27 -> 0 | AD27: 0 | AE27: 0 | AF27: 0 | AG27: =AD27*AE27*AF27 -> 0 | AH27: =AC27+AG27 -> 0 | AI27: =F27+G27+P27+Y27+AH27 -> 0 | AJ27: =AI27/E27 -> 0 | AK27: 451.451 | AL27: 61.56 | AM27: 41.041 | AN27: 123.123 | AO27: 26.67665 | AP27: 205.205 | AQ27: =SUM(AL27:AP27) -> 457.60565 | AR27: =AK27+AQ27 -> 909.05665 | AS27: =E27-AR27 -> 3195.0434
B28: 02/24 | C28: 185 | D28: AHSERC | E28: 5928 | F28: 950.61 | G28: 326.16667 | H28: 1 | I28: 16 | J28: 26 | K28: =H28*I28*J28 -> 416 | L28: 0 | M28: 0 | N28: 0 | O28: =L28*M28*N28 -> 0 | P28: =K28+O28 -> 416 | Q28: 1 | R28: 42.5 | S28: 26 | T28: =Q28*R28*S28 -> 1105 | U28: 0 | V28: 0 | W28: 0 | X28: =U28*V28*W28 -> 0 | Y28: =T28+X28 -> 1105 | Z28: 1 | AA28: 80 | AB28: 1 | AC28: =Z28*AA28*AB28 -> 80 | AD28: 0 | AE28: 0 | AF28: 0 | AG28: =AD28*AE28*AF28 -> 0 | AH28: =AC28+AG28 -> 80 | AI28: =F28+G28+P28+Y28+AH28 -> 2877.7767 | AJ28: =AI28/E28 -> 0.4854549 | AK28: 335.52457 | AL28: 59.28 | AM28: 59.28 | AN28: 177.84 | AO28: 38.532 | AP28: 296.4 | AQ28: =SUM(AL28:AP28) -> 631.332 | AR28: =AK28+AQ28 -> 966.85657 | AS28: =E28-AR28 -> 4961.1434
B29: 02/24 | C29: 171 | D29: RIO PARANÃ | E29: 16252 | F29: 2331.4 | G29: 300 | H29: 1 | I29: 16 | J29: 26 | K29: =H29*I29*J29 -> 416 | L29: 2 | M29: 16 | N29: 16 | O29: =L29*M29*N29 -> 512 | P29: =K29+O29 -> 928 | Q29: 1 | R29: 42.5 | S29: 26 | T29: =Q29*R29*S29 -> 1105 | U29: 2 | V29: 42.5 | W29: 16 | X29: =U29*V29*W29 -> 1360 | Y29: =T29+X29 -> 2465 | Z29: 1 | AA29: 80 | AB29: 1 | AC29: =Z29*AA29*AB29 -> 80 | AD29: 2 | AE29: 80 | AF29: 1 | AG29: =AD29*AE29*AF29 -> 160 | AH29: =AC29+AG29 -> 240 | AI29: =F29+G29+P29+Y29+AH29 -> 6264.4 | AJ29: =AI29/E29 -> 0.3854541 | AK29: 1098.636 | AL29: 162.52 | AM29: 162.52 | AN29: 487.56 | AO29: 105.638 | AP29: 812.6 | AQ29: =SUM(AL29:AP29) -> 1730.838 | AR29: =AK29+AQ29 -> 2829.474 | AS29: =E29-AR29 -> 13422.526
B30: 02/24 | C30: 165 | D30: VANESSA | E30: 5562 | F30: 911.65 | G30: 187.41667 | H30: 1 | I30: 16 | J30: 26 | K30: =H30*I30*J30 -> 416 | L30: 0 | M30: 0 | N30: 0 | O30: =L30*M30*N30 -> 0 | P30: =K30+O30 -> 416 | Q30: 1 | R30: 42.5 | S30: 26 | T30: =Q30*R30*S30 -> 1105 | U30: 0 | V30: 0 | W30: 0 | X30: =U30*V30*W30 -> 0 | Y30: =T30+X30 -> 1105 | Z30: 1 | AA30: 80 | AB30: 1 | AC30: =Z30*AA30*AB30 -> 80 | AD30: 0 | AE30: 0 | AF30: 0 | AG30: =AD30*AE30*AF30 -> 0 | AH30: =AC30+AG30 -> 80 | AI30: =F30+G30+P30+Y30+AH30 -> 2700.0667 | AJ30: =AI30/E30 -> 0.48544888 | AK30: 314.81267 | AL30: 55.62 | AM30: 55.62 | AN30: 166.86 | AO30: 36.153 | AP30: 278.1 | AQ30: =SUM(AL30:AP30) -> 592.353 | AR30: =AK30+AQ30 -> 907.16567 | AS30: =E30-AR30 -> 4654.8343
B31: 02/24 | C31: 166 | D31: ATLANTIS | E31: 26266 | F31: 3822 | G31: 0 | H31: 3 | I31: 16 | J31: 26 | K31: =H31*I31*J31 -> 1248 | L31: 2 | M31: 16 | N31: =16+4 -> 20 | O31: =L31*M31*N31 -> 640 | P31: =K31+O31 -> 1888 | Q31: 3 | R31: 42.5 | S31: 26 | T31: =Q31*R31*S31 -> 3315 | U31: 2 | V31: 42.5 | W31: =16+4 -> 20 | X31: =U31*V31*W31 -> 1700 | Y31: =T31+X31 -> 5015 | Z31: 3 | AA31: 60 | AB31: 1 | AC31: =Z31*AA31*AB31 -> 180 | AD31: 3 | AE31: 90 | AF31: 1 | AG31: =AD31*AE31*AF31 -> 270 | AH31: =AC31+AG31 -> 450 | AI31: =F31+G31+P31+Y31+AH31 -> 11175 | AJ31: =AI31/E31 -> 0.42545496 | AK31: 1660.01 | AL31: 262.66 | AM31: 262.66 | AN31: 787.98 | AO31: 170.729 | AP31: 1313.3 | AQ31: =SUM(AL31:AP31) -> 2797.329 | AR31: =AK31+AQ31 -> 4457.339 | AS31: =E31-AR31 -> 21808.661
B32: 02/24 | C32: 168 | D32: QUATRO ESTAÇÕES 509 | E32: 5810 | F32: 710.95 | G32: 350 | H32: 1 | I32: 16 | J32: 26 | K32: =H32*I32*J32 -> 416 | L32: 0 | M32: 0 | N32: 0 | O32: =L32*M32*N32 -> 0 | P32: =K32+O32 -> 416 | Q32: 1 | R32: 42.5 | S32: 26 | T32: =Q32*R32*S32 -> 1105 | U32: 0 | V32: 0 | W32: 0 | X32: =U32*V32*W32 -> 0 | Y32: =T32+X32 -> 1105 | Z32: 1 | AA32: 80 | AB32: 1 | AC32: =Z32*AA32*AB32 -> 80 | AD32: 0 | AE32: 0 | AF32: 0 | AG32: =AD32*AE32*AF32 -> 0 | AH32: =AC32+AG32 -> 80 | AI32: =F32+G32+P32+Y32+AH32 -> 2661.95 | AJ32: =AI32/E32 -> 0.45816695 | AK32: 346.2855 | AL32: 58.1 | AM32: 58.1 | AN32: 174.3 | AO32: 37.765 | AP32: 290.5 | AQ32: =SUM(AL32:AP32) -> 618.765 | AR32: =AK32+AQ32 -> 965.0505 | AS32: =E32-AR32 -> 4844.9495
B33: 02/24 | C33: 169 | D33: QUATRO ESTAÇÕES 507 | E33: 5928 | F33: 898.55 | G33: 216.5 | H33: 1 | I33: 16 | J33: 26 | K33: =H33*I33*J33 -> 416 | L33: 0 | M33: 0 | N33: 0 | O33: =L33*M33*N33 -> 0 | P33: =K33+O33 -> 416 | Q33: 1 | R33: 42.5 | S33: 26 | T33: =Q33*R33*S33 -> 1105 | U33: 0 | V33: 0 | W33: 0 | X33: =U33*V33*W33 -> 0 | Y33: =T33+X33 -> 1105 | Z33: 1 | AA33: 80 | AB33: 1 | AC33: =Z33*AA33*AB33 -> 80 | AD33: 0 | AE33: 0 | AF33: 0 | AG33: =AD33*AE33*AF33 -> 0 | AH33: =AC33+AG33 -> 80 | AI33: =F33+G33+P33+Y33+AH33 -> 2716.05 | AJ33: =AI33/E33 -> 0.45817308 | AK33: 353.3145 | AL33: 59.28 | AM33: 59.28 | AN33: 177.84 | AO33: 38.532 | AP33: 296.4 | AQ33: =SUM(AL33:AP33) -> 631.332 | AR33: =AK33+AQ33 -> 984.6465 | AS33: =E33-AR33 -> 4943.3535
B34: 02/24 | C34: 170 | D34: TAJ MAHAL | E34: 36840 | F34: 2809.7 | G34: 0 | H34: 1 | I34: 16 | J34: 26 | K34: =H34*I34*J34 -> 416 | L34: 2 | M34: 24 | N34: 16 | O34: =L34*M34*N34 -> 768 | P34: =K34+O34 -> 1184 | Q34: 4 | R34: 20 | S34: 22 | T34: =Q34*R34*S34 -> 1760 | U34: 2 | V34: 20 | W34: 15.5 | X34: =U34*V34*W34 -> 620 | Y34: =T34+X34 -> 2380 | Z34: 4 | AA34: =90/12 -> 7.5 | AB34: 2 | AC34: =Z34*AA34*AB34 -> 60 | AD34: 2 | AE34: =90/12 -> 7.5 | AF34: 2 | AG34: =AD34*AE34*AF34 -> 30 | AH34: =AC34+AG34 -> 90 | AI34: =F34+G34+P34+Y34+AH34 -> 6463.7 | AJ34: =AI34/E34 -> 0.17545331 | AK34: 3341.393 | AL34: 368.4 | AM34: 368.4 | AN34: 1105.2 | AO34: 239.46 | AP34: 0 | AQ34: =SUM(AL34:AP34) -> 2081.46 | AR34: =AK34+AQ34 -> 5422.853 | AS34: =E34-AR34 -> 31417.147
B35: 02/24 | C35: 172 | D35: AHSERC | E35: 470 | F35: 228.16 | G35: 0 | H35: 0 | I35: 0 | J35: 0 | K35: =H35*I35*J35 -> 0 | L35: 0 | M35: 0 | N35: 0 | O35: =L35*M35*N35 -> 0 | P35: =K35+O35 -> 0 | Q35: 0 | R35: 0 | S35: 0 | T35: =Q35*R35*S35 -> 0 | U35: 0 | V35: 0 | W35: 0 | X35: =U35*V35*W35 -> 0 | Y35: =T35+X35 -> 0 | Z35: 0 | AA35: 0 | AB35: 0 | AC35: =Z35*AA35*AB35 -> 0 | AD35: 0 | AE35: 0 | AF35: 0 | AG35: =AD35*AE35*AF35 -> 0 | AH35: =AC35+AG35 -> 0 | AI35: =F35+G35+P35+Y35+AH35 -> 228.16 | AJ35: =AI35/E35 -> 0.48544681 | AK35: 26.6024 | AL35: 4.7 | AM35: 4.7 | AN35: 14.1 | AO35: 3.055 | AP35: 23.5 | AQ35: =SUM(AL35:AP35) -> 50.055 | AR35: =AK35+AQ35 -> 76.6574 | AS35: =E35-AR35 -> 393.3426
B36: 02/24 | C36: 177 | D36: RIO PARANÃ | E36: 1456 | F36: 561.22 | G36: 0 | H36: 0 | I36: 0 | J36: 0 | K36: =H36*I36*J36 -> 0 | L36: 0 | M36: 0 | N36: 0 | O36: =L36*M36*N36 -> 0 | P36: =K36+O36 -> 0 | Q36: 0 | R36: 0 | S36: 0 | T36: =Q36*R36*S36 -> 0 | U36: 0 | V36: 42.5 | W36: 0 | X36: =U36*V36*W36 -> 0 | Y36: =T36+X36 -> 0 | Z36: 0 | AA36: 0 | AB36: 0 | AC36: =Z36*AA36*AB36 -> 0 | AD36: 0 | AE36: 0 | AF36: 0 | AG36: =AD36*AE36*AF36 -> 0 | AH36: =AC36+AG36 -> 0 | AI36: =F36+G36+P36+Y36+AH36 -> 561.22 | AJ36: =AI36/E36 -> 0.3854533 | AK36: 98.4258 | AL36: 14.56 | AM36: 14.56 | AN36: 43.68 | AO36: 9.464 | AP36: 72.8 | AQ36: =SUM(AL36:AP36) -> 155.064 | AR36: =AK36+AQ36 -> 253.4898 | AS36: =E36-AR36 -> 1202.5102
B37: 02/24 | C37: 179 | D37: VANESSA | E37: 762 | F37: 369.91 | G37: 0 | H37: 0 | I37: 0 | J37: 0 | K37: =H37*I37*J37 -> 0 | L37: 0 | M37: 0 | N37: 0 | O37: =L37*M37*N37 -> 0 | P37: =K37+O37 -> 0 | Q37: 0 | R37: 0 | S37: 0 | T37: =Q37*R37*S37 -> 0 | U37: 0 | V37: 0 | W37: 0 | X37: =U37*V37*W37 -> 0 | Y37: =T37+X37 -> 0 | Z37: 0 | AA37: 0 | AB37: 0 | AC37: =Z37*AA37*AB37 -> 0 | AD37: 0 | AE37: 0 | AF37: 0 | AG37: =AD37*AE37*AF37 -> 0 | AH37: =AC37+AG37 -> 0 | AI37: =F37+G37+P37+Y37+AH37 -> 369.91 | AJ37: =AI37/E37 -> 0.48544619 | AK37: 43.1299 | AL37: 7.62 | AM37: 7.62 | AN37: 22.86 | AO37: 4.953 | AP37: 38.1 | AQ37: =SUM(AL37:AP37) -> 81.153 | AR37: =AK37+AQ37 -> 124.2829 | AS37: =E37-AR37 -> 637.7171
B38: 02/24 | C38: 173 | D38: ATLANTIS | E38: 1966 | F38: 836.44 | G38: 0 | H38: 0 | I38: 0 | J38: 0 | K38: =H38*I38*J38 -> 0 | L38: 0 | M38: 0 | N38: 0 | O38: =L38*M38*N38 -> 0 | P38: =K38+O38 -> 0 | Q38: 0 | R38: 0 | S38: 0 | T38: =Q38*R38*S38 -> 0 | U38: 0 | V38: 0 | W38: 0 | X38: =U38*V38*W38 -> 0 | Y38: =T38+X38 -> 0 | Z38: 0 | AA38: 0 | AB38: 0 | AC38: =Z38*AA38*AB38 -> 0 | AD38: 0 | AE38: 0 | AF38: 0 | AG38: =AD38*AE38*AF38 -> 0 | AH38: =AC38+AG38 -> 0 | AI38: =F38+G38+P38+Y38+AH38 -> 836.44 | AJ38: =AI38/E38 -> 0.4254527 | AK38: 124.2516 | AL38: 19.66 | AM38: 19.66 | AN38: 58.98 | AO38: 12.779 | AP38: 98.3 | AQ38: =SUM(AL38:AP38) -> 209.379 | AR38: =AK38+AQ38 -> 333.6306 | AS38: =E38-AR38 -> 1632.3694
B39: 02/24 | C39: 175 | D39: QUATRO ESTAÇÕES 509 | E39: 611 | F39: 279.94 | G39: 0 | H39: 0 | I39: 0 | J39: 0 | K39: =H39*I39*J39 -> 0 | L39: 0 | M39: 0 | N39: 0 | O39: =L39*M39*N39 -> 0 | P39: =K39+O39 -> 0 | Q39: 0 | R39: 0 | S39: 0 | T39: =Q39*R39*S39 -> 0 | U39: 0 | V39: 0 | W39: 0 | X39: =U39*V39*W39 -> 0 | Y39: =T39+X39 -> 0 | Z39: 0 | AA39: 0 | AB39: 0 | AC39: =Z39*AA39*AB39 -> 0 | AD39: 0 | AE39: 0 | AF39: 0 | AG39: =AD39*AE39*AF39 -> 0 | AH39: =AC39+AG39 -> 0 | AI39: =F39+G39+P39+Y39+AH39 -> 279.94 | AJ39: =AI39/E39 -> 0.45816694 | AK39: 36.4166 | AL39: 6.11 | AM39: 6.11 | AN39: 18.33 | AO39: 3.9715 | AP39: 30.55 | AQ39: =SUM(AL39:AP39) -> 65.0715 | AR39: =AK39+AQ39 -> 101.4881 | AS39: =E39-AR39 -> 509.5119
B40: 02/24 | C40: 174 | D40: QUATRO ESTAÇÕES 507 | E40: 551 | F40: 252.45 | G40: 0 | H40: 0 | I40: 0 | J40: 0 | K40: =H40*I40*J40 -> 0 | L40: 0 | M40: 0 | N40: 0 | O40: =L40*M40*N40 -> 0 | P40: =K40+O40 -> 0 | Q40: 0 | R40: 0 | S40: 0 | T40: =Q40*R40*S40 -> 0 | U40: 0 | V40: 0 | W40: 0 | X40: =U40*V40*W40 -> 0 | Y40: =T40+X40 -> 0 | Z40: 0 | AA40: 0 | AB40: 0 | AC40: =Z40*AA40*AB40 -> 0 | AD40: 0 | AE40: 0 | AF40: 0 | AG40: =AD40*AE40*AF40 -> 0 | AH40: =AC40+AG40 -> 0 | AI40: =F40+G40+P40+Y40+AH40 -> 252.45 | AJ40: =AI40/E40 -> 0.45816697 | AK40: 32.8405 | AL40: 5.51 | AM40: 5.51 | AN40: 16.53 | AO40: 3.5815 | AP40: 27.55 | AQ40: =SUM(AL40:AP40) -> 58.6815 | AR40: =AK40+AQ40 -> 91.522 | AS40: =E40-AR40 -> 459.478
B41: 02/24 | C41: 178 | D41: TAJ MAHAL | E41: 3053.58 | F41: 535.76 | G41: 0 | H41: 0 | I41: 0 | J41: 0 | K41: =H41*I41*J41 -> 0 | L41: 0 | M41: 0 | N41: 0 | O41: =L41*M41*N41 -> 0 | P41: =K41+O41 -> 0 | Q41: 0 | R41: 0 | S41: 0 | T41: =Q41*R41*S41 -> 0 | U41: 0 | V41: 0 | W41: 0 | X41: =U41*V41*W41 -> 0 | Y41: =T41+X41 -> 0 | Z41: 0 | AA41: 0 | AB41: 0 | AC41: =Z41*AA41*AB41 -> 0 | AD41: 0 | AE41: 0 | AF41: 0 | AG41: =AD41*AE41*AF41 -> 0 | AH41: =AC41+AG41 -> 0 | AI41: =F41+G41+P41+Y41+AH41 -> 535.76 | AJ41: =AI41/E41 -> 0.17545307 | AK41: 276.9602 | AL41: 30.5358 | AM41: 30.5358 | AN41: 91.6074 | AO41: 19.84827 | AP41: 0 | AQ41: =SUM(AL41:AP41) -> 172.52727 | AR41: =AK41+AQ41 -> 449.48747 | AS41: =E41-AR41 -> 2604.0925
B42: 02/24 | C42: 181 | D42: DIRECIONAL_ ÁGUA BRANCA_SOBRADINHO | E42: 23325.27 | F42: 0 | G42: 0 | H42: 0 | I42: 0 | J42: 0 | K42: =H42*I42*J42 -> 0 | L42: 0 | M42: 0 | N42: 0 | O42: =L42*M42*N42 -> 0 | P42: =K42+O42 -> 0 | Q42: 0 | R42: 0 | S42: 0 | T42: =Q42*R42*S42 -> 0 | U42: 0 | V42: 0 | W42: 0 | X42: =U42*V42*W42 -> 0 | Y42: =T42+X42 -> 0 | Z42: 0 | AA42: 0 | AB42: 0 | AC42: =Z42*AA42*AB42 -> 0 | AD42: 0 | AE42: 0 | AF42: 0 | AG42: =AD42*AE42*AF42 -> 0 | AH42: =AC42+AG42 -> 0 | AI42: =F42+G42+P42+Y42+AH42 -> 0 | AJ42: =AI42/E42 -> 0 | AK42: 2565.7797 | AL42: 233.2527 | AM42: 233.2527 | AN42: 699.7581 | AO42: 151.61425 | AP42: 0 | AQ42: =SUM(AL42:AP42) -> 1317.8778 | AR42: =AK42+AQ42 -> 3883.6575 | AS42: =E42-AR42 -> 19441.613
B43: 02/24 | C43: 182 | D43: DIRECIONAL_ ITAGUATINS_SAMAMBAIA | E43: 4018.49 | F43: 0 | G43: 0 | H43: 0 | I43: 0 | J43: 0 | K43: =H43*I43*J43 -> 0 | L43: 0 | M43: 0 | N43: 0 | O43: =L43*M43*N43 -> 0 | P43: =K43+O43 -> 0 | Q43: 0 | R43: 0 | S43: 0 | T43: =Q43*R43*S43 -> 0 | U43: 0 | V43: 0 | W43: 0 | X43: =U43*V43*W43 -> 0 | Y43: =T43+X43 -> 0 | Z43: 0 | AA43: 0 | AB43: 0 | AC43: =Z43*AA43*AB43 -> 0 | AD43: 0 | AE43: 0 | AF43: 0 | AG43: =AD43*AE43*AF43 -> 0 | AH43: =AC43+AG43 -> 0 | AI43: =F43+G43+P43+Y43+AH43 -> 0 | AJ43: =AI43/E43 -> 0 | AK43: 442.0339 | AL43: 40.1849 | AM43: 40.1849 | AN43: 120.5547 | AO43: 26.120185 | AP43: 200.9245 | AQ43: =SUM(AL43:AP43) -> 427.96918 | AR43: =AK43+AQ43 -> 870.00308 | AS43: =E43-AR43 -> 3148.4869
B44: 02/24 | C44: 184 | D44: DIRECIONAL_TAGUATINGA_SANTA MARIA | E44: 3891.25 | F44: 0 | G44: 0 | H44: 0 | I44: 0 | J44: 0 | K44: =H44*I44*J44 -> 0 | L44: 0 | M44: 0 | N44: 0 | O44: =L44*M44*N44 -> 0 | P44: =K44+O44 -> 0 | Q44: 0 | R44: 0 | S44: 0 | T44: =Q44*R44*S44 -> 0 | U44: 0 | V44: 0 | W44: 0 | X44: =U44*V44*W44 -> 0 | Y44: =T44+X44 -> 0 | Z44: 0 | AA44: 0 | AB44: 0 | AC44: =Z44*AA44*AB44 -> 0 | AD44: 0 | AE44: 0 | AF44: 0 | AG44: =AD44*AE44*AF44 -> 0 | AH44: =AC44+AG44 -> 0 | AI44: =F44+G44+P44+Y44+AH44 -> 0 | AJ44: =AI44/E44 -> 0 | AK44: 428.0375 | AL44: 38.9125 | AM44: 38.9125 | AN44: 116.7375 | AO44: 25.293125 | AP44: 0 | AQ44: =SUM(AL44:AP44) -> 219.85563 | AR44: =AK44+AQ44 -> 647.89313 | AS44: =E44-AR44 -> 3243.3569
B45: 02/24 | C45: 183 | D45: DIRECIONAL_ITAPEMA_PLANALTINA | E45: 4204.97 | F45: 0 | G45: 0 | H45: 0 | I45: 0 | J45: 0 | K45: =H45*I45*J45 -> 0 | L45: 0 | M45: 0 | N45: 0 | O45: =L45*M45*N45 -> 0 | P45: =K45+O45 -> 0 | Q45: 0 | R45: 0 | S45: 0 | T45: =Q45*R45*S45 -> 0 | U45: 0 | V45: 0 | W45: 0 | X45: =U45*V45*W45 -> 0 | Y45: =T45+X45 -> 0 | Z45: 0 | AA45: 0 | AB45: 0 | AC45: =Z45*AA45*AB45 -> 0 | AD45: 0 | AE45: 0 | AF45: 0 | AG45: =AD45*AE45*AF45 -> 0 | AH45: =AC45+AG45 -> 0 | AI45: =F45+G45+P45+Y45+AH45 -> 0 | AJ45: =AI45/E45 -> 0 | AK45: 462.5467 | AL45: 42.0497 | AM45: 42.0497 | AN45: 126.1491 | AO45: 27.332305 | AP45: 210.2485 | AQ45: =SUM(AL45:AP45) -> 447.82931 | AR45: =AK45+AQ45 -> 910.37601 | AS45: =E45-AR45 -> 3294.594
B46: 02/24 | C46: 186 | D46: INDÚSTRIAS ROSSI | E46: 5193.28 | F46: 0 | G46: 0 | H46: 0 | I46: 0 | J46: 0 | K46: =H46*I46*J46 -> 0 | L46: 0 | M46: 0 | N46: 0 | O46: =L46*M46*N46 -> 0 | P46: =K46+O46 -> 0 | Q46: 0 | R46: 0 | S46: 0 | T46: =Q46*R46*S46 -> 0 | U46: 0 | V46: 0 | W46: 0 | X46: =U46*V46*W46 -> 0 | Y46: =T46+X46 -> 0 | Z46: 0 | AA46: 0 | AB46: 0 | AC46: =Z46*AA46*AB46 -> 0 | AD46: 0 | AE46: 0 | AF46: 0 | AG46: =AD46*AE46*AF46 -> 0 | AH46: =AC46+AG46 -> 0 | AI46: =F46+G46+P46+Y46+AH46 -> 0 | AJ46: =AI46/E46 -> 0 | AK46: 571.2608 | AL46: 51.9328 | AM46: 51.9328 | AN46: 155.7984 | AO46: 33.75632 | AP46: 259.664 | AQ46: =SUM(AL46:AP46) -> 553.08432 | AR46: =AK46+AQ46 -> 1124.3451 | AS46: =E46-AR46 -> 4068.9349
... B49: 03/24 | C49: 189 | D49: VANESSA | E49: 5562 | F49: 911.65 | G49: 187.41667 | H49: 1 | I49: 16 | J49: 26 | K49: =H49*I49*J49 -> 416 | L49: 0 | M49: 0 | N49: 0 | O49: =L49*M49*N49 -> 0 | P49: =K49+O49 -> 416 | Q49: 1 | R49: 42.5 | S49: 26 | T49: =Q49*R49*S49 -> 1105 | U49: 0 | V49: 0 | W49: 0 | X49: =U49*V49*W49 -> 0 | Y49: =T49+X49 -> 1105 | Z49: 1 | AA49: 80 | AB49: 1 | AC49: =Z49*AA49*AB49 -> 80 | AD49: 0 | AE49: 0 | AF49: 0 | AG49: =AD49*AE49*AF49 -> 0 | AH49: =AC49+AG49 -> 80 | AI49: =F49+G49+P49+Y49+AH49 -> 2700.0667 | AJ49: =AI49/E49 -> 0.48544888 | AK49: 314.81267 | AL49: 55.62 | AM49: 55.62 | AN49: 166.86 | AO49: 36.153 | AP49: 278.1 | AQ49: =SUM(AL49:AP49) -> 592.353 | AR49: =AK49+AQ49 -> 907.16567 | AS49: =E49-AR49 -> 4654.8343
B50: 03/24 | C50: 190 | D50: ATLANTIS | E50: 26266 | F50: 3822 | G50: 0 | H50: 3 | I50: 16 | J50: 26 | K50: =H50*I50*J50 -> 1248 | L50: 2 | M50: 16 | N50: =16+4 -> 20 | O50: =L50*M50*N50 -> 640 | P50: =K50+O50 -> 1888 | Q50: 3 | R50: 42.5 | S50: 26 | T50: =Q50*R50*S50 -> 3315 | U50: 2 | V50: 42.5 | W50: =16+4 -> 20 | X50: =U50*V50*W50 -> 1700 | Y50: =T50+X50 -> 5015 | Z50: 3 | AA50: 60 | AB50: 1 | AC50: =Z50*AA50*AB50 -> 180 | AD50: 3 | AE50: 90 | AF50: 1 | AG50: =AD50*AE50*AF50 -> 270 | AH50: =AC50+AG50 -> 450 | AI50: =F50+G50+P50+Y50+AH50 -> 11175 | AJ50: =AI50/E50 -> 0.42545496 | AK50: 1660.01 | AL50: 262.66 | AM50: 262.66 | AN50: 787.98 | AO50: 170.729 | AP50: 1313.3 | AQ50: =SUM(AL50:AP50) -> 2797.329 | AR50: =AK50+AQ50 -> 4457.339 | AS50: =E50-AR50 -> 21808.661
B51: 03/24 | C51: 191 | D51: QUATRO ESTAÇÕES 509 | E51: 5810 | F51: 710.95 | G51: 350 | H51: 1 | I51: 16 | J51: 26 | K51: =H51*I51*J51 -> 416 | L51: 0 | M51: 0 | N51: 0 | O51: =L51*M51*N51 -> 0 | P51: =K51+O51 -> 416 | Q51: 1 | R51: 42.5 | S51: 26 | T51: =Q51*R51*S51 -> 1105 | U51: 0 | V51: 0 | W51: 0 | X51: =U51*V51*W51 -> 0 | Y51: =T51+X51 -> 1105 | Z51: 1 | AA51: 80 | AB51: 1 | AC51: =Z51*AA51*AB51 -> 80 | AD51: 0 | AE51: 0 | AF51: 0 | AG51: =AD51*AE51*AF51 -> 0 | AH51: =AC51+AG51 -> 80 | AI51: =F51+G51+P51+Y51+AH51 -> 2661.95 | AJ51: =AI51/E51 -> 0.45816695 | AK51: 346.2855 | AL51: 58.1 | AM51: 58.1 | AN51: 174.3 | AO51: 37.765 | AP51: 290.5 | AQ51: =SUM(AL51:AP51) -> 618.765 | AR51: =AK51+AQ51 -> 965.0505 | AS51: =E51-AR51 -> 4844.9495
B52: 03/24 | C52: 192 | D52: QUATRO ESTAÇÕES 507 | E52: 5928 | F52: 898.55 | G52: 216.5 | H52: 1 | I52: 16 | J52: 26 | K52: =H52*I52*J52 -> 416 | L52: 0 | M52: 0 | N52: 0 | O52: =L52*M52*N52 -> 0 | P52: =K52+O52 -> 416 | Q52: 1 | R52: 42.5 | S52: 26 | T52: =Q52*R52*S52 -> 1105 | U52: 0 | V52: 0 | W52: 0 | X52: =U52*V52*W52 -> 0 | Y52: =T52+X52 -> 1105 | Z52: 1 | AA52: 80 | AB52: 1 | AC52: =Z52*AA52*AB52 -> 80 | AD52: 0 | AE52: 0 | AF52: 0 | AG52: =AD52*AE52*AF52 -> 0 | AH52: =AC52+AG52 -> 80 | AI52: =F52+G52+P52+Y52+AH52 -> 2716.05 | AJ52: =AI52/E52 -> 0.45817308 | AK52: 353.3145 | AL52: 59.28 | AM52: 59.28 | AN52: 177.84 | AO52: 38.532 | AP52: 296.4 | AQ52: =SUM(AL52:AP52) -> 631.332 | AR52: =AK52+AQ52 -> 984.6465 | AS52: =E52-AR52 -> 4943.3535
B53: 03/24 | C53: 193 | D53: TAJ MAHAL | E53: 36840 | F53: 2809.7 | G53: 0 | H53: 1 | I53: 16 | J53: 26 | K53: =H53*I53*J53 -> 416 | L53: 2 | M53: 24 | N53: 16 | O53: =L53*M53*N53 -> 768 | P53: =K53+O53 -> 1184 | Q53: 4 | R53: 20 | S53: 22 | T53: =Q53*R53*S53 -> 1760 | U53: 2 | V53: 20 | W53: 15.5 | X53: =U53*V53*W53 -> 620 | Y53: =T53+X53 -> 2380 | Z53: 4 | AA53: =90/12 -> 7.5 | AB53: 2 | AC53: =Z53*AA53*AB53 -> 60 | AD53: 2 | AE53: =90/12 -> 7.5 | AF53: 2 | AG53: =AD53*AE53*AF53 -> 30 | AH53: =AC53+AG53 -> 90 | AI53: =F53+G53+P53+Y53+AH53 -> 6463.7 | AJ53: =AI53/E53 -> 0.17545331 | AK53: 3341.393 | AL53: 368.4 | AM53: 368.4 | AN53: 1105.2 | AO53: 239.46 | AP53: 0 | AQ53: =SUM(AL53:AP53) -> 2081.46 | AR53: =AK53+AQ53 -> 5422.853 | AS53: =E53-AR53 -> 31417.147
B54: 03/24 | C54: 194 | D54: DIRECIONAL_ ÁGUA BRANCA_SOBRADINHO | E54: 14542.32 | F54: 0 | G54: 0 | H54: 0 | I54: 0 | J54: 0 | K54: =H54*I54*J54 -> 0 | L54: 0 | M54: 0 | N54: 0 | O54: =L54*M54*N54 -> 0 | P54: =K54+O54 -> 0 | Q54: 0 | R54: 0 | S54: 0 | T54: =Q54*R54*S54 -> 0 | U54: 0 | V54: 0 | W54: 0 | X54: =U54*V54*W54 -> 0 | Y54: =T54+X54 -> 0 | Z54: 0 | AA54: 0 | AB54: 0 | AC54: =Z54*AA54*AB54 -> 0 | AD54: 0 | AE54: 0 | AF54: 0 | AG54: =AD54*AE54*AF54 -> 0 | AH54: =AC54+AG54 -> 0 | AI54: =F54+G54+P54+Y54+AH54 -> 0 | AJ54: =AI54/E54 -> 0 | AK54: 1599.6552 | AL54: 145.4232 | AM54: 145.4232 | AN54: 436.2696 | AO54: 94.52508 | AP54: 0 | AQ54: =SUM(AL54:AP54) -> 821.64108 | AR54: =AK54+AQ54 -> 2421.2963 | AS54: =E54-AR54 -> 12121.024
B55: 03/24 | C55: 195 | D55: DIRECIONAL_ ITAGUATINS_SAMAMBAIA | E55: 4018.49 | F55: 0 | G55: 0 | H55: 0 | I55: 0 | J55: 0 | K55: =H55*I55*J55 -> 0 | L55: 0 | M55: 0 | N55: 0 | O55: =L55*M55*N55 -> 0 | P55: =K55+O55 -> 0 | Q55: 0 | R55: 0 | S55: 0 | T55: =Q55*R55*S55 -> 0 | U55: 0 | V55: 0 | W55: 0 | X55: =U55*V55*W55 -> 0 | Y55: =T55+X55 -> 0 | Z55: 0 | AA55: 0 | AB55: 0 | AC55: =Z55*AA55*AB55 -> 0 | AD55: 0 | AE55: 0 | AF55: 0 | AG55: =AD55*AE55*AF55 -> 0 | AH55: =AC55+AG55 -> 0 | AI55: =F55+G55+P55+Y55+AH55 -> 0 | AJ55: =AI55/E55 -> 0 | AK55: 442.0339 | AL55: 40.1849 | AM55: 40.1849 | AN55: 120.5547 | AO55: 26.120185 | AP55: 200.9245 | AQ55: =SUM(AL55:AP55) -> 427.96918 | AR55: =AK55+AQ55 -> 870.00308 | AS55: =E55-AR55 -> 3148.4869
B56: 03/24 | C56: 196 | D56: DIRECIONAL_TAGUATINGA_SANTA MARIA | E56: 3922.57 | F56: 0 | G56: 0 | H56: 0 | I56: 0 | J56: 0 | K56: =H56*I56*J56 -> 0 | L56: 0 | M56: 0 | N56: 0 | O56: =L56*M56*N56 -> 0 | P56: =K56+O56 -> 0 | Q56: 0 | R56: 0 | S56: 0 | T56: =Q56*R56*S56 -> 0 | U56: 0 | V56: 0 | W56: 0 | X56: =U56*V56*W56 -> 0 | Y56: =T56+X56 -> 0 | Z56: 0 | AA56: 0 | AB56: 0 | AC56: =Z56*AA56*AB56 -> 0 | AD56: 0 | AE56: 0 | AF56: 0 | AG56: =AD56*AE56*AF56 -> 0 | AH56: =AC56+AG56 -> 0 | AI56: =F56+G56+P56+Y56+AH56 -> 0 | AJ56: =AI56/E56 -> 0 | AK56: 431.4827 | AL56: 39.2257 | AM56: 39.2257 | AN56: 117.6771 | AO56: 25.496705 | AP56: 0 | AQ56: =SUM(AL56:AP56) -> 221.6252 | AR56: =AK56+AQ56 -> 653.10791 | AS56: =E56-AR56 -> 3269.4621
B57: 03/24 | C57: 197 | D57: DIRECIONAL_ITAPEMA_PLANALTINA | E57: 4304.06 | F57: 0 | G57: 0 | H57: 0 | I57: 0 | J57: 0 | K57: =H57*I57*J57 -> 0 | L57: 0 | M57: 0 | N57: 0 | O57: =L57*M57*N57 -> 0 | P57: =K57+O57 -> 0 | Q57: 0 | R57: 0 | S57: 0 | T57: =Q57*R57*S57 -> 0 | U57: 0 | V57: 0 | W57: 0 | X57: =U57*V57*W57 -> 0 | Y57: =T57+X57 -> 0 | Z57: 0 | AA57: 0 | AB57: 0 | AC57: =Z57*AA57*AB57 -> 0 | AD57: 0 | AE57: 0 | AF57: 0 | AG57: =AD57*AE57*AF57 -> 0 | AH57: =AC57+AG57 -> 0 | AI57: =F57+G57+P57+Y57+AH57 -> 0 | AJ57: =AI57/E57 -> 0 | AK57: 473.4466 | AL57: 43.0406 | AM57: 43.0406 | AN57: 129.1218 | AO57: 27.97639 | AP57: 215.203 | AQ57: =SUM(AL57:AP57) -> 458.38239 | AR57: =AK57+AQ57 -> 931.82899 | AS57: =E57-AR57 -> 3372.231
B58: 03/24 | C58: 198 | D58: INDÚSTRIAS ROSSI | E58: 6695.1 | F58: 0 | G58: 0 | H58: 0 | I58: 0 | J58: 0 | K58: =H58*I58*J58 -> 0 | L58: 0 | M58: 0 | N58: 0 | O58: =L58*M58*N58 -> 0 | P58: =K58+O58 -> 0 | Q58: 0 | R58: 0 | S58: 0 | T58: =Q58*R58*S58 -> 0 | U58: 0 | V58: 0 | W58: 0 | X58: =U58*V58*W58 -> 0 | Y58: =T58+X58 -> 0 | Z58: 0 | AA58: 0 | AB58: 0 | AC58: =Z58*AA58*AB58 -> 0 | AD58: 0 | AE58: 0 | AF58: 0 | AG58: =AD58*AE58*AF58 -> 0 | AH58: =AC58+AG58 -> 0 | AI58: =F58+G58+P58+Y58+AH58 -> 0 | AJ58: =AI58/E58 -> 0 | AK58: 736.461 | AL58: 66.951 | AM58: 66.951 | AN58: 200.853 | AO58: 43.51815 | AP58: 334.755 | AQ58: =SUM(AL58:AP58) -> 713.02815 | AR58: =AK58+AQ58 -> 1449.4892 | AS58: =E58-AR58 -> 5245.6109
B59: 04/24 | C59: 199 | D59: AHSERC | E59: 5928 | F59: 950.61 | G59: 326.16667 | H59: 1 | I59: 16 | J59: 26 | K59: =H59*I59*J59 -> 416 | L59: 0 | M59: 0 | N59: 0 | O59: =L59*M59*N59 -> 0 | P59: =K59+O59 -> 416 | Q59: 1 | R59: 42.5 | S59: 26 | T59: =Q59*R59*S59 -> 1105 | U59: 0 | V59: 0 | W59: 0 | X59: =U59*V59*W59 -> 0 | Y59: =T59+X59 -> 1105 | Z59: 1 | AA59: 80 | AB59: 1 | AC59: =Z59*AA59*AB59 -> 80 | AD59: 0 | AE59: 0 | AF59: 0 | AG59: =AD59*AE59*AF59 -> 0 | AH59: =AC59+AG59 -> 80 | AI59: =F59+G59+P59+Y59+AH59 -> 2877.7767 | AJ59: =AI59/E59 -> 0.4854549 | AK59: 335.52457 | AL59: 59.28 | AM59: 59.28 | AN59: 177.84 | AO59: 38.532 | AP59: 296.4 | AQ59: =SUM(AL59:AP59) -> 631.332 | AR59: =AK59+AQ59 -> 966.85657 | AS59: =E59-AR59 -> 4961.1434
B60: 04/24 | C60: 200 | D60: RIO PARANÃ | E60: 16252 | F60: 2331.4 | G60: 300 | H60: 1 | I60: 16 | J60: 26 | K60: =H60*I60*J60 -> 416 | L60: 2 | M60: 16 | N60: 16 | O60: =L60*M60*N60 -> 512 | P60: =K60+O60 -> 928 | Q60: 1 | R60: 42.5 | S60: 26 | T60: =Q60*R60*S60 -> 1105 | U60: 2 | V60: 42.5 | W60: 16 | X60: =U60*V60*W60 -> 1360 | Y60: =T60+X60 -> 2465 | Z60: 1 | AA60: 80 | AB60: 1 | AC60: =Z60*AA60*AB60 -> 80 | AD60: 2 | AE60: 80 | AF60: 1 | AG60: =AD60*AE60*AF60 -> 160 | AH60: =AC60+AG60 -> 240 | AI60: =F60+G60+P60+Y60+AH60 -> 6264.4 | AJ60: =AI60/E60 -> 0.3854541 | AK60: 1098.636 | AL60: 162.52 | AM60: 162.52 | AN60: 487.56 | AO60: 105.638 | AP60: 812.6 | AQ60: =SUM(AL60:AP60) -> 1730.838 | AR60: =AK60+AQ60 -> 2829.474 | AS60: =E60-AR60 -> 13422.526
B61: 04/24 | C61: 201 | D61: VANESSA | E61: 5562 | F61: 911.65 | G61: 187.41667 | H61: 1 | I61: 16 | J61: 26 | K61: =H61*I61*J61 -> 416 | L61: 0 | M61: 0 | N61: 0 | O61: =L61*M61*N61 -> 0 | P61: =K61+O61 -> 416 | Q61: 1 | R61: 42.5 | S61: 26 | T61: =Q61*R61*S61 -> 1105 | U61: 0 | V61: 0 | W61: 0 | X61: =U61*V61*W61 -> 0 | Y61: =T61+X61 -> 1105 | Z61: 1 | AA61: 80 | AB61: 1 | AC61: =Z61*AA61*AB61 -> 80 | AD61: 0 | AE61: 0 | AF61: 0 | AG61: =AD61*AE61*AF61 -> 0 | AH61: =AC61+AG61 -> 80 | AI61: =F61+G61+P61+Y61+AH61 -> 2700.0667 | AJ61: =AI61/E61 -> 0.48544888 | AK61: 314.81267 | AL61: 55.62 | AM61: 55.62 | AN61: 166.86 | AO61: 36.153 | AP61: 278.1 | AQ61: =SUM(AL61:AP61) -> 592.353 | AR61: =AK61+AQ61 -> 907.16567 | AS61: =E61-AR61 -> 4654.8343
B62: 04/24 | C62: 202 | D62: ATLANTIS | E62: =(26266/30)*7 -> 6128.7333 | F62: 110 | G62: 0 | H62: 3 | I62: 16 | J62: 7 | K62: =H62*I62*J62 -> 336 | L62: 2 | M62: 16 | N62: 7 | O62: =L62*M62*N62 -> 224 | P62: =K62+O62 -> 560 | Q62: 3 | R62: 42.5 | S62: 7 | T62: =Q62*R62*S62 -> 892.5 | U62: 2 | V62: 42.5 | W62: 7 | X62: =U62*V62*W62 -> 595 | Y62: =T62+X62 -> 1487.5 | Z62: 3 | AA62: 60 | AB62: 1 | AC62: =Z62*AA62*AB62 -> 180 | AD62: 3 | AE62: 90 | AF62: 1 | AG62: =AD62*AE62*AF62 -> 270 | AH62: =AC62+AG62 -> 450 | AI62: =F62+G62+P62+Y62+AH62 -> 2607.5 | AJ62: =AI62/E62 -> 0.42545496 | AK62: 387.33567 | AL62: 61.287333 | AM62: 61.287333 | AN62: 183.862 | AO62: 39.836767 | AP62: 306.43667 | AQ62: =SUM(AL62:AP62) -> 652.7101 | AR62: =AK62+AQ62 -> 1040.0458 | AS62: =E62-AR62 -> 5088.6876
B63: 04/24 | C63: 203 | D63: QUATRO ESTAÇÕES 509 | E63: 5810 | F63: 710.95 | G63: 350 | H63: 1 | I63: 16 | J63: 26 | K63: =H63*I63*J63 -> 416 | L63: 0 | M63: 0 | N63: 0 | O63: =L63*M63*N63 -> 0 | P63: =K63+O63 -> 416 | Q63: 1 | R63: 42.5 | S63: 26 | T63: =Q63*R63*S63 -> 1105 | U63: 0 | V63: 0 | W63: 0 | X63: =U63*V63*W63 -> 0 | Y63: =T63+X63 -> 1105 | Z63: 1 | AA63: 80 | AB63: 1 | AC63: =Z63*AA63*AB63 -> 80 | AD63: 0 | AE63: 0 | AF63: 0 | AG63: =AD63*AE63*AF63 -> 0 | AH63: =AC63+AG63 -> 80 | AI63: =F63+G63+P63+Y63+AH63 -> 2661.95 | AJ63: =AI63/E63 -> 0.45816695 | AK63: 346.2855 | AL63: 58.1 | AM63: 58.1 | AN63: 174.3 | AO63: 37.765 | AP63: 290.5 | AQ63: =SUM(AL63:AP63) -> 618.765 | AR63: =AK63+AQ63 -> 965.0505 | AS63: =E63-AR63 -> 4844.9495
B64: 04/24 | C64: 204 | D64: QUATRO ESTAÇÕES 507 | E64: 5928 | F64: 898.55 | G64: 216.5 | H64: 1 | I64: 16 | J64: 26 | K64: =H64*I64*J64 -> 416 | L64: 0 | M64: 0 | N64: 0 | O64: =L64*M64*N64 -> 0 | P64: =K64+O64 -> 416 | Q64: 1 | R64: 42.5 | S64: 26 | T64: =Q64*R64*S64 -> 1105 | U64: 0 | V64: 0 | W64: 0 | X64: =U64*V64*W64 -> 0 | Y64: =T64+X64 -> 1105 | Z64: 1 | AA64: 80 | AB64: 1 | AC64: =Z64*AA64*AB64 -> 80 | AD64: 0 | AE64: 0 | AF64: 0 | AG64: =AD64*AE64*AF64 -> 0 | AH64: =AC64+AG64 -> 80 | AI64: =F64+G64+P64+Y64+AH64 -> 2716.05 | AJ64: =AI64/E64 -> 0.45817308 | AK64: 353.3145 | AL64: 59.28 | AM64: 59.28 | AN64: 177.84 | AO64: 38.532 | AP64: 296.4 | AQ64: =SUM(AL64:AP64) -> 631.332 | AR64: =AK64+AQ64 -> 984.6465 | AS64: =E64-AR64 -> 4943.3535
B65: 04/24 | C65: 205 | D65: TAJ MAHAL | E65: 36840 | F65: 2809.7 | G65: 0 | H65: 1 | I65: 16 | J65: 26 | K65: =H65*I65*J65 -> 416 | L65: 2 | M65: 24 | N65: 16 | O65: =L65*M65*N65 -> 768 | P65: =K65+O65 -> 1184 | Q65: 4 | R65: 20 | S65: 22 | T65: =Q65*R65*S65 -> 1760 | U65: 2 | V65: 20 | W65: 15.5 | X65: =U65*V65*W65 -> 620 | Y65: =T65+X65 -> 2380 | Z65: 4 | AA65: =90/12 -> 7.5 | AB65: 2 | AC65: =Z65*AA65*AB65 -> 60 | AD65: 2 | AE65: =90/12 -> 7.5 | AF65: 2 | AG65: =AD65*AE65*AF65 -> 30 | AH65: =AC65+AG65 -> 90 | AI65: =F65+G65+P65+Y65+AH65 -> 6463.7 | AJ65: =AI65/E65 -> 0.17545331 | AK65: 3341.393 | AL65: 368.4 | AM65: 368.4 | AN65: 1105.2 | AO65: 239.46 | AP65: 0 | AQ65: =SUM(AL65:AP65) -> 2081.46 | AR65: =AK65+AQ65 -> 5422.853 | AS65: =E65-AR65 -> 31417.147
B66: 04/24 | C66: 206 | D66: DIRECIONAL_ CEILÂNDIA | E66: 4018.49 | F66: 0 | G66: 0 | H66: 0 | I66: 0 | J66: 0 | K66: =H66*I66*J66 -> 0 | L66: 0 | M66: 0 | N66: 0 | O66: =L66*M66*N66 -> 0 | P66: =K66+O66 -> 0 | Q66: 0 | R66: 0 | S66: 0 | T66: =Q66*R66*S66 -> 0 | U66: 0 | V66: 0 | W66: 0 | X66: =U66*V66*W66 -> 0 | Y66: =T66+X66 -> 0 | Z66: 0 | AA66: 0 | AB66: 0 | AC66: =Z66*AA66*AB66 -> 0 | AD66: 0 | AE66: 0 | AF66: 0 | AG66: =AD66*AE66*AF66 -> 0 | AH66: =AC66+AG66 -> 0 | AI66: =F66+G66+P66+Y66+AH66 -> 0 | AJ66: =AI66/E66 -> 0 | AK66: 442.0339 | AL66: 40.1849 | AM66: 40.1849 | AN66: 120.5547 | AO66: 26.120185 | AP66: 0 | AQ66: =SUM(AL66:AP66) -> 227.04468 | AR66: =AK66+AQ66 -> 669.07858 | AS66: =E66-AR66 -> 3349.4114
B67: 04/24 | C67: 207 | D67: DIRECIONAL_TAGUATINGA_SANTA MARIA | E67: 3804.21 | F67: 0 | G67: 0 | H67: 0 | I67: 0 | J67: 0 | K67: =H67*I67*J67 -> 0 | L67: 0 | M67: 0 | N67: 0 | O67: =L67*M67*N67 -> 0 | P67: =K67+O67 -> 0 | Q67: 0 | R67: 0 | S67: 0 | T67: =Q67*R67*S67 -> 0 | U67: 0 | V67: 0 | W67: 0 | X67: =U67*V67*W67 -> 0 | Y67: =T67+X67 -> 0 | Z67: 0 | AA67: 0 | AB67: 0 | AC67: =Z67*AA67*AB67 -> 0 | AD67: 0 | AE67: 0 | AF67: 0 | AG67: =AD67*AE67*AF67 -> 0 | AH67: =AC67+AG67 -> 0 | AI67: =F67+G67+P67+Y67+AH67 -> 0 | AJ67: =AI67/E67 -> 0 | AK67: 418.4631 | AL67: 38.0421 | AM67: 38.0421 | AN67: 114.1263 | AO67: 24.727365 | AP67: 0 | AQ67: =SUM(AL67:AP67) -> 214.93786 | AR67: =AK67+AQ67 -> 633.40097 | AS67: =E67-AR67 -> 3170.809
B68: 04/24 | C68: 208 | D68: DIRECIONAL_ITAPEMA_PLANALTINA | E68: 4369.29 | F68: 0 | G68: 0 | H68: 0 | I68: 0 | J68: 0 | K68: =H68*I68*J68 -> 0 | L68: 0 | M68: 0 | N68: 0 | O68: =L68*M68*N68 -> 0 | P68: =K68+O68 -> 0 | Q68: 0 | R68: 0 | S68: 0 | T68: =Q68*R68*S68 -> 0 | U68: 0 | V68: 0 | W68: 0 | X68: =U68*V68*W68 -> 0 | Y68: =T68+X68 -> 0 | Z68: 0 | AA68: 0 | AB68: 0 | AC68: =Z68*AA68*AB68 -> 0 | AD68: 0 | AE68: 0 | AF68: 0 | AG68: =AD68*AE68*AF68 -> 0 | AH68: =AC68+AG68 -> 0 | AI68: =F68+G68+P68+Y68+AH68 -> 0 | AJ68: =AI68/E68 -> 0 | AK68: 480.6219 | AL68: 43.6929 | AM68: 43.6929 | AN68: 131.0787 | AO68: 28.400385 | AP68: 218.4645 | AQ68: =SUM(AL68:AP68) -> 465.32939 | AR68: =AK68+AQ68 -> 945.95128 | AS68: =E68-AR68 -> 3423.3387
B69: 04/24 | C69: 209 | D69: INDÚSTRIAS ROSSI | E69: 6157.54 | F69: 0 | G69: 0 | H69: 0 | I69: 0 | J69: 0 | K69: =H69*I69*J69 -> 0 | L69: 0 | M69: 0 | N69: 0 | O69: =L69*M69*N69 -> 0 | P69: =K69+O69 -> 0 | Q69: 0 | R69: 0 | S69: 0 | T69: =Q69*R69*S69 -> 0 | U69: 0 | V69: 0 | W69: 0 | X69: =U69*V69*W69 -> 0 | Y69: =T69+X69 -> 0 | Z69: 0 | AA69: 0 | AB69: 0 | AC69: =Z69*AA69*AB69 -> 0 | AD69: 0 | AE69: 0 | AF69: 0 | AG69: =AD69*AE69*AF69 -> 0 | AH69: =AC69+AG69 -> 0 | AI69: =F69+G69+P69+Y69+AH69 -> 0 | AJ69: =AI69/E69 -> 0 | AK69: 677.3294 | AL69: 61.5754 | AM69: 61.5754 | AN69: 184.7262 | AO69: 40.02401 | AP69: 307.877 | AQ69: =SUM(AL69:AP69) -> 655.77801 | AR69: =AK69+AQ69 -> 1333.1074 | AS69: =E69-AR69 -> 4824.4326
B70: 05/24 | C70: 210 CANCELAR | D70: DIRECIONAL_ CEILÂNDIA | E70: 1149.74 | F70: 0 | G70: 0 | H70: 0 | I70: 0 | J70: 0 | K70: =H70*I70*J70 -> 0 | L70: 0 | M70: 0 | N70: 0 | O70: =L70*M70*N70 -> 0 | P70: =K70+O70 -> 0 | Q70: 0 | R70: 0 | S70: 0 | T70: =Q70*R70*S70 -> 0 | U70: 0 | V70: 0 | W70: 0 | X70: =U70*V70*W70 -> 0 | Y70: =T70+X70 -> 0 | Z70: 0 | AA70: 0 | AB70: 0 | AC70: =Z70*AA70*AB70 -> 0 | AD70: 0 | AE70: 0 | AF70: 0 | AG70: =AD70*AE70*AF70 -> 0 | AH70: =AC70+AG70 -> 0 | AI70: =F70+G70+P70+Y70+AH70 -> 0 | AJ70: =AI70/E70 -> 0 | AK70: 126.4714 | AL70: 11.4974 | AM70: 11.4974 | AN70: 34.4922 | AO70: 7.47331 | AP70: 0 | AQ70: =SUM(AL70:AP70) -> 64.96031 | AR70: =AK70+AQ70 -> 191.43171 | AS70: =E70-AR70 -> 958.30829
B71: 05/24 | C71: 217 | D71: AHSERC | E71: 5928 | F71: 950.61 | G71: 326.16667 | H71: 1 | I71: 16 | J71: 26 | K71: =H71*I71*J71 -> 416 | L71: 0 | M71: 0 | N71: 0 | O71: =L71*M71*N71 -> 0 | P71: =K71+O71 -> 416 | Q71: 1 | R71: 42.5 | S71: 26 | T71: =Q71*R71*S71 -> 1105 | U71: 0 | V71: 0 | W71: 0 | X71: =U71*V71*W71 -> 0 | Y71: =T71+X71 -> 1105 | Z71: 1 | AA71: 80 | AB71: 1 | AC71: =Z71*AA71*AB71 -> 80 | AD71: 0 | AE71: 0 | AF71: 0 | AG71: =AD71*AE71*AF71 -> 0 | AH71: =AC71+AG71 -> 80 | AI71: =F71+G71+P71+Y71+AH71 -> 2877.7767 | AJ71: =AI71/E71 -> 0.4854549 | AK71: 335.52457 | AL71: 59.28 | AM71: 59.28 | AN71: 177.84 | AO71: 38.532 | AP71: 296.4 | AQ71: =SUM(AL71:AP71) -> 631.332 | AR71: =AK71+AQ71 -> 966.85657 | AS71: =E71-AR71 -> 4961.1434
B72: 05/24 | C72: 218 | D72: RIO PARANÃ | E72: 16252 | F72: 2331.4 | G72: 300 | H72: 1 | I72: 16 | J72: 26 | K72: =H72*I72*J72 -> 416 | L72: 2 | M72: 16 | N72: 16 | O72: =L72*M72*N72 -> 512 | P72: =K72+O72 -> 928 | Q72: 1 | R72: 42.5 | S72: 26 | T72: =Q72*R72*S72 -> 1105 | U72: 2 | V72: 42.5 | W72: 16 | X72: =U72*V72*W72 -> 1360 | Y72: =T72+X72 -> 2465 | Z72: 1 | AA72: 80 | AB72: 1 | AC72: =Z72*AA72*AB72 -> 80 | AD72: 2 | AE72: 80 | AF72: 1 | AG72: =AD72*AE72*AF72 -> 160 | AH72: =AC72+AG72 -> 240 | AI72: =F72+G72+P72+Y72+AH72 -> 6264.4 | AJ72: =AI72/E72 -> 0.3854541 | AK72: 1098.636 | AL72: 162.52 | AM72: 162.52 | AN72: 487.56 | AO72: 105.638 | AP72: 812.6 | AQ72: =SUM(AL72:AP72) -> 1730.838 | AR72: =AK72+AQ72 -> 2829.474 | AS72: =E72-AR72 -> 13422.526
B73: 05/24 | C73: 219 | D73: VANESSA | E73: 5562 | F73: 911.65 | G73: 187.41667 | H73: 1 | I73: 16 | J73: 26 | K73: =H73*I73*J73 -> 416 | L73: 0 | M73: 0 | N73: 0 | O73: =L73*M73*N73 -> 0 | P73: =K73+O73 -> 416 | Q73: 1 | R73: 42.5 | S73: 26 | T73: =Q73*R73*S73 -> 1105 | U73: 0 | V73: 0 | W73: 0 | X73: =U73*V73*W73 -> 0 | Y73: =T73+X73 -> 1105 | Z73: 1 | AA73: 80 | AB73: 1 | AC73: =Z73*AA73*AB73 -> 80 | AD73: 0 | AE73: 0 | AF73: 0 | AG73: =AD73*AE73*AF73 -> 0 | AH73: =AC73+AG73 -> 80 | AI73: =F73+G73+P73+Y73+AH73 -> 2700.0667 | AJ73: =AI73/E73 -> 0.48544888 | AK73: 314.81267 | AL73: 55.62 | AM73: 55.62 | AN73: 166.86 | AO73: 36.153 | AP73: 278.1 | AQ73: =SUM(AL73:AP73) -> 592.353 | AR73: =AK73+AQ73 -> 907.16567 | AS73: =E73-AR73 -> 4654.8343
B74: 05/24 | C74: 221 | D74: QUATRO ESTAÇÕES 509 | E74: 5810 | F74: 710.95 | G74: 350 | H74: 1 | I74: 16 | J74: 26 | K74: =H74*I74*J74 -> 416 | L74: 0 | M74: 0 | N74: 0 | O74: =L74*M74*N74 -> 0 | P74: =K74+O74 -> 416 | Q74: 1 | R74: 42.5 | S74: 26 | T74: =Q74*R74*S74 -> 1105 | U74: 0 | V74: 0 | W74: 0 | X74: =U74*V74*W74 -> 0 | Y74: =T74+X74 -> 1105 | Z74: 1 | AA74: 80 | AB74: 1 | AC74: =Z74*AA74*AB74 -> 80 | AD74: 0 | AE74: 0 | AF74: 0 | AG74: =AD74*AE74*AF74 -> 0 | AH74: =AC74+AG74 -> 80 | AI74: =F74+G74+P74+Y74+AH74 -> 2661.95 | AJ74: =AI74/E74 -> 0.45816695 | AK74: 346.2855 | AL74: 58.1 | AM74: 58.1 | AN74: 174.3 | AO74: 37.765 | AP74: 290.5 | AQ74: =SUM(AL74:AP74) -> 618.765 | AR74: =AK74+AQ74 -> 965.0505 | AS74: =E74-AR74 -> 4844.9495
B75: 05/24 | C75: 222 | D75: QUATRO ESTAÇÕES 507 | E75: 5928 | F75: 898.55 | G75: 216.5 | H75: 1 | I75: 16 | J75: 26 | K75: =H75*I75*J75 -> 416 | L75: 0 | M75: 0 | N75: 0 | O75: =L75*M75*N75 -> 0 | P75: =K75+O75 -> 416 | Q75: 1 | R75: 42.5 | S75: 26 | T75: =Q75*R75*S75 -> 1105 | U75: 0 | V75: 0 | W75: 0 | X75: =U75*V75*W75 -> 0 | Y75: =T75+X75 -> 1105 | Z75: 1 | AA75: 80 | AB75: 1 | AC75: =Z75*AA75*AB75 -> 80 | AD75: 0 | AE75: 0 | AF75: 0 | AG75: =AD75*AE75*AF75 -> 0 | AH75: =AC75+AG75 -> 80 | AI75: =F75+G75+P75+Y75+AH75 -> 2716.05 | AJ75: =AI75/E75 -> 0.45817308 | AK75: 353.3145 | AL75: 59.28 | AM75: 59.28 | AN75: 177.84 | AO75: 38.532 | AP75: 296.4 | AQ75: =SUM(AL75:AP75) -> 631.332 | AR75: =AK75+AQ75 -> 984.6465 | AS75: =E75-AR75 -> 4943.3535
B76: 05/24 | C76: 223 | D76: TAJ MAHAL | E76: 36840 | F76: 2809.7 | G76: 0 | H76: 1 | I76: 16 | J76: 26 | K76: =H76*I76*J76 -> 416 | L76: 2 | M76: 24 | N76: 16 | O76: =L76*M76*N76 -> 768 | P76: =K76+O76 -> 1184 | Q76: 4 | R76: 20 | S76: 22 | T76: =Q76*R76*S76 -> 1760 | U76: 2 | V76: 20 | W76: 15.5 | X76: =U76*V76*W76 -> 620 | Y76: =T76+X76 -> 2380 | Z76: 4 | AA76: =90/12 -> 7.5 | AB76: 2 | AC76: =Z76*AA76*AB76 -> 60 | AD76: 2 | AE76: =90/12 -> 7.5 | AF76: 2 | AG76: =AD76*AE76*AF76 -> 30 | AH76: =AC76+AG76 -> 90 | AI76: =F76+G76+P76+Y76+AH76 -> 6463.7 | AJ76: =AI76/E76 -> 0.17545331 | AK76: 3341.393 | AL76: 368.4 | AM76: 368.4 | AN76: 1105.2 | AO76: 239.46 | AP76: 0 | AQ76: =SUM(AL76:AP76) -> 2081.46 | AR76: =AK76+AQ76 -> 5422.853 | AS76: =E76-AR76 -> 31417.147
B77: 05/24 | C77: 227 | D77: RPR27 | E77: 28588 | F77: 2968.35 | G77: 1600 | H77: 2 | I77: 16 | J77: 26 | K77: =H77*I77*J77 -> 832 | L77: 4 | M77: 16 | N77: 16 | O77: =L77*M77*N77 -> 1024 | P77: =K77+O77 -> 1856 | Q77: 2 | R77: 42.5 | S77: 22 | T77: =Q77*R77*S77 -> 1870 | U77: 4 | V77: 42.5 | W77: 15.5 | X77: =U77*V77*W77 -> 2635 | Y77: =T77+X77 -> 4505 | Z77: 2 | AA77: =90/12 -> 7.5 | AB77: 2 | AC77: =Z77*AA77*AB77 -> 30 | AD77: 4 | AE77: =90/12 -> 7.5 | AF77: 2 | AG77: =AD77*AE77*AF77 -> 60 | AH77: =AC77+AG77 -> 90 | AI77: =F77+G77+P77+Y77+AH77 -> 11019.35 | AJ77: =AI77/E77 -> 0.38545369 | AK77: 1932.5515 | AL77: 285.88 | AM77: 285.88 | AN77: 857.64 | AO77: 185.822 | AP77: 1429.4 | AQ77: =SUM(AL77:AP77) -> 3044.622 | AR77: =AK77+AQ77 -> 4977.1735 | AS77: =E77-AR77 -> 23610.826
B78: 05/24 | C78: 228 | D78: MONACO | E78: 2723 | F78: 247.4 | G78: 0 | H78: 1 | I78: 16 | J78: 17 | K78: =H78*I78*J78 -> 272 | L78: 0 | M78: 0 | N78: 0 | O78: =L78*M78*N78 -> 0 | P78: =K78+O78 -> 272 | Q78: 1 | R78: 42.5 | S78: 17 | T78: =Q78*R78*S78 -> 722.5 | U78: 0 | V78: 0 | W78: 0 | X78: =U78*V78*W78 -> 0 | Y78: =T78+X78 -> 722.5 | Z78: 1 | AA78: 80 | AB78: 1 | AC78: =Z78*AA78*AB78 -> 80 | AD78: 0 | AE78: 0 | AF78: 0 | AG78: =AD78*AE78*AF78 -> 0 | AH78: =AC78+AG78 -> 80 | AI78: =F78+G78+P78+Y78+AH78 -> 1321.9 | AJ78: 0.48544888 | AK78: 154.121 | AL78: 27.23 | AM78: 27.23 | AN78: 81.69 | AO78: 17.6995 | AP78: 0 | AQ78: =SUM(AL78:AP78) -> 153.8495 | AR78: =AK78+AQ78 -> 307.9705 | AS78: =E78-AR78 -> 2415.0295
B79: 06/24 | C79: 229 | D79: TAJ MAHAL CONSTRUÇÃO E INCORPORAÇÃO | E79: 1372 | F79: 472.7 | G79: 0 | H79: 1 | I79: 24 | J79: 4 | K79: =H79*I79*J79 -> 96 | L79: 0 | M79: 0 | N79: 0 | O79: =L79*M79*N79 -> 0 | P79: =K79+O79 -> 96 | Q79: 1 | R79: 21 | S79: 4 | T79: =Q79*R79*S79 -> 84 | U79: 0 | V79: 0 | W79: 0 | X79: =U79*V79*W79 -> 0 | Y79: =T79+X79 -> 84 | Z79: 1 | AA79: =80/12 -> 6.6666667 | AB79: 2 | AC79: =Z79*AA79*AB79 -> 13.333333 | AD79: 0 | AE79: 0 | AF79: 0 | AG79: =AD79*AE79*AF79 -> 0 | AH79: =AC79+AG79 -> 13.333333 | AI79: =F79+G79+P79+Y79+AH79 -> 666.03333 | AJ79: =AI79/E79 -> 0.48544704 | AK79: 77.656333 | AL79: 13.72 | AM79: 13.72 | AN79: 41.16 | AO79: 8.918 | AQ79: =SUM(AL79:AP79) -> 77.518 | AR79: =AK79+AQ79 -> 155.17433 | AS79: =E79-AR79 -> 1216.8257
B80: 06/24 | C80: 231 | D80: INDÚSTRIAS ROSSI | E80: 32480.511 | F80: 0 | G80: 0 | H80: 0 | I80: 0 | J80: 0 | K80: =H80*I80*J80 -> 0 | L80: 0 | M80: 0 | N80: 0 | O80: =L80*M80*N80 -> 0 | P80: =K80+O80 -> 0 | Q80: 0 | R80: 0 | S80: 0 | T80: =Q80*R80*S80 -> 0 | U80: 0 | V80: 0 | W80: 0 | X80: =U80*V80*W80 -> 0 | Y80: =T80+X80 -> 0 | Z80: 0 | AA80: 0 | AB80: 0 | AC80: =Z80*AA80*AB80 -> 0 | AD80: 0 | AE80: 0 | AF80: 0 | AG80: =AD80*AE80*AF80 -> 0 | AH80: =AC80+AG80 -> 0 | AI80: =F80+G80+P80+Y80+AH80 -> 0 | AJ80: =AI80/E80 -> 0 | AK80: 3572.8562 | AL80: 324.80511 | AM80: 324.80511 | AN80: 974.41532 | AO80: 211.12332 | AP80: 1624.0255 | AQ80: =SUM(AL80:AP80) -> 3459.1744 | AR80: =AK80+AQ80 -> 7032.0305 | AS80: =E80-AR80 -> 25448.48
B81: 06/24 | C81: 232 | D81: QUATRO ESTAÇÕES 507 | E81: 5928 | F81: 898.55 | G81: 216.5 | H81: 1 | I81: 16 | J81: 26 | K81: =H81*I81*J81 -> 416 | L81: 0 | M81: 0 | N81: 0 | O81: =L81*M81*N81 -> 0 | P81: =K81+O81 -> 416 | Q81: 1 | R81: 42.5 | S81: 26 | T81: =Q81*R81*S81 -> 1105 | U81: 0 | V81: 0 | W81: 0 | X81: =U81*V81*W81 -> 0 | Y81: =T81+X81 -> 1105 | Z81: 1 | AA81: 80 | AB81: 1 | AC81: =Z81*AA81*AB81 -> 80 | AD81: 0 | AE81: 0 | AF81: 0 | AG81: =AD81*AE81*AF81 -> 0 | AH81: =AC81+AG81 -> 80 | AI81: =F81+G81+P81+Y81+AH81 -> 2716.05 | AJ81: =AI81/E81 -> 0.45817308 | AK81: 353.3145 | AL81: 59.28 | AM81: 59.28 | AN81: 177.84 | AO81: 38.532 | AP81: 296.4 | AQ81: =SUM(AL81:AP81) -> 631.332 | AR81: =AK81+AQ81 -> 984.6465 | AS81: =E81-AR81 -> 4943.3535
B82: 06/24 | C82: 233 | D82: AHSERC | E82: 5928 | F82: 950.61 | G82: 326.16667 | H82: 1 | I82: 16 | J82: 26 | K82: =H82*I82*J82 -> 416 | L82: 0 | M82: 0 | N82: 0 | O82: =L82*M82*N82 -> 0 | P82: =K82+O82 -> 416 | Q82: 1 | R82: 42.5 | S82: 26 | T82: =Q82*R82*S82 -> 1105 | U82: 0 | V82: 0 | W82: 0 | X82: =U82*V82*W82 -> 0 | Y82: =T82+X82 -> 1105 | Z82: 1 | AA82: 80 | AB82: 1 | AC82: =Z82*AA82*AB82 -> 80 | AD82: 0 | AE82: 0 | AF82: 0 | AG82: =AD82*AE82*AF82 -> 0 | AH82: =AC82+AG82 -> 80 | AI82: =F82+G82+P82+Y82+AH82 -> 2877.7767 | AJ82: =AI82/E82 -> 0.4854549 | AK82: 335.52457 | AL82: 59.28 | AM82: 59.28 | AN82: 177.84 | AO82: 38.532 | AP82: 296.4 | AQ82: =SUM(AL82:AP82) -> 631.332 | AR82: =AK82+AQ82 -> 966.85657 | AS82: =E82-AR82 -> 4961.1434
B83: 06/24 | C83: 234 | D83: RIO PARANÃ | E83: 16252 | F83: 2331.4 | G83: 300 | H83: 1 | I83: 16 | J83: 26 | K83: =H83*I83*J83 -> 416 | L83: 2 | M83: 16 | N83: 16 | O83: =L83*M83*N83 -> 512 | P83: =K83+O83 -> 928 | Q83: 1 | R83: 42.5 | S83: 26 | T83: =Q83*R83*S83 -> 1105 | U83: 2 | V83: 42.5 | W83: 16 | X83: =U83*V83*W83 -> 1360 | Y83: =T83+X83 -> 2465 | Z83: 1 | AA83: 80 | AB83: 1 | AC83: =Z83*AA83*AB83 -> 80 | AD83: 2 | AE83: 80 | AF83: 1 | AG83: =AD83*AE83*AF83 -> 160 | AH83: =AC83+AG83 -> 240 | AI83: =F83+G83+P83+Y83+AH83 -> 6264.4 | AJ83: =AI83/E83 -> 0.3854541 | AK83: 1098.636 | AL83: 162.52 | AM83: 162.52 | AN83: 487.56 | AO83: 105.638 | AP83: 812.6 | AQ83: =SUM(AL83:AP83) -> 1730.838 | AR83: =AK83+AQ83 -> 2829.474 | AS83: =E83-AR83 -> 13422.526
B84: 06/24 | C84: 235 | D84: VANESSA | E84: 5562 | F84: 911.65 | G84: 187.41667 | H84: 1 | I84: 16 | J84: 26 | K84: =H84*I84*J84 -> 416 | L84: 0 | M84: 0 | N84: 0 | O84: =L84*M84*N84 -> 0 | P84: =K84+O84 -> 416 | Q84: 1 | R84: 42.5 | S84: 26 | T84: =Q84*R84*S84 -> 1105 | U84: 0 | V84: 0 | W84: 0 | X84: =U84*V84*W84 -> 0 | Y84: =T84+X84 -> 1105 | Z84: 1 | AA84: 80 | AB84: 1 | AC84: =Z84*AA84*AB84 -> 80 | AD84: 0 | AE84: 0 | AF84: 0 | AG84: =AD84*AE84*AF84 -> 0 | AH84: =AC84+AG84 -> 80 | AI84: =F84+G84+P84+Y84+AH84 -> 2700.0667 | AJ84: =AI84/E84 -> 0.48544888 | AK84: 314.81267 | AL84: 55.62 | AM84: 55.62 | AN84: 166.86 | AO84: 36.153 | AP84: 278.1 | AQ84: =SUM(AL84:AP84) -> 592.353 | AR84: =AK84+AQ84 -> 907.16567 | AS84: =E84-AR84 -> 4654.8343
B85: 06/24 | C85: 236 | D85: QUATRO ESTAÇÕES 509 | E85: 5810 | F85: 710.95 | G85: 350 | H85: 1 | I85: 16 | J85: 26 | K85: =H85*I85*J85 -> 416 | L85: 0 | M85: 0 | N85: 0 | O85: =L85*M85*N85 -> 0 | P85: =K85+O85 -> 416 | Q85: 1 | R85: 42.5 | S85: 26 | T85: =Q85*R85*S85 -> 1105 | U85: 0 | V85: 0 | W85: 0 | X85: =U85*V85*W85 -> 0 | Y85: =T85+X85 -> 1105 | Z85: 1 | AA85: 80 | AB85: 1 | AC85: =Z85*AA85*AB85 -> 80 | AD85: 0 | AE85: 0 | AF85: 0 | AG85: =AD85*AE85*AF85 -> 0 | AH85: =AC85+AG85 -> 80 | AI85: =F85+G85+P85+Y85+AH85 -> 2661.95 | AJ85: =AI85/E85 -> 0.45816695 | AK85: 346.2855 | AL85: 58.1 | AM85: 58.1 | AN85: 174.3 | AO85: 37.765 | AP85: 290.5 | AQ85: =SUM(AL85:AP85) -> 618.765 | AR85: =AK85+AQ85 -> 965.0505 | AS85: =E85-AR85 -> 4844.9495
B86: 06/24 | C86: 237 | D86: TAJ MAHAL | E86: 36840 | F86: 2809.7 | G86: 0 | H86: 1 | I86: 16 | J86: 26 | K86: =H86*I86*J86 -> 416 | L86: 2 | M86: 24 | N86: 16 | O86: =L86*M86*N86 -> 768 | P86: =K86+O86 -> 1184 | Q86: 4 | R86: 20 | S86: 22 | T86: =Q86*R86*S86 -> 1760 | U86: 2 | V86: 20 | W86: 15.5 | X86: =U86*V86*W86 -> 620 | Y86: =T86+X86 -> 2380 | Z86: 4 | AA86: =90/12 -> 7.5 | AB86: 2 | AC86: =Z86*AA86*AB86 -> 60 | AD86: 2 | AE86: =90/12 -> 7.5 | AF86: 2 | AG86: =AD86*AE86*AF86 -> 30 | AH86: =AC86+AG86 -> 90 | AI86: =F86+G86+P86+Y86+AH86 -> 6463.7 | AJ86: =AI86/E86 -> 0.17545331 | AK86: 3341.393 | AL86: 368.4 | AM86: 368.4 | AN86: 1105.2 | AO86: 239.46 | AP86: 0 | AQ86: =SUM(AL86:AP86) -> 2081.46 | AR86: =AK86+AQ86 -> 5422.853 | AS86: =E86-AR86 -> 31417.147
B87: 06/24 | C87: 238 | D87: RPR27 | E87: 28588 | F87: 2968.35 | G87: 1600 | H87: 2 | I87: 16 | J87: 26 | K87: =H87*I87*J87 -> 832 | L87: 4 | M87: 16 | N87: 16 | O87: =L87*M87*N87 -> 1024 | P87: =K87+O87 -> 1856 | Q87: 2 | R87: 42.5 | S87: 22 | T87: =Q87*R87*S87 -> 1870 | U87: 4 | V87: 42.5 | W87: 15.5 | X87: =U87*V87*W87 -> 2635 | Y87: =T87+X87 -> 4505 | Z87: 2 | AA87: =90/12 -> 7.5 | AB87: 2 | AC87: =Z87*AA87*AB87 -> 30 | AD87: 4 | AE87: =90/12 -> 7.5 | AF87: 2 | AG87: =AD87*AE87*AF87 -> 60 | AH87: =AC87+AG87 -> 90 | AI87: =F87+G87+P87+Y87+AH87 -> 11019.35 | AJ87: =AI87/E87 -> 0.38545369 | AK87: 1932.5515 | AL87: 285.88 | AM87: 285.88 | AN87: 857.64 | AO87: 185.822 | AP87: 1429.4 | AQ87: =SUM(AL87:AP87) -> 3044.622 | AR87: =AK87+AQ87 -> 4977.1735 | AS87: =E87-AR87 -> 23610.826
B88: 06/24 | C88: 240 | D88: TAJ MAHAL CONSTRUÇÃO E INCORPORAÇÃO | E88: 1372 | F88: 472.7 | G88: 0 | H88: 1 | I88: 24 | J88: 4 | K88: =H88*I88*J88 -> 96 | L88: 0 | M88: 0 | N88: 0 | O88: =L88*M88*N88 -> 0 | P88: =K88+O88 -> 96 | Q88: 1 | R88: 21 | S88: 4 | T88: =Q88*R88*S88 -> 84 | U88: 0 | V88: 0 | W88: 0 | X88: =U88*V88*W88 -> 0 | Y88: =T88+X88 -> 84 | Z88: 1 | AA88: =80/12 -> 6.6666667 | AB88: 2 | AC88: =Z88*AA88*AB88 -> 13.333333 | AD88: 0 | AE88: 0 | AF88: 0 | AG88: =AD88*AE88*AF88 -> 0 | AH88: =AC88+AG88 -> 13.333333 | AI88: =F88+G88+P88+Y88+AH88 -> 666.03333 | AJ88: =AI88/E88 -> 0.48544704 | AK88: 77.656333 | AL88: 13.72 | AM88: 13.72 | AN88: 41.16 | AO88: 8.918 | AQ88: =SUM(AL88:AP88) -> 77.518 | AR88: =AK88+AQ88 -> 155.17433 | AS88: =E88-AR88 -> 1216.8257
B89: 06/24 | C89: 241 | D89: INDÚSTRIAS ROSSI | E89: 41109.56 | F89: 0 | G89: 0 | H89: 0 | I89: 0 | J89: 0 | K89: =H89*I89*J89 -> 0 | L89: 0 | M89: 0 | N89: 0 | O89: =L89*M89*N89 -> 0 | P89: =K89+O89 -> 0 | Q89: 0 | R89: 0 | S89: 0 | T89: =Q89*R89*S89 -> 0 | U89: 0 | V89: 0 | W89: 0 | X89: =U89*V89*W89 -> 0 | Y89: =T89+X89 -> 0 | Z89: 0 | AA89: 0 | AB89: 0 | AC89: =Z89*AA89*AB89 -> 0 | AD89: 0 | AE89: 0 | AF89: 0 | AG89: =AD89*AE89*AF89 -> 0 | AH89: =AC89+AG89 -> 0 | AI89: =F89+G89+P89+Y89+AH89 -> 0 | AJ89: =AI89/E89 -> 0 | AK89: 4522.0516 | AL89: 411.0956 | AM89: 411.0956 | AN89: 1233.2868 | AO89: 267.21214 | AP89: 2055.478 | AQ89: =SUM(AL89:AP89) -> 4378.1681 | AR89: =AK89+AQ89 -> 8900.2197 | AS89: =E89-AR89 -> 32209.34
B90: 06/24 | C90: 242 | D90: MONACO | E90: 5446 | F90: 911.65 | G90: 131.08 | H90: 1 | I90: 16 | J90: 26 | K90: =H90*I90*J90 -> 416 | L90: 0 | M90: 0 | N90: 0 | O90: =L90*M90*N90 -> 0 | P90: =K90+O90 -> 416 | Q90: 1 | R90: 42.5 | S90: 26 | T90: =Q90*R90*S90 -> 1105 | U90: 0 | V90: 0 | W90: 0 | X90: =U90*V90*W90 -> 0 | Y90: =T90+X90 -> 1105 | Z90: 1 | AA90: 80 | AB90: 1 | AC90: =Z90*AA90*AB90 -> 80 | AD90: 0 | AE90: 0 | AF90: 0 | AG90: =AD90*AE90*AF90 -> 0 | AH90: =AC90+AG90 -> 80 | AI90: =F90+G90+P90+Y90+AH90 -> 2643.73 | AJ90: 0.48544888 | AK90: 308.2497 | AL90: 54.46 | AM90: 54.46 | AN90: 163.38 | AO90: 35.399 | AP90: 272.3 | AQ90: =SUM(AL90:AP90) -> 579.999 | AR90: =AK90+AQ90 -> 888.2487 | AS90: =E90-AR90 -> 4557.7513
B91: 07/24 | C91: 244 | D91: TAJ MAHAL CONSTRUÇÃO E INCORPORAÇÃO | E91: 1372 | F91: 472.7 | G91: 0 | H91: 1 | I91: 24 | J91: 4 | K91: =H91*I91*J91 -> 96 | L91: 0 | M91: 0 | N91: 0 | O91: =L91*M91*N91 -> 0 | P91: =K91+O91 -> 96 | Q91: 1 | R91: 21 | S91: 4 | T91: =Q91*R91*S91 -> 84 | U91: 0 | V91: 0 | W91: 0 | X91: =U91*V91*W91 -> 0 | Y91: =T91+X91 -> 84 | Z91: 1 | AA91: =80/12 -> 6.6666667 | AB91: 2 | AC91: =Z91*AA91*AB91 -> 13.333333 | AD91: 0 | AE91: 0 | AF91: 0 | AG91: =AD91*AE91*AF91 -> 0 | AH91: =AC91+AG91 -> 13.333333 | AI91: =F91+G91+P91+Y91+AH91 -> 666.03333 | AJ91: =AI91/E91 -> 0.48544704 | AK91: 77.656333 | AL91: 13.72 | AM91: 13.72 | AN91: 41.16 | AO91: 8.918 | AQ91: =SUM(AL91:AP91) -> 77.518 | AR91: =AK91+AQ91 -> 155.17433 | AS91: =E91-AR91 -> 1216.8257
B92: 07/24 | C92: 246 | D92: QUATRO ESTAÇÕES 507 | E92: 5928 | F92: 898.55 | G92: 216.5 | H92: 1 | I92: 16 | J92: 26 | K92: =H92*I92*J92 -> 416 | L92: 0 | M92: 0 | N92: 0 | O92: =L92*M92*N92 -> 0 | P92: =K92+O92 -> 416 | Q92: 1 | R92: 42.5 | S92: 26 | T92: =Q92*R92*S92 -> 1105 | U92: 0 | V92: 0 | W92: 0 | X92: =U92*V92*W92 -> 0 | Y92: =T92+X92 -> 1105 | Z92: 1 | AA92: 80 | AB92: 1 | AC92: =Z92*AA92*AB92 -> 80 | AD92: 0 | AE92: 0 | AF92: 0 | AG92: =AD92*AE92*AF92 -> 0 | AH92: =AC92+AG92 -> 80 | AI92: =F92+G92+P92+Y92+AH92 -> 2716.05 | AJ92: =AI92/E92 -> 0.45817308 | AK92: 353.3145 | AL92: 59.28 | AM92: 59.28 | AN92: 177.84 | AO92: 38.532 | AP92: 296.4 | AQ92: =SUM(AL92:AP92) -> 631.332 | AR92: =AK92+AQ92 -> 984.6465 | AS92: =E92-AR92 -> 4943.3535
B93: 07/24 | C93: 247 | D93: AHSERC | E93: 5928 | F93: 950.61 | G93: 326.16667 | H93: 1 | I93: 16 | J93: 26 | K93: =H93*I93*J93 -> 416 | L93: 0 | M93: 0 | N93: 0 | O93: =L93*M93*N93 -> 0 | P93: =K93+O93 -> 416 | Q93: 1 | R93: 42.5 | S93: 26 | T93: =Q93*R93*S93 -> 1105 | U93: 0 | V93: 0 | W93: 0 | X93: =U93*V93*W93 -> 0 | Y93: =T93+X93 -> 1105 | Z93: 1 | AA93: 80 | AB93: 1 | AC93: =Z93*AA93*AB93 -> 80 | AD93: 0 | AE93: 0 | AF93: 0 | AG93: =AD93*AE93*AF93 -> 0 | AH93: =AC93+AG93 -> 80 | AI93: =F93+G93+P93+Y93+AH93 -> 2877.7767 | AJ93: =AI93/E93 -> 0.4854549 | AK93: 335.52457 | AL93: 59.28 | AM93: 59.28 | AN93: 177.84 | AO93: 38.532 | AP93: 296.4 | AQ93: =SUM(AL93:AP93) -> 631.332 | AR93: =AK93+AQ93 -> 966.85657 | AS93: =E93-AR93 -> 4961.1434
B94: 07/24 | C94: 248 | D94: RIO PARANÃ | E94: 16252 | F94: 2331.4 | G94: 300 | H94: 1 | I94: 16 | J94: 26 | K94: =H94*I94*J94 -> 416 | L94: 2 | M94: 16 | N94: 16 | O94: =L94*M94*N94 -> 512 | P94: =K94+O94 -> 928 | Q94: 1 | R94: 42.5 | S94: 26 | T94: =Q94*R94*S94 -> 1105 | U94: 2 | V94: 42.5 | W94: 16 | X94: =U94*V94*W94 -> 1360 | Y94: =T94+X94 -> 2465 | Z94: 1 | AA94: 80 | AB94: 1 | AC94: =Z94*AA94*AB94 -> 80 | AD94: 2 | AE94: 80 | AF94: 1 | AG94: =AD94*AE94*AF94 -> 160 | AH94: =AC94+AG94 -> 240 | AI94: =F94+G94+P94+Y94+AH94 -> 6264.4 | AJ94: =AI94/E94 -> 0.3854541 | AK94: 1098.636 | AL94: 162.52 | AM94: 162.52 | AN94: 487.56 | AO94: 105.638 | AP94: 812.6 | AQ94: =SUM(AL94:AP94) -> 1730.838 | AR94: =AK94+AQ94 -> 2829.474 | AS94: =E94-AR94 -> 13422.526
B95: 07/24 | C95: 249 | D95: VANESSA | E95: 5562 | F95: 911.65 | G95: 187.41667 | H95: 1 | I95: 16 | J95: 26 | K95: =H95*I95*J95 -> 416 | L95: 0 | M95: 0 | N95: 0 | O95: =L95*M95*N95 -> 0 | P95: =K95+O95 -> 416 | Q95: 1 | R95: 42.5 | S95: 26 | T95: =Q95*R95*S95 -> 1105 | U95: 0 | V95: 0 | W95: 0 | X95: =U95*V95*W95 -> 0 | Y95: =T95+X95 -> 1105 | Z95: 1 | AA95: 80 | AB95: 1 | AC95: =Z95*AA95*AB95 -> 80 | AD95: 0 | AE95: 0 | AF95: 0 | AG95: =AD95*AE95*AF95 -> 0 | AH95: =AC95+AG95 -> 80 | AI95: =F95+G95+P95+Y95+AH95 -> 2700.0667 | AJ95: =AI95/E95 -> 0.48544888 | AK95: 314.81267 | AL95: 55.62 | AM95: 55.62 | AN95: 166.86 | AO95: 36.153 | AP95: 278.1 | AQ95: =SUM(AL95:AP95) -> 592.353 | AR95: =AK95+AQ95 -> 907.16567 | AS95: =E95-AR95 -> 4654.8343
B96: 07/24 | C96: 250 | D96: QUATRO ESTAÇÕES 509 | E96: 5810 | F96: 710.95 | G96: 350 | H96: 1 | I96: 16 | J96: 26 | K96: =H96*I96*J96 -> 416 | L96: 0 | M96: 0 | N96: 0 | O96: =L96*M96*N96 -> 0 | P96: =K96+O96 -> 416 | Q96: 1 | R96: 42.5 | S96: 26 | T96: =Q96*R96*S96 -> 1105 | U96: 0 | V96: 0 | W96: 0 | X96: =U96*V96*W96 -> 0 | Y96: =T96+X96 -> 1105 | Z96: 1 | AA96: 80 | AB96: 1 | AC96: =Z96*AA96*AB96 -> 80 | AD96: 0 | AE96: 0 | AF96: 0 | AG96: =AD96*AE96*AF96 -> 0 | AH96: =AC96+AG96 -> 80 | AI96: =F96+G96+P96+Y96+AH96 -> 2661.95 | AJ96: =AI96/E96 -> 0.45816695 | AK96: 346.2855 | AL96: 58.1 | AM96: 58.1 | AN96: 174.3 | AO96: 37.765 | AP96: 290.5 | AQ96: =SUM(AL96:AP96) -> 618.765 | AR96: =AK96+AQ96 -> 965.0505 | AS96: =E96-AR96 -> 4844.9495
B97: 07/24 | C97: 252 | D97: RPR27 | E97: 28588 | F97: 2968.35 | G97: 1600 | H97: 2 | I97: 16 | J97: 26 | K97: =H97*I97*J97 -> 832 | L97: 4 | M97: 16 | N97: 16 | O97: =L97*M97*N97 -> 1024 | P97: =K97+O97 -> 1856 | Q97: 2 | R97: 42.5 | S97: 22 | T97: =Q97*R97*S97 -> 1870 | U97: 4 | V97: 42.5 | W97: 15.5 | X97: =U97*V97*W97 -> 2635 | Y97: =T97+X97 -> 4505 | Z97: 2 | AA97: =90/12 -> 7.5 | AB97: 2 | AC97: =Z97*AA97*AB97 -> 30 | AD97: 4 | AE97: =90/12 -> 7.5 | AF97: 2 | AG97: =AD97*AE97*AF97 -> 60 | AH97: =AC97+AG97 -> 90 | AI97: =F97+G97+P97+Y97+AH97 -> 11019.35 | AJ97: =AI97/E97 -> 0.38545369 | AK97: 1932.5515 | AL97: 285.88 | AM97: 285.88 | AN97: 857.64 | AO97: 185.822 | AP97: 1429.4 | AQ97: =SUM(AL97:AP97) -> 3044.622 | AR97: =AK97+AQ97 -> 4977.1735 | AS97: =E97-AR97 -> 23610.826
B98: 07/24 | C98: 253 | D98: MONACO | E98: 5446 | F98: 911.65 | G98: 131.08 | H98: 1 | I98: 16 | J98: 26 | K98: =H98*I98*J98 -> 416 | L98: 0 | M98: 0 | N98: 0 | O98: =L98*M98*N98 -> 0 | P98: =K98+O98 -> 416 | Q98: 1 | R98: 42.5 | S98: 26 | T98: =Q98*R98*S98 -> 1105 | U98: 0 | V98: 0 | W98: 0 | X98: =U98*V98*W98 -> 0 | Y98: =T98+X98 -> 1105 | Z98: 1 | AA98: 80 | AB98: 1 | AC98: =Z98*AA98*AB98 -> 80 | AD98: 0 | AE98: 0 | AF98: 0 | AG98: =AD98*AE98*AF98 -> 0 | AH98: =AC98+AG98 -> 80 | AI98: =F98+G98+P98+Y98+AH98 -> 2643.73 | AJ98: 0.48544888 | AK98: 308.2497 | AL98: 54.46 | AM98: 54.46 | AN98: 163.38 | AO98: 35.399 | AP98: 272.3 | AQ98: =SUM(AL98:AP98) -> 579.999 | AR98: =AK98+AQ98 -> 888.2487 | AS98: =E98-AR98 -> 4557.7513
B99: 07/24 | C99: 254 | D99: TAJ MAHAL | E99: =37805-1750 -> 36055 | F99: 860 | G99: 0 | H99: 6 | I99: 16 | J99: 26 | K99: =H99*I99*J99 -> 2496 | L99: 0 | M99: 0 | N99: 0 | O99: =L99*M99*N99 -> 0 | P99: =K99+O99 -> 2496 | Q99: 6 | R99: 20 | S99: 24 | T99: =Q99*R99*S99 -> 2880 | U99: 0 | V99: 0 | W99: 0 | X99: =U99*V99*W99 -> 0 | Y99: =T99+X99 -> 2880 | Z99: 6 | AA99: =90/12 -> 7.5 | AB99: 2 | AC99: =Z99*AA99*AB99 -> 90 | AD99: 0 | AE99: 0 | AF99: 0 | AG99: =AD99*AE99*AF99 -> 0 | AH99: =AC99+AG99 -> 90 | AI99: =F99+G99+P99+Y99+AH99 -> 6326 | AJ99: =AI99/E99 -> 0.17545417 | AK99: 3270.19 | AL99: 360.55 | AM99: 360.55 | AN99: 1081.65 | AO99: 234.3575 | AQ99: =SUM(AL99:AP99) -> 2037.1075 | AR99: =AK99+AQ99 -> 5307.2975 | AS99: =E99-AR99 -> 30747.702
B100: 07/24 | C100: 255 | D100: INDÚSTRIAS ROSSI | E100: 47460.13 | F100: 0 | G100: 0 | H100: 0 | I100: 0 | J100: 0 | K100: =H100*I100*J100 -> 0 | L100: 0 | M100: 0 | N100: 0 | O100: =L100*M100*N100 -> 0 | P100: =K100+O100 -> 0 | Q100: 0 | R100: 0 | S100: 0 | T100: =Q100*R100*S100 -> 0 | U100: 0 | V100: 0 | W100: 0 | X100: =U100*V100*W100 -> 0 | Y100: =T100+X100 -> 0 | Z100: 0 | AA100: 0 | AB100: 0 | AC100: =Z100*AA100*AB100 -> 0 | AD100: 0 | AE100: 0 | AF100: 0 | AG100: =AD100*AE100*AF100 -> 0 | AH100: =AC100+AG100 -> 0 | AI100: =F100+G100+P100+Y100+AH100 -> 0 | AJ100: =AI100/E100 -> 0 | AK100: 5220.6143 | AL100: 474.6013 | AM100: 474.6013 | AN100: 1423.8039 | AO100: 308.49084 | AP100: 2373.0065 | AQ100: =SUM(AL100:AP100) -> 5054.5038 | AR100: =AK100+AQ100 -> 10275.118 | AS100: =E100-AR100 -> 37185.012
B101: 08/24 | C101: 257 | D101: TAJ MAHAL CONSTRUÇÃO E INCORPORAÇÃO | E101: 1372 | F101: 472.7 | G101: 0 | H101: 1 | I101: 24 | J101: 4 | K101: =H101*I101*J101 -> 96 | L101: 0 | M101: 0 | N101: 0 | O101: =L101*M101*N101 -> 0 | P101: =K101+O101 -> 96 | Q101: 1 | R101: 21 | S101: 4 | T101: =Q101*R101*S101 -> 84 | U101: 0 | V101: 0 | W101: 0 | X101: =U101*V101*W101 -> 0 | Y101: =T101+X101 -> 84 | Z101: 1 | AA101: =80/12 -> 6.6666667 | AB101: 2 | AC101: =Z101*AA101*AB101 -> 13.333333 | AD101: 0 | AE101: 0 | AF101: 0 | AG101: =AD101*AE101*AF101 -> 0 | AH101: =AC101+AG101 -> 13.333333 | AI101: =F101+G101+P101+Y101+AH101 -> 666.03333 | AJ101: =AI101/E101 -> 0.48544704 | AK101: 77.656333 | AL101: 13.72 | AM101: 13.72 | AN101: 41.16 | AO101: 8.918 | AQ101: =SUM(AL101:AP101) -> 77.518 | AR101: =AK101+AQ101 -> 155.17433 | AS101: =E101-AR101 -> 1216.8257
B102: 08/24 | C102: 258 | D102: QUATRO ESTAÇÕES 507 | E102: 5928 | F102: 898.55 | G102: 216.5 | H102: 1 | I102: 16 | J102: 26 | K102: =H102*I102*J102 -> 416 | L102: 0 | M102: 0 | N102: 0 | O102: =L102*M102*N102 -> 0 | P102: =K102+O102 -> 416 | Q102: 1 | R102: 42.5 | S102: 26 | T102: =Q102*R102*S102 -> 1105 | U102: 0 | V102: 0 | W102: 0 | X102: =U102*V102*W102 -> 0 | Y102: =T102+X102 -> 1105 | Z102: 1 | AA102: 80 | AB102: 1 | AC102: =Z102*AA102*AB102 -> 80 | AD102: 0 | AE102: 0 | AF102: 0 | AG102: =AD102*AE102*AF102 -> 0 | AH102: =AC102+AG102 -> 80 | AI102: =F102+G102+P102+Y102+AH102 -> 2716.05 | AJ102: =AI102/E102 -> 0.45817308 | AK102: 353.3145 | AL102: 59.28 | AM102: 59.28 | AN102: 177.84 | AO102: 38.532 | AP102: 296.4 | AQ102: =SUM(AL102:AP102) -> 631.332 | AR102: =AK102+AQ102 -> 984.6465 | AS102: =E102-AR102 -> 4943.3535
B103: 08/24 | C103: 259 | D103: AHSERC | E103: 5928 | F103: 950.61 | G103: 326.16667 | H103: 1 | I103: 16 | J103: 26 | K103: =H103*I103*J103 -> 416 | L103: 0 | M103: 0 | N103: 0 | O103: =L103*M103*N103 -> 0 | P103: =K103+O103 -> 416 | Q103: 1 | R103: 42.5 | S103: 26 | T103: =Q103*R103*S103 -> 1105 | U103: 0 | V103: 0 | W103: 0 | X103: =U103*V103*W103 -> 0 | Y103: =T103+X103 -> 1105 | Z103: 1 | AA103: 80 | AB103: 1 | AC103: =Z103*AA103*AB103 -> 80 | AD103: 0 | AE103: 0 | AF103: 0 | AG103: =AD103*AE103*AF103 -> 0 | AH103: =AC103+AG103 -> 80 | AI103: =F103+G103+P103+Y103+AH103 -> 2877.7767 | AJ103: =AI103/E103 -> 0.4854549 | AK103: 335.52457 | AL103: 59.28 | AM103: 59.28 | AN103: 177.84 | AO103: 38.532 | AP103: 296.4 | AQ103: =SUM(AL103:AP103) -> 631.332 | AR103: =AK103+AQ103 -> 966.85657 | AS103: =E103-AR103 -> 4961.1434
B104: 08/24 | C104: 260 | D104: RIO PARANÃ | E104: 16252 | F104: 2331.4 | G104: 300 | H104: 1 | I104: 16 | J104: 26 | K104: =H104*I104*J104 -> 416 | L104: 2 | M104: 16 | N104: 16 | O104: =L104*M104*N104 -> 512 | P104: =K104+O104 -> 928 | Q104: 1 | R104: 42.5 | S104: 26 | T104: =Q104*R104*S104 -> 1105 | U104: 2 | V104: 42.5 | W104: 16 | X104: =U104*V104*W104 -> 1360 | Y104: =T104+X104 -> 2465 | Z104: 1 | AA104: 80 | AB104: 1 | AC104: =Z104*AA104*AB104 -> 80 | AD104: 2 | AE104: 80 | AF104: 1 | AG104: =AD104*AE104*AF104 -> 160 | AH104: =AC104+AG104 -> 240 | AI104: =F104+G104+P104+Y104+AH104 -> 6264.4 | AJ104: =AI104/E104 -> 0.3854541 | AK104: 1098.636 | AL104: 162.52 | AM104: 162.52 | AN104: 487.56 | AO104: 105.638 | AP104: 812.6 | AQ104: =SUM(AL104:AP104) -> 1730.838 | AR104: =AK104+AQ104 -> 2829.474 | AS104: =E104-AR104 -> 13422.526
B105: 08/24 | C105: 261 | D105: VANESSA | E105: 5562 | F105: 911.65 | G105: 187.41667 | H105: 1 | I105: 16 | J105: 26 | K105: =H105*I105*J105 -> 416 | L105: 0 | M105: 0 | N105: 0 | O105: =L105*M105*N105 -> 0 | P105: =K105+O105 -> 416 | Q105: 1 | R105: 42.5 | S105: 26 | T105: =Q105*R105*S105 -> 1105 | U105: 0 | V105: 0 | W105: 0 | X105: =U105*V105*W105 -> 0 | Y105: =T105+X105 -> 1105 | Z105: 1 | AA105: 80 | AB105: 1 | AC105: =Z105*AA105*AB105 -> 80 | AD105: 0 | AE105: 0 | AF105: 0 | AG105: =AD105*AE105*AF105 -> 0 | AH105: =AC105+AG105 -> 80 | AI105: =F105+G105+P105+Y105+AH105 -> 2700.0667 | AJ105: =AI105/E105 -> 0.48544888 | AK105: 314.81267 | AL105: 55.62 | AM105: 55.62 | AN105: 166.86 | AO105: 36.153 | AP105: 278.1 | AQ105: =SUM(AL105:AP105) -> 592.353 | AR105: =AK105+AQ105 -> 907.16567 | AS105: =E105-AR105 -> 4654.8343
B106: 08/24 | C106: 262 | D106: QUATRO ESTAÇÕES 509 | E106: 5810 | F106: 710.95 | G106: 350 | H106: 1 | I106: 16 | J106: 26 | K106: =H106*I106*J106 -> 416 | L106: 0 | M106: 0 | N106: 0 | O106: =L106*M106*N106 -> 0 | P106: =K106+O106 -> 416 | Q106: 1 | R106: 42.5 | S106: 26 | T106: =Q106*R106*S106 -> 1105 | U106: 0 | V106: 0 | W106: 0 | X106: =U106*V106*W106 -> 0 | Y106: =T106+X106 -> 1105 | Z106: 1 | AA106: 80 | AB106: 1 | AC106: =Z106*AA106*AB106 -> 80 | AD106: 0 | AE106: 0 | AF106: 0 | AG106: =AD106*AE106*AF106 -> 0 | AH106: =AC106+AG106 -> 80 | AI106: =F106+G106+P106+Y106+AH106 -> 2661.95 | AJ106: =AI106/E106 -> 0.45816695 | AK106: 346.2855 | AL106: 58.1 | AM106: 58.1 | AN106: 174.3 | AO106: 37.765 | AP106: 290.5 | AQ106: =SUM(AL106:AP106) -> 618.765 | AR106: =AK106+AQ106 -> 965.0505 | AS106: =E106-AR106 -> 4844.9495
...

Sheet 2026_RECEITA _JJB SERV
B1: JJ BARBOSA SERVIÇOS
B2: RECEITA
B4: CNAE-Fiscal: | D4: N812140000 _ LIMPEZA EM PREDIOS E EM DOMICILIOS
B5: ATIVIDADE MUNICIPIO: | D5: 710 - 7.10 - Limpeza, manutenção e conservação de vias e logradouros
B7: ANO: | C7: 2026 | D7: VERSÃO 2024.11.20
B8: CLIENTE: | C8: JJ BARBOSA SERVIÇOS | E8: REGIME DE TRIBUTAÇÃO: | F8: SIMPLES NACIONAL
B9: CNPJ: | C9: 27.468,199.0001-33
B10: ENDEREÇO: | C10: ÁGUAS CLARAS
B11: TOTAL | C11: =E179 -> 108198
B13: COMP | C13: NF | D13: CLIENTE | E13: VALOR TOTAL DOS SERVIÇOS | F13: MATERIAS | G13: EQUIPAMENTOS | H13: VALE TRANSPORTE | Q13: VALE ALIMENTAÇÃO | Z13: UNIFORME | AI13: TOTAL BASE RETENÇÃO INSS | AJ13: BASE CÁCULO INSS | AK13: RETENÇÃO DESTACADO NA NF | AS13: TOTAL RETENÇÃO NF | AT13: VALOR LIQUIDO DA NOTA FISCAL
H14: 44H/S | L14: 12 X 36 | P14: TOTAL | Q14: 44H/S | U14: 12 X 36 | Y14: TOTAL | Z14: 44H/S | AD14: 12 X 36 | AH14: TOTAL | AK14: GPS 2631 | AL14: IRRJ 1001 | AM14: CSLL 1002 | AN14: COFINS 1004 | AO14: PIS 1005 | AP14: ISSQN 1732 | AR14: TOTAL
H15: QTDE | I15: $ UNIT | J15: DIAS | K15: TOTAL | L15: QTDE | M15: $ UNIT | N15: DIAS | O15: TOTAL | Q15: QTDE | R15: $ UNIT | S15: DIAS | T15: TOTAL | U15: QTDE | V15: $ UNIT | W15: DIAS | X15: TOTAL | Z15: QTDE | AA15: $ UNIT | AB15: ANO | AC15: TOTAL | AD15: QTDE | AE15: $ UNIT | AF15: ANO | AG15: TOTAL | AJ15: % | AK15: 0.11 | AL15: 0 | AM15: 0 | AN15: 0 | AO15: 0 | AP15: % | AQ15: $ | AR15: =SUBTOTAL(9,AL15:AQ15) -> 0 | AS15: =AK15+AR15 -> 0.11
AR16: =AL16+AM16+AN16+AO16+AQ16 -> 0
B17: 01/24 | C17: 050_GRENWAY | D17: PAINEIRA | E17: 27970 | F17: 4247 | G17: 2550 | H17: 2 | I17: 24 | J17: 26 | K17: =H17*I17*J17 -> 1248 | L17: 4 | M17: 16 | N17: 16 | O17: =L17*M17*N17 -> 1024 | P17: =K17+O17 -> 2272 | Q17: 2 | R17: 42.5 | S17: 26 | T17: =Q17*R17*S17 -> 2210 | U17: 4 | V17: 42.5 | W17: 16 | X17: =U17*V17*W17 -> 2720 | Y17: =T17+X17 -> 4930 | Z17: 2 | AA17: 80 | AB17: 1 | AC17: =Z17*AA17*AB17 -> 160 | AD17: 4 | AE17: 90 | AF17: 1 | AG17: =AD17*AE17*AF17 -> 360 | AH17: =AC17+AG17 -> 520 | AI17: =F17+G17+P17+Y17+AH17 -> 14519 | AJ17: =AI17/E17 -> 0.51909188 | AK17: =(E17-AI17)*$AK$15 -> 1479.61 | AL17: 0 | AM17: 0 | AN17: 0 | AO17: 0 | AP17: 0.05 | AQ17: =AP17*E17 -> 1398.5 | AR17: =AL17+AM17+AN17+AO17+AQ17 -> 1398.5 | AS17: =AK17+AR17 -> 2878.11 | AT17: =E17-AS17 -> 25091.89
B18: 01/24 | C18: 051_GRENWAY | D18: SUMMER | E18: 28630 | F18: 4563.5 | G18: 2550 | H18: 2 | I18: 24 | J18: 26 | K18: =H18*I18*J18 -> 1248 | L18: 4 | M18: 16 | N18: 16 | O18: =L18*M18*N18 -> 1024 | P18: =K18+O18 -> 2272 | Q18: 2 | R18: 42.5 | S18: 26 | T18: =Q18*R18*S18 -> 2210 | U18: 4 | V18: 42.5 | W18: 16 | X18: =U18*V18*W18 -> 2720 | Y18: =T18+X18 -> 4930 | Z18: 2 | AA18: 80 | AB18: 1 | AC18: =Z18*AA18*AB18 -> 160 | AD18: 4 | AE18: 90 | AF18: 1 | AG18: =AD18*AE18*AF18 -> 360 | AH18: =AC18+AG18 -> 520 | AI18: =F18+G18+P18+Y18+AH18 -> 14835.5 | AJ18: =AI18/E18 -> 0.51818023 | AK18: =(E18-AI18)*$AK$15 -> 1517.395 | AL18: 0 | AM18: 0 | AN18: 0 | AO18: 0 | AP18: 0.05 | AQ18: =AP18*E18 -> 1431.5 | AR18: =AL18+AM18+AN18+AO18+AQ18 -> 1431.5 | AS18: =AK18+AR18 -> 2948.895 | AT18: =E18-AS18 -> 25681.105
B19: 02/24 | C19: 052 | D19: PAINEIRA | E19: 29976 | F19: 5288.3 | G19: 2550 | H19: 2 | I19: 24 | J19: 26 | K19: =H19*I19*J19 -> 1248 | L19: 4 | M19: 16 | N19: 16 | O19: =L19*M19*N19 -> 1024 | P19: =K19+O19 -> 2272 | Q19: 2 | R19: 42.5 | S19: 26 | T19: =Q19*R19*S19 -> 2210 | U19: 4 | V19: 42.5 | W19: 16 | X19: =U19*V19*W19 -> 2720 | Y19: =T19+X19 -> 4930 | Z19: 2 | AA19: 80 | AB19: 1 | AC19: =Z19*AA19*AB19 -> 160 | AD19: 4 | AE19: 90 | AF19: 1 | AG19: =AD19*AE19*AF19 -> 360 | AH19: =AC19+AG19 -> 520 | AI19: =F19+G19+P19+Y19+AH19 -> 15560.3 | AJ19: =AI19/E19 -> 0.51909194 | AK19: =(E19-AI19)*$AK$15 -> 1585.727 | AL19: 0 | AM19: 0 | AN19: 0 | AO19: 0 | AP19: 0.05 | AQ19: =AP19*E19 -> 1498.8 | AR19: =AL19+AM19+AN19+AO19+AQ19 -> 1498.8 | AS19: =AK19+AR19 -> 3084.527 | AT19: =E19-AS19 -> 26891.473
B20: 02/24 | C20: 053 | D20: SUMMER | E20: 30680 | F20: 5625.8 | G20: 2550 | H20: 2 | I20: 24 | J20: 26 | K20: =H20*I20*J20 -> 1248 | L20: 4 | M20: 16 | N20: 16 | O20: =L20*M20*N20 -> 1024 | P20: =K20+O20 -> 2272 | Q20: 2 | R20: 42.5 | S20: 26 | T20: =Q20*R20*S20 -> 2210 | U20: 4 | V20: 42.5 | W20: 16 | X20: =U20*V20*W20 -> 2720 | Y20: =T20+X20 -> 4930 | Z20: 2 | AA20: 80 | AB20: 1 | AC20: =Z20*AA20*AB20 -> 160 | AD20: 4 | AE20: 90 | AF20: 1 | AG20: =AD20*AE20*AF20 -> 360 | AH20: =AC20+AG20 -> 520 | AI20: =F20+G20+P20+Y20+AH20 -> 15897.8 | AJ20: =AI20/E20 -> 0.51818123 | AK20: =(E20-AI20)*$AK$15 -> 1626.042 | AL20: 0 | AM20: 0 | AN20: 0 | AO20: 0 | AP20: 0.05 | AQ20: =AP20*E20 -> 1534 | AR20: =AL20+AM20+AN20+AO20+AQ20 -> 1534 | AS20: =AK20+AR20 -> 3160.042 | AT20: =E20-AS20 -> 27519.958
B21: 02/24 | C21: 054 | D21: PAINEIRA | E21: 2006 | F21: 1041.3 | G21: 0 | H21: 0 | I21: 0 | J21: 0 | K21: =H21*I21*J21 -> 0 | L21: 0 | M21: 0 | N21: 0 | O21: =L21*M21*N21 -> 0 | P21: =K21+O21 -> 0 | Q21: 0 | R21: 0 | S21: 0 | T21: =Q21*R21*S21 -> 0 | U21: 0 | V21: 0 | W21: 0 | X21: =U21*V21*W21 -> 0 | Y21: =T21+X21 -> 0 | Z21: 0 | AA21: 0 | AB21: 0 | AC21: =Z21*AA21*AB21 -> 0 | AD21: 0 | AE21: 0 | AF21: 0 | AG21: =AD21*AE21*AF21 -> 0 | AH21: =AC21+AG21 -> 0 | AI21: =F21+G21+P21+Y21+AH21 -> 1041.3 | AJ21: =AI21/E21 -> 0.51909272 | AK21: =(E21-AI21)*$AK$15 -> 106.117 | AL21: 0 | AM21: 0 | AN21: 0 | AO21: 0 | AP21: 0.05 | AQ21: =AP21*E21 -> 100.3 | AR21: =AL21+AM21+AN21+AO21+AQ21 -> 100.3 | AS21: =AK21+AR21 -> 206.417 | AT21: =E21-AS21 -> 1799.583
B22: 02/24 | C22: 055 | D22: SUMMER | E22: 2050 | F22: 1062.3 | G22: 0 | H22: 0 | I22: 0 | J22: 0 | K22: =H22*I22*J22 -> 0 | L22: 0 | M22: 0 | N22: 0 | O22: =L22*M22*N22 -> 0 | P22: =K22+O22 -> 0 | Q22: 0 | R22: 0 | S22: 0 | T22: =Q22*R22*S22 -> 0 | U22: 0 | V22: 0 | W22: 0 | X22: =U22*V22*W22 -> 0 | Y22: =T22+X22 -> 0 | Z22: 0 | AA22: 0 | AB22: 0 | AC22: =Z22*AA22*AB22 -> 0 | AD22: 0 | AE22: 0 | AF22: 0 | AG22: =AD22*AE22*AF22 -> 0 | AH22: =AC22+AG22 -> 0 | AI22: =F22+G22+P22+Y22+AH22 -> 1062.3 | AJ22: =AI22/E22 -> 0.51819512 | AK22: =(E22-AI22)*$AK$15 -> 108.647 | AL22: 0 | AM22: 0 | AN22: 0 | AO22: 0 | AP22: 0.05 | AQ22: =AP22*E22 -> 102.5 | AR22: =AL22+AM22+AN22+AO22+AQ22 -> 102.5 | AS22: =AK22+AR22 -> 211.147 | AT22: =E22-AS22 -> 1838.853
B23: 03/24 | C23: 056 | D23: PAINEIRA | E23: 29976 | F23: 5288.3 | G23: 2550 | H23: 2 | I23: 24 | J23: 26 | K23: =H23*I23*J23 -> 1248 | L23: 4 | M23: 16 | N23: 16 | O23: =L23*M23*N23 -> 1024 | P23: =K23+O23 -> 2272 | Q23: 2 | R23: 42.5 | S23: 26 | T23: =Q23*R23*S23 -> 2210 | U23: 4 | V23: 42.5 | W23: 16 | X23: =U23*V23*W23 -> 2720 | Y23: =T23+X23 -> 4930 | Z23: 2 | AA23: 80 | AB23: 1 | AC23: =Z23*AA23*AB23 -> 160 | AD23: 4 | AE23: 90 | AF23: 1 | AG23: =AD23*AE23*AF23 -> 360 | AH23: =AC23+AG23 -> 520 | AI23: =F23+G23+P23+Y23+AH23 -> 15560.3 | AJ23: =AI23/E23 -> 0.51909194 | AK23: =(E23-AI23)*$AK$15 -> 1585.727 | AL23: 0 | AM23: 0 | AN23: 0 | AO23: 0 | AP23: 0.05 | AQ23: =AP23*E23 -> 1498.8 | AR23: =AL23+AM23+AN23+AO23+AQ23 -> 1498.8 | AS23: =AK23+AR23 -> 3084.527 | AT23: =E23-AS23 -> 26891.473
B24: 03/24 | C24: 057 | D24: SUMMER | E24: 30680 | F24: 5625.8 | G24: 2550 | H24: 2 | I24: 24 | J24: 26 | K24: =H24*I24*J24 -> 1248 | L24: 4 | M24: 16 | N24: 16 | O24: =L24*M24*N24 -> 1024 | P24: =K24+O24 -> 2272 | Q24: 2 | R24: 42.5 | S24: 26 | T24: =Q24*R24*S24 -> 2210 | U24: 4 | V24: 42.5 | W24: 16 | X24: =U24*V24*W24 -> 2720 | Y24: =T24+X24 -> 4930 | Z24: 2 | AA24: 80 | AB24: 1 | AC24: =Z24*AA24*AB24 -> 160 | AD24: 4 | AE24: 90 | AF24: 1 | AG24: =AD24*AE24*AF24 -> 360 | AH24: =AC24+AG24 -> 520 | AI24: =F24+G24+P24+Y24+AH24 -> 15897.8 | AJ24: =AI24/E24 -> 0.51818123 | AK24: =(E24-AI24)*$AK$15 -> 1626.042 | AL24: 0 | AM24: 0 | AN24: 0 | AO24: 0 | AP24: 0.05 | AQ24: =AP24*E24 -> 1534 | AR24: =AL24+AM24+AN24+AO24+AQ24 -> 1534 | AS24: =AK24+AR24 -> 3160.042 | AT24: =E24-AS24 -> 27519.958
B25: 04/24 | C25: 058 | D25: PAINEIRA | E25: 29976 | F25: 5288.3 | G25: 2550 | H25: 2 | I25: 24 | J25: 26 | K25: =H25*I25*J25 -> 1248 | L25: 4 | M25: 16 | N25: 16 | O25: =L25*M25*N25 -> 1024 | P25: =K25+O25 -> 2272 | Q25: 2 | R25: 42.5 | S25: 26 | T25: =Q25*R25*S25 -> 2210 | U25: 4 | V25: 42.5 | W25: 16 | X25: =U25*V25*W25 -> 2720 | Y25: =T25+X25 -> 4930 | Z25: 2 | AA25: 80 | AB25: 1 | AC25: =Z25*AA25*AB25 -> 160 | AD25: 4 | AE25: 90 | AF25: 1 | AG25: =AD25*AE25*AF25 -> 360 | AH25: =AC25+AG25 -> 520 | AI25: =F25+G25+P25+Y25+AH25 -> 15560.3 | AJ25: =AI25/E25 -> 0.51909194 | AK25: =(E25-AI25)*$AK$15 -> 1585.727 | AL25: 0 | AM25: 0 | AN25: 0 | AO25: 0 | AP25: 0.05 | AQ25: =AP25*E25 -> 1498.8 | AR25: =AL25+AM25+AN25+AO25+AQ25 -> 1498.8 | AS25: =AK25+AR25 -> 3084.527 | AT25: =E25-AS25 -> 26891.473
B26: 04/24 | C26: 059 | D26: SUMMER | E26: 30680 | F26: 5625.8 | G26: 2550 | H26: 2 | I26: 24 | J26: 26 | K26: =H26*I26*J26 -> 1248 | L26: 4 | M26: 16 | N26: 16 | O26: =L26*M26*N26 -> 1024 | P26: =K26+O26 -> 2272 | Q26: 2 | R26: 42.5 | S26: 26 | T26: =Q26*R26*S26 -> 2210 | U26: 4 | V26: 42.5 | W26: 16 | X26: =U26*V26*W26 -> 2720 | Y26: =T26+X26 -> 4930 | Z26: 2 | AA26: 80 | AB26: 1 | AC26: =Z26*AA26*AB26 -> 160 | AD26: 4 | AE26: 90 | AF26: 1 | AG26: =AD26*AE26*AF26 -> 360 | AH26: =AC26+AG26 -> 520 | AI26: =F26+G26+P26+Y26+AH26 -> 15897.8 | AJ26: =AI26/E26 -> 0.51818123 | AK26: =(E26-AI26)*$AK$15 -> 1626.042 | AL26: 0 | AM26: 0 | AN26: 0 | AO26: 0 | AP26: 0.05 | AQ26: =AP26*E26 -> 1534 | AR26: =AL26+AM26+AN26+AO26+AQ26 -> 1534 | AS26: =AK26+AR26 -> 3160.042 | AT26: =E26-AS26 -> 27519.958
B27: 05/24 | C27: 060 | D27: PAINEIRA | E27: 29976 | F27: 5288.3 | G27: 2550 | H27: 2 | I27: 24 | J27: 26 | K27: =H27*I27*J27 -> 1248 | L27: 4 | M27: 16 | N27: 16 | O27: =L27*M27*N27 -> 1024 | P27: =K27+O27 -> 2272 | Q27: 2 | R27: 42.5 | S27: 26 | T27: =Q27*R27*S27 -> 2210 | U27: 4 | V27: 42.5 | W27: 16 | X27: =U27*V27*W27 -> 2720 | Y27: =T27+X27 -> 4930 | Z27: 2 | AA27: 80 | AB27: 1 | AC27: =Z27*AA27*AB27 -> 160 | AD27: 4 | AE27: 90 | AF27: 1 | AG27: =AD27*AE27*AF27 -> 360 | AH27: =AC27+AG27 -> 520 | AI27: =F27+G27+P27+Y27+AH27 -> 15560.3 | AJ27: =AI27/E27 -> 0.51909194 | AK27: =(E27-AI27)*$AK$15 -> 1585.727 | AL27: 0 | AM27: 0 | AN27: 0 | AO27: 0 | AP27: 0.0393 | AQ27: =AP27*E27 -> 1178.0568 | AR27: =AL27+AM27+AN27+AO27+AQ27 -> 1178.0568 | AS27: =AK27+AR27 -> 2763.7838 | AT27: =E27-AS27 -> 27212.216
B28: 05/24 | C28: 061 | D28: SUMMER | E28: 30680 | F28: 5625.8 | G28: 2550 | H28: 2 | I28: 24 | J28: 26 | K28: =H28*I28*J28 -> 1248 | L28: 4 | M28: 16 | N28: 16 | O28: =L28*M28*N28 -> 1024 | P28: =K28+O28 -> 2272 | Q28: 2 | R28: 42.5 | S28: 26 | T28: =Q28*R28*S28 -> 2210 | U28: 4 | V28: 42.5 | W28: 16 | X28: =U28*V28*W28 -> 2720 | Y28: =T28+X28 -> 4930 | Z28: 2 | AA28: 80 | AB28: 1 | AC28: =Z28*AA28*AB28 -> 160 | AD28: 4 | AE28: 90 | AF28: 1 | AG28: =AD28*AE28*AF28 -> 360 | AH28: =AC28+AG28 -> 520 | AI28: =F28+G28+P28+Y28+AH28 -> 15897.8 | AJ28: =AI28/E28 -> 0.51818123 | AK28: =(E28-AI28)*$AK$15 -> 1626.042 | AL28: 0 | AM28: 0 | AN28: 0 | AO28: 0 | AP28: 0.0393 | AQ28: =AP28*E28 -> 1205.724 | AR28: =AL28+AM28+AN28+AO28+AQ28 -> 1205.724 | AS28: =AK28+AR28 -> 2831.766 | AT28: =E28-AS28 -> 27848.234
... B35: 09/24 | C35: 068 | D35: SUMMER | E35: 30680 | F35: 5625.8 | G35: 2550 | H35: 2 | I35: 24 | J35: 26 | K35: =H35*I35*J35 -> 1248 | L35: 4 | M35: 16 | N35: 16 | O35: =L35*M35*N35 -> 1024 | P35: =K35+O35 -> 2272 | Q35: 2 | R35: 42.5 | S35: 26 | T35: =Q35*R35*S35 -> 2210 | U35: 4 | V35: 42.5 | W35: 16 | X35: =U35*V35*W35 -> 2720 | Y35: =T35+X35 -> 4930 | Z35: 2 | AA35: 80 | AB35: 1 | AC35: =Z35*AA35*AB35 -> 160 | AD35: 4 | AE35: 90 | AF35: 1 | AG35: =AD35*AE35*AF35 -> 360 | AH35: =AC35+AG35 -> 520 | AI35: =F35+G35+P35+Y35+AH35 -> 15897.8 | AJ35: =AI35/E35 -> 0.51818123 | AK35: =(E35-AI35)*$AK$15 -> 1626.042 | AL35: 0 | AM35: 0 | AN35: 0 | AO35: 0 | AP35: 0.0372 | AQ35: =AP35*E35 -> 1141.296 | AR35: =AL35+AM35+AN35+AO35+AQ35 -> 1141.296 | AS35: =AK35+AR35 -> 2767.338 | AT35: =E35-AS35 -> 27912.662
B36: 10/24 | C36: 70 | D36: SUMMER | E36: 30680 | F36: 5625.8 | G36: 2550 | H36: 2 | I36: 24 | J36: 26 | K36: =H36*I36*J36 -> 1248 | L36: 4 | M36: 16 | N36: 16 | O36: =L36*M36*N36 -> 1024 | P36: =K36+O36 -> 2272 | Q36: 2 | R36: 42.5 | S36: 26 | T36: =Q36*R36*S36 -> 2210 | U36: 4 | V36: 42.5 | W36: 16 | X36: =U36*V36*W36 -> 2720 | Y36: =T36+X36 -> 4930 | Z36: 2 | AA36: 80 | AB36: 1 | AC36: =Z36*AA36*AB36 -> 160 | AD36: 4 | AE36: 90 | AF36: 1 | AG36: =AD36*AE36*AF36 -> 360 | AH36: =AC36+AG36 -> 520 | AI36: =F36+G36+P36+Y36+AH36 -> 15897.8 | AJ36: =AI36/E36 -> 0.51818123 | AK36: =(E36-AI36)*$AK$15 -> 1626.042 | AL36: 0 | AM36: 0 | AN36: 0 | AO36: 0 | AP36: 0.0366 | AQ36: =AP36*E36 -> 1122.888 | AR36: =AL36+AM36+AN36+AO36+AQ36 -> 1122.888 | AS36: =AK36+AR36 -> 2748.93 | AT36: =E36-AS36 -> 27931.07
B37: 10/24 | C37: 69 | D37: TAJ MAHAL_GO | E37: 37805 | F37: 6980 | G37: 4760 | H37: 6 | I37: 24 | J37: 26 | K37: =H37*I37*J37 -> 3744 | L37: 0 | M37: 0 | N37: 0 | O37: =L37*M37*N37 -> 0 | P37: =K37+O37 -> 3744 | Q37: 6 | R37: 42.5 | S37: 26 | T37: =Q37*R37*S37 -> 6630 | U37: 0 | V37: 0 | W37: 0 | X37: =U37*V37*W37 -> 0 | Y37: =T37+X37 -> 6630 | Z37: 6 | AA37: 90 | AB37: 2 | AC37: =Z37*AA37*AB37 -> 1080 | AD37: 0 | AE37: 0 | AF37: 0 | AG37: =AD37*AE37*AF37 -> 0 | AH37: =AC37+AG37 -> 1080 | AI37: =F37+G37+P37+Y37+AH37 -> 23194 | AJ37: =AI37/E37 -> 0.61351673 | AK37: =(E37-AI37)*$AK$15 -> 1607.21 | AL37: 0 | AM37: 0 | AN37: 0 | AO37: 0 | AP37: 0 | AQ37: =AP37*E37 -> 0 | AR37: =AL37+AM37+AN37+AO37+AQ37 -> 0 | AS37: =AK37+AR37 -> 1607.21 | AT37: =E37-AS37 -> 36197.79 | AV37: 32240.097 | AW37: =AT37-AV37 -> 3957.6925
B38: 10/24 | C38: 71 | D38: TAJ MAHAL CONSTRUÇÃO E INCORPORAÇÃO_GO | E38: 1372 | F38: 472.7 | G38: 132 | H38: 1 | I38: 24 | J38: 4 | K38: =H38*I38*J38 -> 96 | L38: 0 | M38: 0 | N38: 0 | O38: =L38*M38*N38 -> 0 | P38: =K38+O38 -> 96 | Q38: 1 | R38: 42.5 | S38: 4 | T38: =Q38*R38*S38 -> 170 | U38: 0 | V38: 0 | W38: 0 | X38: =U38*V38*W38 -> 0 | Y38: =T38+X38 -> 170 | Z38: 1 | AA38: 80 | AB38: 2 | AC38: =Z38*AA38*AB38 -> 160 | AD38: 0 | AE38: 0 | AF38: 0 | AG38: =AD38*AE38*AF38 -> 0 | AH38: =AC38+AG38 -> 160 | AI38: =F38+G38+P38+Y38+AH38 -> 1030.7 | AJ38: =AI38/E38 -> 0.75123907 | AK38: =(E38-AI38)*$AK$15 -> 37.543 | AL38: 0 | AM38: 0 | AN38: 0 | AO38: 0 | AP38: 0 | AQ38: =AP38*E38 -> 0 | AR38: =AL38+AM38+AN38+AO38+AQ38 -> 0 | AS38: =AK38+AR38 -> 37.543 | AT38: =E38-AS38 -> 1334.457
B39: 11/24 | C39: 72 | D39: SUMMER | E39: 30680 | F39: 5625.8 | G39: 2550 | H39: 2 | I39: 24 | J39: 26 | K39: =H39*I39*J39 -> 1248 | L39: 4 | M39: 16 | N39: 16 | O39: =L39*M39*N39 -> 1024 | P39: =K39+O39 -> 2272 | Q39: 2 | R39: 42.5 | S39: 26 | T39: =Q39*R39*S39 -> 2210 | U39: 4 | V39: 42.5 | W39: 16 | X39: =U39*V39*W39 -> 2720 | Y39: =T39+X39 -> 4930 | Z39: 2 | AA39: 80 | AB39: 1 | AC39: =Z39*AA39*AB39 -> 160 | AD39: 4 | AE39: 90 | AF39: 1 | AG39: =AD39*AE39*AF39 -> 360 | AH39: =AC39+AG39 -> 520 | AI39: =F39+G39+P39+Y39+AH39 -> 15897.8 | AJ39: =AI39/E39 -> 0.51818123 | AK39: =(E39-AI39)*$AK$15 -> 1626.042 | AL39: 0 | AM39: 0 | AN39: 0 | AO39: 0 | AP39: 0.03520013 | AQ39: =AP39*E39 -> 1079.94 | AR39: =AL39+AM39+AN39+AO39+AQ39 -> 1079.94 | AS39: =AK39+AR39 -> 2705.982 | AT39: =E39-AS39 -> 27974.018 | AV39: 1079.94 | AW39: =AV39/E39 -> 0.03520013
B40: 11/24 | C40: 77 | D40: TAJ MAHAL_GO | E40: 37805 | F40: 6980 | G40: 4760 | H40: 6 | I40: 24 | J40: 26 | K40: =H40*I40*J40 -> 3744 | L40: 0 | M40: 0 | N40: 0 | O40: =L40*M40*N40 -> 0 | P40: =K40+O40 -> 3744 | Q40: 6 | R40: 42.5 | S40: 26 | T40: =Q40*R40*S40 -> 6630 | U40: 0 | V40: 0 | W40: 0 | X40: =U40*V40*W40 -> 0 | Y40: =T40+X40 -> 6630 | Z40: 6 | AA40: 90 | AB40: 2 | AC40: =Z40*AA40*AB40 -> 1080 | AD40: 0 | AE40: 0 | AF40: 0 | AG40: =AD40*AE40*AF40 -> 0 | AH40: =AC40+AG40 -> 1080 | AI40: =F40+G40+P40+Y40+AH40 -> 23194 | AJ40: =AI40/E40 -> 0.61351673 | AK40: =(E40-AI40)*$AK$15 -> 1607.21 | AL40: 0 | AM40: 0 | AN40: 0 | AO40: 0 | AP40: 0 | AQ40: =AP40*E40 -> 0 | AR40: =AL40+AM40+AN40+AO40+AQ40 -> 0 | AS40: =AK40+AR40 -> 1607.21 | AT40: =E40-AS40 -> 36197.79 | AV40: 32240.097 | AW40: =AT40-AV40 -> 3957.6925
B41: 11/24 | C41: 76 | D41: TAJ MAHAL CONSTRUÇÃO E INCORPORAÇÃO_GO | E41: 1372 | F41: 320 | G41: 0 | H41: 1 | I41: 24 | J41: 4 | K41: =H41*I41*J41 -> 96 | L41: 0 | M41: 0 | N41: 0 | O41: =L41*M41*N41 -> 0 | P41: =K41+O41 -> 96 | Q41: 1 | R41: 42.5 | S41: 4 | T41: =Q41*R41*S41 -> 170 | U41: 0 | V41: 0 | W41: 0 | X41: =U41*V41*W41 -> 0 | Y41: =T41+X41 -> 170 | Z41: 1 | AA41: 80 | AB41: 1 | AC41: =Z41*AA41*AB41 -> 80 | AD41: 0 | AE41: 0 | AF41: 0 | AG41: =AD41*AE41*AF41 -> 0 | AH41: =AC41+AG41 -> 80 | AI41: =F41+G41+P41+Y41+AH41 -> 666 | AJ41: =AI41/E41 -> 0.48542274 | AK41: =(E41-AI41)*$AK$15 -> 77.66 | AL41: 0 | AM41: 0 | AN41: 0 | AO41: 0 | AP41: 0 | AQ41: =AP41*E41 -> 0 | AR41: =AL41+AM41+AN41+AO41+AQ41 -> 0 | AS41: =AK41+AR41 -> 77.66 | AT41: =E41-AS41 -> 1294.34
B42: 11/24 | C42: 79 | D42: AGROBRASIL_GO | E42: 20712 | F42: 799 | G42: 490 | H42: 4 | I42: 24 | J42: 26 | K42: =H42*I42*J42 -> 2496 | L42: 0 | M42: 0 | N42: 0 | O42: =L42*M42*N42 -> 0 | P42: =K42+O42 -> 2496 | Q42: 4 | R42: 42.5 | S42: 26 | T42: =Q42*R42*S42 -> 4420 | U42: 0 | V42: 0 | W42: 0 | X42: =U42*V42*W42 -> 0 | Y42: =T42+X42 -> 4420 | Z42: 4 | AA42: 90 | AB42: 2 | AC42: =Z42*AA42*AB42 -> 720 | AD42: 0 | AE42: 0 | AF42: 0 | AG42: =AD42*AE42*AF42 -> 0 | AH42: =AC42+AG42 -> 720 | AI42: =F42+G42+P42+Y42+AH42 -> 8925 | AJ42: =AI42/E42 -> 0.43090962 | AK42: =(E42-AI42)*$AK$15 -> 1296.57 | AL42: 0 | AM42: 0 | AN42: 0 | AO42: 0 | AP42: 0 | AQ42: =AP42*E42 -> 0 | AR42: =AL42+AM42+AN42+AO42+AQ42 -> 0 | AS42: =AK42+AR42 -> 1296.57 | AT42: =E42-AS42 -> 19415.43
B43: 12/24 | C43: 80 | D43: SUMMER | E43: 30680 | F43: 5625.8 | G43: 2550 | H43: 2 | I43: 24 | J43: 26 | K43: =H43*I43*J43 -> 1248 | L43: 4 | M43: 16 | N43: 16 | O43: =L43*M43*N43 -> 1024 | P43: =K43+O43 -> 2272 | Q43: 2 | R43: 42.5 | S43: 26 | T43: =Q43*R43*S43 -> 2210 | U43: 4 | V43: 42.5 | W43: 16 | X43: =U43*V43*W43 -> 2720 | Y43: =T43+X43 -> 4930 | Z43: 2 | AA43: 80 | AB43: 1 | AC43: =Z43*AA43*AB43 -> 160 | AD43: 4 | AE43: 90 | AF43: 1 | AG43: =AD43*AE43*AF43 -> 360 | AH43: =AC43+AG43 -> 520 | AI43: =F43+G43+P43+Y43+AH43 -> 15897.8 | AJ43: =AI43/E43 -> 0.51818123 | AK43: =(E43-AI43)*$AK$15 -> 1626.042 | AL43: 0 | AM43: 0 | AN43: 0 | AO43: 0 | AP43: 0.0348 | AQ43: =AP43*E43 -> 1067.664 | AR43: =AL43+AM43+AN43+AO43+AQ43 -> 1067.664 | AS43: =AK43+AR43 -> 2693.706 | AT43: =E43-AS43 -> 27986.294
B44: 12/24 | C44: 81 | D44: TAJ MAHAL_GO | E44: 37805 | F44: 6980 | G44: 4760 | H44: 6 | I44: 24 | J44: 26 | K44: =H44*I44*J44 -> 3744 | L44: 0 | M44: 0 | N44: 0 | O44: =L44*M44*N44 -> 0 | P44: =K44+O44 -> 3744 | Q44: 6 | R44: 42.5 | S44: 26 | T44: =Q44*R44*S44 -> 6630 | U44: 0 | V44: 0 | W44: 0 | X44: =U44*V44*W44 -> 0 | Y44: =T44+X44 -> 6630 | Z44: 6 | AA44: 90 | AB44: 2 | AC44: =Z44*AA44*AB44 -> 1080 | AD44: 0 | AE44: 0 | AF44: 0 | AG44: =AD44*AE44*AF44 -> 0 | AH44: =AC44+AG44 -> 1080 | AI44: =F44+G44+P44+Y44+AH44 -> 23194 | AJ44: =AI44/E44 -> 0.61351673 | AK44: =(E44-AI44)*$AK$15 -> 1607.21 | AL44: 0 | AM44: 0 | AN44: 0 | AO44: 0 | AP44: 0 | AQ44: =AP44*E44 -> 0 | AR44: =AL44+AM44+AN44+AO44+AQ44 -> 0 | AS44: =AK44+AR44 -> 1607.21 | AT44: =E44-AS44 -> 36197.79
B45: 12/24 | C45: 82 | D45: TAJ MAHAL CONSTRUÇÃO E INCORPORAÇÃO_GO | E45: 1372 | F45: 320 | G45: 0 | H45: 1 | I45: 24 | J45: 4 | K45: =H45*I45*J45 -> 96 | L45: 0 | M45: 0 | N45: 0 | O45: =L45*M45*N45 -> 0 | P45: =K45+O45 -> 96 | Q45: 1 | R45: 42.5 | S45: 4 | T45: =Q45*R45*S45 -> 170 | U45: 0 | V45: 0 | W45: 0 | X45: =U45*V45*W45 -> 0 | Y45: =T45+X45 -> 170 | Z45: 1 | AA45: 80 | AB45: 1 | AC45: =Z45*AA45*AB45 -> 80 | AD45: 0 | AE45: 0 | AF45: 0 | AG45: =AD45*AE45*AF45 -> 0 | AH45: =AC45+AG45 -> 80 | AI45: =F45+G45+P45+Y45+AH45 -> 666 | AJ45: =AI45/E45 -> 0.48542274 | AK45: =(E45-AI45)*$AK$15 -> 77.66 | AL45: 0 | AM45: 0 | AN45: 0 | AO45: 0 | AP45: 0 | AQ45: =AP45*E45 -> 0 | AR45: =AL45+AM45+AN45+AO45+AQ45 -> 0 | AS45: =AK45+AR45 -> 77.66 | AT45: =E45-AS45 -> 1294.34
B46: 12/24 | C46: 83 | D46: AGROBRASIL_GO | E46: 20712 | F46: 799 | G46: 490 | H46: 4 | I46: 24 | J46: 26 | K46: =H46*I46*J46 -> 2496 | L46: 0 | M46: 0 | N46: 0 | O46: =L46*M46*N46 -> 0 | P46: =K46+O46 -> 2496 | Q46: 4 | R46: 42.5 | S46: 26 | T46: =Q46*R46*S46 -> 4420 | U46: 0 | V46: 0 | W46: 0 | X46: =U46*V46*W46 -> 0 | Y46: =T46+X46 -> 4420 | Z46: 4 | AA46: 90 | AB46: 2 | AC46: =Z46*AA46*AB46 -> 720 | AD46: 0 | AE46: 0 | AF46: 0 | AG46: =AD46*AE46*AF46 -> 0 | AH46: =AC46+AG46 -> 720 | AI46: =F46+G46+P46+Y46+AH46 -> 8925 | AJ46: =AI46/E46 -> 0.43090962 | AK46: =(E46-AI46)*$AK$15 -> 1296.57 | AL46: 0 | AM46: 0 | AN46: 0 | AO46: 0 | AP46: 0 | AQ46: =AP46*E46 -> 0 | AR46: =AL46+AM46+AN46+AO46+AQ46 -> 0 | AS46: =AK46+AR46 -> 1296.57 | AT46: =E46-AS46 -> 19415.43
B47: 12/24 | C47: 84 | D47: BELA VISTA | E47: =5300+530 -> 5830 | F47: 950.61 | G47: 351.9 | H47: 1 | I47: 24 | J47: 26 | K47: =H47*I47*J47 -> 624 | L47: 0 | M47: 0 | N47: 0 | O47: =L47*M47*N47 -> 0 | P47: =K47+O47 -> 624 | Q47: 1 | R47: 42.5 | S47: 26 | T47: =Q47*R47*S47 -> 1105 | U47: 0 | V47: 0 | W47: 0 | X47: =U47*V47*W47 -> 0 | Y47: =T47+X47 -> 1105 | Z47: 1 | AA47: 90 | AB47: 2 | AC47: =Z47*AA47*AB47 -> 180 | AD47: 0 | AE47: 0 | AF47: 0 | AG47: =AD47*AE47*AF47 -> 0 | AH47: =AC47+AG47 -> 180 | AI47: =F47+G47+P47+Y47+AH47 -> 3211.51 | AJ47: =AI47/E47 -> 0.55085935 | AK47: =(E47-AI47)*$AK$15 -> 288.0339 | AL47: 0 | AM47: 0 | AN47: 0 | AO47: 0 | AP47: 0.0348 | AQ47: =AP47*E47 -> 202.884 | AR47: =AL47+AM47+AN47+AO47+AQ47 -> 202.884 | AS47: =AK47+AR47 -> 490.9179 | AT47: =E47-AS47 -> 5339.0821
B48: 12/24 | C48: 85 | D48: VICENZA_GO | E48: =(7820/30)*16 -> 4170.6667 | F48: 290 | G48: 130 | H48: 2 | I48: 24 | J48: 16 | K48: =H48*I48*J48 -> 768 | L48: 0 | M48: 0 | N48: 0 | O48: =L48*M48*N48 -> 0 | P48: =K48+O48 -> 768 | Q48: 2 | R48: 42.5 | S48: 16 | T48: =Q48*R48*S48 -> 1360 | U48: 0 | V48: 0 | W48: 0 | X48: =U48*V48*W48 -> 0 | Y48: =T48+X48 -> 1360 | Z48: 2 | AA48: 90 | AB48: 2 | AC48: =Z48*AA48*AB48 -> 360 | AD48: 0 | AE48: 0 | AF48: 0 | AG48: =AD48*AE48*AF48 -> 0 | AH48: =AC48+AG48 -> 360 | AI48: =F48+G48+P48+Y48+AH48 -> 2908 | AJ48: =AI48/E48 -> 0.69725064 | AK48: =(E48-AI48)*$AK$15 -> 138.89333 | AL48: 0 | AM48: 0 | AN48: 0 | AO48: 0 | AP48: 0 | AQ48: =AP48*E48 -> 0 | AR48: =AL48+AM48+AN48+AO48+AQ48 -> 0 | AS48: =AK48+AR48 -> 138.89333 | AT48: =E48-AS48 -> 4031.7733
B49: 01/25 | C49: 91 | D49: SUMMER | E49: 30680 | F49: 5625.8 | G49: 2550 | H49: 2 | I49: 24 | J49: 26 | K49: =H49*I49*J49 -> 1248 | L49: 4 | M49: 16 | N49: 16 | O49: =L49*M49*N49 -> 1024 | P49: =K49+O49 -> 2272 | Q49: 2 | R49: 42.5 | S49: 26 | T49: =Q49*R49*S49 -> 2210 | U49: 4 | V49: 42.5 | W49: 16 | X49: =U49*V49*W49 -> 2720 | Y49: =T49+X49 -> 4930 | Z49: 2 | AA49: 80 | AB49: 1 | AC49: =Z49*AA49*AB49 -> 160 | AD49: 4 | AE49: 90 | AF49: 1 | AG49: =AD49*AE49*AF49 -> 360 | AH49: =AC49+AG49 -> 520 | AI49: =F49+G49+P49+Y49+AH49 -> 15897.8 | AJ49: =AI49/E49 -> 0.51818123 | AK49: =(E49-AI49)*$AK$15 -> 1626.042 | AL49: 0 | AM49: 0 | AN49: 0 | AO49: 0 | AP49: 0.05 | AQ49: =AP49*E49 -> 1534 | AR49: =AL49+AM49+AN49+AO49+AQ49 -> 1534 | AS49: =AK49+AR49 -> 3160.042 | AT49: =E49-AS49 -> 27519.958
B50: 01/25 | C50: 87 | D50: TAJ MAHAL_GO | E50: 37805 | F50: 6980 | G50: 4760 | H50: 6 | I50: 24 | J50: 26 | K50: =H50*I50*J50 -> 3744 | L50: 0 | M50: 0 | N50: 0 | O50: =L50*M50*N50 -> 0 | P50: =K50+O50 -> 3744 | Q50: 6 | R50: 42.5 | S50: 26 | T50: =Q50*R50*S50 -> 6630 | U50: 0 | V50: 0 | W50: 0 | X50: =U50*V50*W50 -> 0 | Y50: =T50+X50 -> 6630 | Z50: 6 | AA50: 90 | AB50: 2 | AC50: =Z50*AA50*AB50 -> 1080 | AD50: 0 | AE50: 0 | AF50: 0 | AG50: =AD50*AE50*AF50 -> 0 | AH50: =AC50+AG50 -> 1080 | AI50: =F50+G50+P50+Y50+AH50 -> 23194 | AJ50: =AI50/E50 -> 0.61351673 | AK50: =(E50-AI50)*$AK$15 -> 1607.21 | AL50: 0 | AM50: 0 | AN50: 0 | AO50: 0 | AP50: 0 | AQ50: =AP50*E50 -> 0 | AR50: =AL50+AM50+AN50+AO50+AQ50 -> 0 | AS50: =AK50+AR50 -> 1607.21 | AT50: =E50-AS50 -> 36197.79
B51: 01/25 | C51: 89 | D51: TAJ MAHAL CONSTRUÇÃO E INCORPORAÇÃO_GO | E51: 1372 | F51: 320 | G51: 0 | H51: 1 | I51: 24 | J51: 4 | K51: =H51*I51*J51 -> 96 | L51: 0 | M51: 0 | N51: 0 | O51: =L51*M51*N51 -> 0 | P51: =K51+O51 -> 96 | Q51: 1 | R51: 42.5 | S51: 4 | T51: =Q51*R51*S51 -> 170 | U51: 0 | V51: 0 | W51: 0 | X51: =U51*V51*W51 -> 0 | Y51: =T51+X51 -> 170 | Z51: 1 | AA51: 80 | AB51: 1 | AC51: =Z51*AA51*AB51 -> 80 | AD51: 0 | AE51: 0 | AF51: 0 | AG51: =AD51*AE51*AF51 -> 0 | AH51: =AC51+AG51 -> 80 | AI51: =F51+G51+P51+Y51+AH51 -> 666 | AJ51: =AI51/E51 -> 0.48542274 | AK51: =(E51-AI51)*$AK$15 -> 77.66 | AL51: 0 | AM51: 0 | AN51: 0 | AO51: 0 | AP51: 0 | AQ51: =AP51*E51 -> 0 | AR51: =AL51+AM51+AN51+AO51+AQ51 -> 0 | AS51: =AK51+AR51 -> 77.66 | AT51: =E51-AS51 -> 1294.34
B52: 01/25 | C52: 86 | D52: AGROBRASIL_GO | E52: 20712 | F52: 799 | G52: 490 | H52: 4 | I52: 24 | J52: 26 | K52: =H52*I52*J52 -> 2496 | L52: 0 | M52: 0 | N52: 0 | O52: =L52*M52*N52 -> 0 | P52: =K52+O52 -> 2496 | Q52: 4 | R52: 42.5 | S52: 26 | T52: =Q52*R52*S52 -> 4420 | U52: 0 | V52: 0 | W52: 0 | X52: =U52*V52*W52 -> 0 | Y52: =T52+X52 -> 4420 | Z52: 4 | AA52: 90 | AB52: 2 | AC52: =Z52*AA52*AB52 -> 720 | AD52: 0 | AE52: 0 | AF52: 0 | AG52: =AD52*AE52*AF52 -> 0 | AH52: =AC52+AG52 -> 720 | AI52: =F52+G52+P52+Y52+AH52 -> 8925 | AJ52: =AI52/E52 -> 0.43090962 | AK52: =(E52-AI52)*$AK$15 -> 1296.57 | AL52: 0 | AM52: 0 | AN52: 0 | AO52: 0 | AP52: 0 | AQ52: =AP52*E52 -> 0 | AR52: =AL52+AM52+AN52+AO52+AQ52 -> 0 | AS52: =AK52+AR52 -> 1296.57 | AT52: =E52-AS52 -> 19415.43
B53: 01/25 | C53: 92 | D53: BELA VISTA | E53: 5300 | F53: 950.61 | G53: 351.9 | H53: 1 | I53: 24 | J53: 26 | K53: =H53*I53*J53 -> 624 | L53: 0 | M53: 0 | N53: 0 | O53: =L53*M53*N53 -> 0 | P53: =K53+O53 -> 624 | Q53: 1 | R53: 42.5 | S53: 26 | T53: =Q53*R53*S53 -> 1105 | U53: 0 | V53: 0 | W53: 0 | X53: =U53*V53*W53 -> 0 | Y53: =T53+X53 -> 1105 | Z53: 1 | AA53: 90 | AB53: 2 | AC53: =Z53*AA53*AB53 -> 180 | AD53: 0 | AE53: 0 | AF53: 0 | AG53: =AD53*AE53*AF53 -> 0 | AH53: =AC53+AG53 -> 180 | AI53: =F53+G53+P53+Y53+AH53 -> 3211.51 | AJ53: =AI53/E53 -> 0.60594528 | AK53: =(E53-AI53)*$AK$15 -> 229.7339 | AL53: 0 | AM53: 0 | AN53: 0 | AO53: 0 | AP53: 0.05 | AQ53: =AP53*E53 -> 265 | AR53: =AL53+AM53+AN53+AO53+AQ53 -> 265 | AS53: =AK53+AR53 -> 494.7339 | AT53: =E53-AS53 -> 4805.2661
B54: 01/25 | C54: 88 | D54: VICENZA_GO | E54: 7820 | F54: 950.61 | G54: 230 | H54: 2 | I54: 24 | J54: 16 | K54: =H54*I54*J54 -> 768 | L54: 0 | M54: 0 | N54: 0 | O54: =L54*M54*N54 -> 0 | P54: =K54+O54 -> 768 | Q54: 2 | R54: 42.5 | S54: 16 | T54: =Q54*R54*S54 -> 1360 | U54: 0 | V54: 0 | W54: 0 | X54: =U54*V54*W54 -> 0 | Y54: =T54+X54 -> 1360 | Z54: 2 | AA54: 90 | AB54: 2 | AC54: =Z54*AA54*AB54 -> 360 | AD54: 0 | AE54: 0 | AF54: 0 | AG54: =AD54*AE54*AF54 -> 0 | AH54: =AC54+AG54 -> 360 | AI54: =F54+G54+P54+Y54+AH54 -> 3668.61 | AJ54: =AI54/E54 -> 0.46913171 | AK54: =(E54-AI54)*$AK$15 -> 456.6529 | AL54: 0 | AM54: 0 | AN54: 0 | AO54: 0 | AP54: 0 | AQ54: =AP54*E54 -> 0 | AR54: =AL54+AM54+AN54+AO54+AQ54 -> 0 | AS54: =AK54+AR54 -> 456.6529 | AT54: =E54-AS54 -> 7363.3471
B56: 02/25 | C56: 93 | D56: AGROBRASIL_GO | E56: 20712 | F56: 799 | G56: 490 | H56: 4 | I56: 24 | J56: 26 | K56: =H56*I56*J56 -> 2496 | L56: 0 | M56: 0 | N56: 0 | O56: =L56*M56*N56 -> 0 | P56: =K56+O56 -> 2496 | Q56: 4 | R56: 44.3 | S56: 26 | T56: =Q56*R56*S56 -> 4607.2 | U56: 0 | V56: 0 | W56: 0 | X56: =U56*V56*W56 -> 0 | Y56: =T56+X56 -> 4607.2 | Z56: 4 | AA56: 90 | AB56: 2 | AC56: =Z56*AA56*AB56 -> 720 | AD56: 0 | AE56: 0 | AF56: 0 | AG56: =AD56*AE56*AF56 -> 0 | AH56: =AC56+AG56 -> 720 | AI56: =F56+G56+P56+Y56+AH56 -> 9112.2 | AJ56: =AI56/E56 -> 0.43994786 | AK56: =(E56-AI56)*$AK$15 -> 1275.978 | AL56: 0 | AM56: 0 | AN56: 0 | AO56: 0 | AP56: 0 | AQ56: =AP56*E56 -> 0 | AR56: =AL56+AM56+AN56+AO56+AQ56 -> 0 | AS56: =AK56+AR56 -> 1275.978 | AT56: =E56-AS56 -> 19436.022
B57: 02/25 | C57: 100 | D57: SUMMER | E57: 33317 | F57: 5925 | G57: 2550 | H57: 2 | I57: 24 | J57: 26 | K57: =H57*I57*J57 -> 1248 | L57: 4 | M57: 16 | N57: 16 | O57: =L57*M57*N57 -> 1024 | P57: =K57+O57 -> 2272 | Q57: 2 | R57: 44.3 | S57: 26 | T57: =Q57*R57*S57 -> 2303.6 | U57: 4 | V57: 44.3 | W57: 16 | X57: =U57*V57*W57 -> 2835.2 | Y57: =T57+X57 -> 5138.8 | Z57: 2 | AA57: 40 | AB57: 2 | AC57: =Z57*AA57*AB57 -> 160 | AD57: 4 | AE57: 90 | AF57: 2 | AG57: =AD57*AE57*AF57 -> 720 | AH57: =AC57+AG57 -> 880 | AI57: =F57+G57+P57+Y57+AH57 -> 16765.8 | AJ57: =AI57/E57 -> 0.50322058 | AK57: =(E57-AI57)*$AK$15 -> 1820.632 | AL57: 0 | AM57: 0 | AN57: 0 | AO57: 0 | AP57: 0.0356 | AQ57: =AP57*E57 -> 1186.0852 | AR57: =AL57+AM57+AN57+AO57+AQ57 -> 1186.0852 | AS57: =AK57+AR57 -> 3006.7172 | AT57: =E57-AS57 -> 30310.283
B58: 02/25 | C58: 96 | D58: TAJ MAHAL_GO | E58: 37805 | F58: 6980 | G58: 4760 | H58: 6 | I58: 24 | J58: 26 | K58: =H58*I58*J58 -> 3744 | L58: 0 | M58: 0 | N58: 0 | O58: =L58*M58*N58 -> 0 | P58: =K58+O58 -> 3744 | Q58: 6 | R58: 42.5 | S58: 26 | T58: =Q58*R58*S58 -> 6630 | U58: 0 | V58: 0 | W58: 0 | X58: =U58*V58*W58 -> 0 | Y58: =T58+X58 -> 6630 | Z58: 6 | AA58: 90 | AB58: 2 | AC58: =Z58*AA58*AB58 -> 1080 | AD58: 0 | AE58: 0 | AF58: 0 | AG58: =AD58*AE58*AF58 -> 0 | AH58: =AC58+AG58 -> 1080 | AI58: =F58+G58+P58+Y58+AH58 -> 23194 | AJ58: =AI58/E58 -> 0.61351673 | AK58: =(E58-AI58)*$AK$15 -> 1607.21 | AL58: 0 | AM58: 0 | AN58: 0 | AO58: 0 | AP58: 0 | AQ58: =AP58*E58 -> 0 | AR58: =AL58+AM58+AN58+AO58+AQ58 -> 0 | AS58: =AK58+AR58 -> 1607.21 | AT58: =E58-AS58 -> 36197.79
B59: 02/25 | C59: 95 | D59: TAJ MAHAL CONSTRUÇÃO E INCORPORAÇÃO_GO | E59: 1372 | F59: 320 | G59: 0 | H59: 1 | I59: 24 | J59: 4 | K59: =H59*I59*J59 -> 96 | L59: 0 | M59: 0 | N59: 0 | O59: =L59*M59*N59 -> 0 | P59: =K59+O59 -> 96 | Q59: 1 | R59: 42.5 | S59: 4 | T59: =Q59*R59*S59 -> 170 | U59: 0 | V59: 0 | W59: 0 | X59: =U59*V59*W59 -> 0 | Y59: =T59+X59 -> 170 | Z59: 1 | AA59: 80 | AB59: 1 | AC59: =Z59*AA59*AB59 -> 80 | AD59: 0 | AE59: 0 | AF59: 0 | AG59: =AD59*AE59*AF59 -> 0 | AH59: =AC59+AG59 -> 80 | AI59: =F59+G59+P59+Y59+AH59 -> 666 | AJ59: =AI59/E59 -> 0.48542274 | AK59: =(E59-AI59)*$AK$15 -> 77.66 | AL59: 0 | AM59: 0 | AN59: 0 | AO59: 0 | AP59: 0 | AQ59: =AP59*E59 -> 0 | AR59: =AL59+AM59+AN59+AO59+AQ59 -> 0 | AS59: =AK59+AR59 -> 77.66 | AT59: =E59-AS59 -> 1294.34
B60: 02/25 | C60: 98 | D60: BELA VISTA | E60: =5300+530 -> 5830 | F60: 950.61 | G60: 351.9 | H60: 1 | I60: 24 | J60: 26 | K60: =H60*I60*J60 -> 624 | L60: 0 | M60: 0 | N60: 0 | O60: =L60*M60*N60 -> 0 | P60: =K60+O60 -> 624 | Q60: 1 | R60: 42.5 | S60: 26 | T60: =Q60*R60*S60 -> 1105 | U60: 0 | V60: 0 | W60: 0 | X60: =U60*V60*W60 -> 0 | Y60: =T60+X60 -> 1105 | Z60: 1 | AA60: 90 | AB60: 2 | AC60: =Z60*AA60*AB60 -> 180 | AD60: 0 | AE60: 0 | AF60: 0 | AG60: =AD60*AE60*AF60 -> 0 | AH60: =AC60+AG60 -> 180 | AI60: =F60+G60+P60+Y60+AH60 -> 3211.51 | AJ60: =AI60/E60 -> 0.55085935 | AK60: =(E60-AI60)*$AK$15 -> 288.0339 | AL60: 0 | AM60: 0 | AN60: 0 | AO60: 0 | AP60: 0.0356 | AQ60: =AP60*E60 -> 207.548 | AR60: =AL60+AM60+AN60+AO60+AQ60 -> 207.548 | AS60: =AK60+AR60 -> 495.5819 | AT60: =E60-AS60 -> 5334.4181
B61: 02/25 | C61: 97 | D61: VICENZA_GO | E61: 7820 | F61: 950.61 | G61: 230 | H61: 2 | I61: 24 | J61: 16 | K61: =H61*I61*J61 -> 768 | L61: 0 | M61: 0 | N61: 0 | O61: =L61*M61*N61 -> 0 | P61: =K61+O61 -> 768 | Q61: 2 | R61: 42.5 | S61: 16 | T61: =Q61*R61*S61 -> 1360 | U61: 0 | V61: 0 | W61: 0 | X61: =U61*V61*W61 -> 0 | Y61: =T61+X61 -> 1360 | Z61: 2 | AA61: 90 | AB61: 2 | AC61: =Z61*AA61*AB61 -> 360 | AD61: 0 | AE61: 0 | AF61: 0 | AG61: =AD61*AE61*AF61 -> 0 | AH61: =AC61+AG61 -> 360 | AI61: =F61+G61+P61+Y61+AH61 -> 3668.61 | AJ61: =AI61/E61 -> 0.46913171 | AK61: =(E61-AI61)*$AK$15 -> 456.6529 | AL61: 0 | AM61: 0 | AN61: 0 | AO61: 0 | AP61: 0 | AQ61: =AP61*E61 -> 0 | AR61: =AL61+AM61+AN61+AO61+AQ61 -> 0 | AS61: =AK61+AR61 -> 456.6529 | AT61: =E61-AS61 -> 7363.3471
B62: 02/25 | C62: 99 | D62: SAFIRA | E62: 6104 | F62: 950.61 | G62: 351.9 | H62: 1 | I62: 24 | J62: 26 | K62: =H62*I62*J62 -> 624 | L62: 0 | M62: 0 | N62: 0 | O62: =L62*M62*N62 -> 0 | P62: =K62+O62 -> 624 | Q62: 1 | R62: 44.3 | S62: 26 | T62: =Q62*R62*S62 -> 1151.8 | U62: 0 | V62: 0 | W62: 0 | X62: =U62*V62*W62 -> 0 | Y62: =T62+X62 -> 1151.8 | Z62: 1 | AA62: 90 | AB62: 2 | AC62: =Z62*AA62*AB62 -> 180 | AD62: 0 | AE62: 0 | AF62: 0 | AG62: =AD62*AE62*AF62 -> 0 | AH62: =AC62+AG62 -> 180 | AI62: =F62+G62+P62+Y62+AH62 -> 3258.31 | AJ62: =AI62/E62 -> 0.53379915 | AK62: =(E62-AI62)*$AK$15 -> 313.0259 | AL62: 0 | AM62: 0 | AN62: 0 | AO62: 0 | AP62: 0.0356 | AQ62: =AP62*E62 -> 217.3024 | AR62: =AL62+AM62+AN62+AO62+AQ62 -> 217.3024 | AS62: =AK62+AR62 -> 530.3283 | AT62: =E62-AS62 -> 5573.6717 | AV62: 3500 | AW62: =AT62-AV62 -> 2073.6717
B64: 03/25 | C64: 102 | D64: AGROBRASIL_GO | E64: 22775 | F64: 871.39 | G64: 534.39 | H64: 4 | I64: 24 | J64: 26 | K64: =H64*I64*J64 -> 2496 | L64: 0 | M64: 0 | N64: 0 | O64: =L64*M64*N64 -> 0 | P64: =K64+O64 -> 2496 | Q64: 4 | R64: 44.3 | S64: 26 | T64: =Q64*R64*S64 -> 4607.2 | U64: 0 | V64: 0 | W64: 0 | X64: =U64*V64*W64 -> 0 | Y64: =T64+X64 -> 4607.2 | Z64: 4 | AA64: 90 | AB64: 4 | AC64: =Z64*AA64*AB64 -> 1440 | AD64: 0 | AE64: 0 | AF64: 0 | AG64: =AD64*AE64*AF64 -> 0 | AH64: =AC64+AG64 -> 1440 | AI64: =F64+G64+P64+Y64+AH64 -> 9948.98 | AJ64: =AI64/E64 -> 0.43683776 | AK64: =(E64-AI64)*$AK$15 -> 1410.8622 | AL64: 0 | AM64: 0 | AN64: 0 | AO64: 0 | AP64: 0 | AQ64: =AP64*E64 -> 0 | AR64: =AL64+AM64+AN64+AO64+AQ64 -> 0 | AS64: =AK64+AR64 -> 1410.8622 | AT64: =E64-AS64 -> 21364.138
B65: 03/25 | C65: 105 | D65: SUMMER | E65: 33317 | F65: 5925 | G65: 2550 | H65: 2 | I65: 24 | J65: 26 | K65: =H65*I65*J65 -> 1248 | L65: 4 | M65: 16 | N65: 16 | O65: =L65*M65*N65 -> 1024 | P65: =K65+O65 -> 2272 | Q65: 2 | R65: 44.3 | S65: 26 | T65: =Q65*R65*S65 -> 2303.6 | U65: 4 | V65: 44.3 | W65: 16 | X65: =U65*V65*W65 -> 2835.2 | Y65: =T65+X65 -> 5138.8 | Z65: 2 | AA65: 40 | AB65: 2 | AC65: =Z65*AA65*AB65 -> 160 | AD65: 4 | AE65: 90 | AF65: 2 | AG65: =AD65*AE65*AF65 -> 720 | AH65: =AC65+AG65 -> 880 | AI65: =F65+G65+P65+Y65+AH65 -> 16765.8 | AJ65: =AI65/E65 -> 0.50322058 | AK65: =(E65-AI65)*$AK$15 -> 1820.632 | AL65: 0 | AM65: 0 | AN65: 0 | AO65: 0 | AP65: 0.0356 | AQ65: =AP65*E65 -> 1186.0852 | AR65: =AL65+AM65+AN65+AO65+AQ65 -> 1186.0852 | AS65: =AK65+AR65 -> 3006.7172 | AT65: =E65-AS65 -> 30310.283
B66: 03/25 | C66: 104 | D66: TAJ MAHAL_GO | E66: 40937 | F66: 7513.97 | G66: 5124.14 | H66: 6 | I66: 24 | J66: 26 | K66: =H66*I66*J66 -> 3744 | L66: 0 | M66: 0 | N66: 0 | O66: =L66*M66*N66 -> 0 | P66: =K66+O66 -> 3744 | Q66: 6 | R66: 44.3 | S66: 26 | T66: =Q66*R66*S66 -> 6910.8 | U66: 0 | V66: 0 | W66: 0 | X66: =U66*V66*W66 -> 0 | Y66: =T66+X66 -> 6910.8 | Z66: 6 | AA66: 90 | AB66: 2 | AC66: =Z66*AA66*AB66 -> 1080 | AD66: 0 | AE66: 0 | AF66: 0 | AG66: =AD66*AE66*AF66 -> 0 | AH66: =AC66+AG66 -> 1080 | AI66: =F66+G66+P66+Y66+AH66 -> 24372.91 | AJ66: =AI66/E66 -> 0.59537607 | AK66: =(E66-AI66)*$AK$15 -> 1822.0499 | AL66: 0 | AM66: 0 | AN66: 0 | AO66: 0 | AP66: 0 | AQ66: =AP66*E66 -> 0 | AR66: =AL66+AM66+AN66+AO66+AQ66 -> 0 | AS66: =AK66+AR66 -> 1822.0499 | AT66: =E66-AS66 -> 39114.95
B67: 03/25 | C67: 106 | D67: TAJ MAHAL CONSTRUÇÃO E INCORPORAÇÃO_GO | E67: =1562-235.74 -> 1326.26 | F67: 395.2 | G67: 0 | H67: 1 | I67: 24 | J67: 4 | K67: =H67*I67*J67 -> 96 | L67: 0 | M67: 0 | N67: 0 | O67: =L67*M67*N67 -> 0 | P67: =K67+O67 -> 96 | Q67: 1 | R67: 44.3 | S67: 4 | T67: =Q67*R67*S67 -> 177.2 | U67: 0 | V67: 0 | W67: 0 | X67: =U67*V67*W67 -> 0 | Y67: =T67+X67 -> 177.2 | Z67: 1 | AA67: 90 | AB67: 1 | AC67: =Z67*AA67*AB67 -> 90 | AD67: 0 | AE67: 0 | AF67: 0 | AG67: =AD67*AE67*AF67 -> 0 | AH67: =AC67+AG67 -> 90 | AI67: =F67+G67+P67+Y67+AH67 -> 758.4 | AJ67: =AI67/E67 -> 0.57183358 | AK67: =(E67-AI67)*$AK$15 -> 62.4646 | AL67: 0 | AM67: 0 | AN67: 0 | AO67: 0 | AP67: 0 | AQ67: =AP67*E67 -> 0 | AR67: =AL67+AM67+AN67+AO67+AQ67 -> 0 | AS67: =AK67+AR67 -> 62.4646 | AT67: =E67-AS67 -> 1263.7954
B68: 03/25 | C68: 107 | D68: BELA VISTA | E68: 5870 | F68: 1043 | G68: 387 | H68: 1 | I68: 24 | J68: 26 | K68: =H68*I68*J68 -> 624 | L68: 0 | M68: 0 | N68: 0 | O68: =L68*M68*N68 -> 0 | P68: =K68+O68 -> 624 | Q68: 1 | R68: 44.3 | S68: 26 | T68: =Q68*R68*S68 -> 1151.8 | U68: 0 | V68: 0 | W68: 0 | X68: =U68*V68*W68 -> 0 | Y68: =T68+X68 -> 1151.8 | Z68: 1 | AA68: 90 | AB68: 2 | AC68: =Z68*AA68*AB68 -> 180 | AD68: 0 | AE68: 0 | AF68: 0 | AG68: =AD68*AE68*AF68 -> 0 | AH68: =AC68+AG68 -> 180 | AI68: =F68+G68+P68+Y68+AH68 -> 3385.8 | AJ68: =AI68/E68 -> 0.57679727 | AK68: =(E68-AI68)*$AK$15 -> 273.262 | AL68: 0 | AM68: 0 | AN68: 0 | AO68: 0 | AP68: 0.0356 | AQ68: =AP68*E68 -> 208.972 | AR68: =AL68+AM68+AN68+AO68+AQ68 -> 208.972 | AS68: =AK68+AR68 -> 482.234 | AT68: =E68-AS68 -> 5387.766
B69: 03/25 | C69: 108 | D69: VICENZA_GO | E69: 8960 | F69: 1190 | G69: 410 | H69: 2 | I69: 24 | J69: 16 | K69: =H69*I69*J69 -> 768 | L69: 0 | M69: 0 | N69: 0 | O69: =L69*M69*N69 -> 0 | P69: =K69+O69 -> 768 | Q69: 2 | R69: 44.3 | S69: 16 | T69: =Q69*R69*S69 -> 1417.6 | U69: 0 | V69: 0 | W69: 0 | X69: =U69*V69*W69 -> 0 | Y69: =T69+X69 -> 1417.6 | Z69: 2 | AA69: 90 | AB69: 2 | AC69: =Z69*AA69*AB69 -> 360 | AD69: 0 | AE69: 0 | AF69: 0 | AG69: =AD69*AE69*AF69 -> 0 | AH69: =AC69+AG69 -> 360 | AI69: =F69+G69+P69+Y69+AH69 -> 4145.6 | AJ69: =AI69/E69 -> 0.46267857 | AK69: =(E69-AI69)*$AK$15 -> 529.584 | AL69: 0 | AM69: 0 | AN69: 0 | AO69: 0 | AP69: 0 | AQ69: =AP69*E69 -> 0 | AR69: =AL69+AM69+AN69+AO69+AQ69 -> 0 | AS69: =AK69+AR69 -> 529.584 | AT69: =E69-AS69 -> 8430.416
B70: 03/25 | C70: 109 | D70: SAFIRA | E70: 6104 | F70: 950.61 | G70: 351.9 | H70: 1 | I70: 24 | J70: 26 | K70: =H70*I70*J70 -> 624 | L70: 0 | M70: 0 | N70: 0 | O70: =L70*M70*N70 -> 0 | P70: =K70+O70 -> 624 | Q70: 1 | R70: 44.3 | S70: 26 | T70: =Q70*R70*S70 -> 1151.8 | U70: 0 | V70: 0 | W70: 0 | X70: =U70*V70*W70 -> 0 | Y70: =T70+X70 -> 1151.8 | Z70: 1 | AA70: 90 | AB70: 2 | AC70: =Z70*AA70*AB70 -> 180 | AD70: 0 | AE70: 0 | AF70: 0 | AG70: =AD70*AE70*AF70 -> 0 | AH70: =AC70+AG70 -> 180 | AI70: =F70+G70+P70+Y70+AH70 -> 3258.31 | AJ70: =AI70/E70 -> 0.53379915 | AK70: =(E70-AI70)*$AK$15 -> 313.0259 | AL70: 0 | AM70: 0 | AN70: 0 | AO70: 0 | AP70: 0.0356 | AQ70: =AP70*E70 -> 217.3024 | AR70: =AL70+AM70+AN70+AO70+AQ70 -> 217.3024 | AS70: =AK70+AR70 -> 530.3283 | AT70: =E70-AS70 -> 5573.6717
B72: 04/25 | C72: 111 | D72: AGROBRASIL_GO | E72: =11388+4126 -> 15514 | F72: 871.39 | G72: 534.39 | H72: 4 | I72: 24 | J72: 26 | K72: =H72*I72*J72 -> 2496 | L72: 0 | M72: 0 | N72: 0 | O72: =L72*M72*N72 -> 0 | P72: =K72+O72 -> 2496 | Q72: 4 | R72: 44.3 | S72: 26 | T72: =Q72*R72*S72 -> 4607.2 | U72: 0 | V72: 0 | W72: 0 | X72: =U72*V72*W72 -> 0 | Y72: =T72+X72 -> 4607.2 | Z72: 4 | AA72: 90 | AB72: 4 | AC72: =Z72*AA72*AB72 -> 1440 | AD72: 0 | AE72: 0 | AF72: 0 | AG72: =AD72*AE72*AF72 -> 0 | AH72: =AC72+AG72 -> 1440 | AI72: =F72+G72+P72+Y72+AH72 -> 9948.98 | AJ72: =AI72/E72 -> 0.64129045 | AK72: =(E72-AI72)*$AK$15 -> 612.1522 | AL72: 0 | AM72: 0 | AN72: 0 | AO72: 0 | AP72: 0 | AQ72: =AP72*E72 -> 0 | AR72: =AL72+AM72+AN72+AO72+AQ72 -> 0 | AS72: =AK72+AR72 -> 612.1522 | AT72: =E72-AS72 -> 14901.848
B73: 04/25 | C73: emitir | D73: SUMMER | E73: =33317+2637 -> 35954 | F73: 5925 | G73: 2550 | H73: 2 | I73: 24 | J73: 26 | K73: =H73*I73*J73 -> 1248 | L73: 4 | M73: 20 | N73: 16 | O73: =L73*M73*N73 -> 1280 | P73: =K73+O73 -> 2528 | Q73: 2 | R73: 44.3 | S73: 26 | T73: =Q73*R73*S73 -> 2303.6 | U73: 4 | V73: 44.3 | W73: 16 | X73: =U73*V73*W73 -> 2835.2 | Y73: =T73+X73 -> 5138.8 | Z73: 2 | AA73: 40 | AB73: 2 | AC73: =Z73*AA73*AB73 -> 160 | AD73: 4 | AE73: 90 | AF73: 2 | AG73: =AD73*AE73*AF73 -> 720 | AH73: =AC73+AG73 -> 880 | AI73: =F73+G73+P73+Y73+AH73 -> 17021.8 | AJ73: =AI73/E73 -> 0.47343272 | AK73: =(E73-AI73)*$AK$15 -> 2082.542 | AL73: 0 | AM73: 0 | AN73: 0 | AO73: 0 | AP73: 0.0372 | AQ73: =AP73*E73 -> 1337.4888 | AR73: =AL73+AM73+AN73+AO73+AQ73 -> 1337.4888 | AS73: =AK73+AR73 -> 3420.0308 | AT73: =E73-AS73 -> 32533.969
B74: 04/25 | C74: 113 | D74: TAJ MAHAL_GO | E74: =40937 -> 40937 | F74: 7513.97 | G74: 5124.14 | H74: 6 | I74: 24 | J74: 26 | K74: =H74*I74*J74 -> 3744 | L74: 0 | M74: 0 | N74: 0 | O74: =L74*M74*N74 -> 0 | P74: =K74+O74 -> 3744 | Q74: 6 | R74: 44.3 | S74: 26 | T74: =Q74*R74*S74 -> 6910.8 | U74: 0 | V74: 0 | W74: 0 | X74: =U74*V74*W74 -> 0 | Y74: =T74+X74 -> 6910.8 | Z74: 6 | AA74: 90 | AB74: 2 | AC74: =Z74*AA74*AB74 -> 1080 | AD74: 0 | AE74: 0 | AF74: 0 | AG74: =AD74*AE74*AF74 -> 0 | AH74: =AC74+AG74 -> 1080 | AI74: =F74+G74+P74+Y74+AH74 -> 24372.91 | AJ74: =AI74/E74 -> 0.59537607 | AK74: =(E74-AI74)*$AK$15 -> 1822.0499 | AL74: 0 | AM74: 0 | AN74: 0 | AO74: 0 | AP74: 0 | AQ74: =AP74*E74 -> 0 | AR74: =AL74+AM74+AN74+AO74+AQ74 -> 0 | AS74: =AK74+AR74 -> 1822.0499 | AT74: =E74-AS74 -> 39114.95
B75: 04/25 | C75: 114 | D75: TAJ MAHAL_GO | E75: =6264 -> 6264 | F75: 1149.75 | G75: 784.07 | H75: 6 | I75: 3.68 | J75: 26 | K75: =H75*I75*J75 -> 574.08 | L75: 0 | M75: 0 | N75: 0 | O75: =L75*M75*N75 -> 0 | P75: =K75+O75 -> 574.08 | Q75: 6 | R75: 6.78 | S75: 26 | T75: =Q75*R75*S75 -> 1057.68 | U75: 0 | V75: 0 | W75: 0 | X75: =U75*V75*W75 -> 0 | Y75: =T75+X75 -> 1057.68 | Z75: 6 | AA75: 13.78 | AB75: 2 | AC75: =Z75*AA75*AB75 -> 165.36 | AD75: 0 | AE75: 0 | AF75: 0 | AG75: =AD75*AE75*AF75 -> 0 | AH75: =AC75+AG75 -> 165.36 | AI75: =F75+G75+P75+Y75+AH75 -> 3730.94 | AJ75: =AI75/E75 -> 0.59561622 | AK75: =(E75-AI75)*$AK$15 -> 278.6366 | AL75: 0 | AM75: 0 | AN75: 0 | AO75: 0 | AP75: 0 | AQ75: =AP75*E75 -> 0 | AR75: =AL75+AM75+AN75+AO75+AQ75 -> 0 | AS75: =AK75+AR75 -> 278.6366 | AT75: =E75-AS75 -> 5985.3634
B76: 04/25 | C76: 115 | D76: TAJ MAHAL CONSTRUÇÃO E INCORPORAÇÃO_GO | E76: =1562+380 -> 1942 | F76: 395.2 | G76: 0 | H76: 1 | I76: 24 | J76: 4 | K76: =H76*I76*J76 -> 96 | L76: 0 | M76: 0 | N76: 0 | O76: =L76*M76*N76 -> 0 | P76: =K76+O76 -> 96 | Q76: 1 | R76: 44.3 | S76: 4 | T76: =Q76*R76*S76 -> 177.2 | U76: 0 | V76: 0 | W76: 0 | X76: =U76*V76*W76 -> 0 | Y76: =T76+X76 -> 177.2 | Z76: 1 | AA76: 90 | AB76: 1 | AC76: =Z76*AA76*AB76 -> 90 | AD76: 0 | AE76: 0 | AF76: 0 | AG76: =AD76*AE76*AF76 -> 0 | AH76: =AC76+AG76 -> 90 | AI76: =F76+G76+P76+Y76+AH76 -> 758.4 | AJ76: =AI76/E76 -> 0.39052523 | AK76: =(E76-AI76)*$AK$15 -> 130.196 | AL76: 0 | AM76: 0 | AN76: 0 | AO76: 0 | AP76: 0 | AQ76: =AP76*E76 -> 0 | AR76: =AL76+AM76+AN76+AO76+AQ76 -> 0 | AS76: =AK76+AR76 -> 130.196 | AT76: =E76-AS76 -> 1811.804
B77: 04/25 | C77: 116 | D77: BELA VISTA | E77: =5964+664 -> 6628 | F77: 1043 | G77: 387 | H77: 1 | I77: 24 | J77: 26 | K77: =H77*I77*J77 -> 624 | L77: 0 | M77: 0 | N77: 0 | O77: =L77*M77*N77 -> 0 | P77: =K77+O77 -> 624 | Q77: 1 | R77: 44.3 | S77: 26 | T77: =Q77*R77*S77 -> 1151.8 | U77: 0 | V77: 0 | W77: 0 | X77: =U77*V77*W77 -> 0 | Y77: =T77+X77 -> 1151.8 | Z77: 1 | AA77: 90 | AB77: 2 | AC77: =Z77*AA77*AB77 -> 180 | AD77: 0 | AE77: 0 | AF77: 0 | AG77: =AD77*AE77*AF77 -> 0 | AH77: =AC77+AG77 -> 180 | AI77: =F77+G77+P77+Y77+AH77 -> 3385.8 | AJ77: =AI77/E77 -> 0.51083283 | AK77: =(E77-AI77)*$AK$15 -> 356.642 | AL77: 0 | AM77: 0 | AN77: 0 | AO77: 0 | AP77: 0.0356 | AQ77: =AP77*E77 -> 235.9568 | AR77: =AL77+AM77+AN77+AO77+AQ77 -> 235.9568 | AS77: =AK77+AR77 -> 592.5988 | AT77: =E77-AS77 -> 6035.4012
B78: 04/25 | C78: 117 | D78: VICENZA_GO | E78: =8960+2280 -> 11240 | F78: 1190 | G78: 410 | H78: 2 | I78: 24 | J78: 16 | K78: =H78*I78*J78 -> 768 | L78: 0 | M78: 0 | N78: 0 | O78: =L78*M78*N78 -> 0 | P78: =K78+O78 -> 768 | Q78: 2 | R78: 44.3 | S78: 16 | T78: =Q78*R78*S78 -> 1417.6 | U78: 0 | V78: 0 | W78: 0 | X78: =U78*V78*W78 -> 0 | Y78: =T78+X78 -> 1417.6 | Z78: 2 | AA78: 90 | AB78: 2 | AC78: =Z78*AA78*AB78 -> 360 | AD78: 0 | AE78: 0 | AF78: 0 | AG78: =AD78*AE78*AF78 -> 0 | AH78: =AC78+AG78 -> 360 | AI78: =F78+G78+P78+Y78+AH78 -> 4145.6 | AJ78: =AI78/E78 -> 0.36882562 | AK78: =(E78-AI78)*$AK$15 -> 780.384 | AL78: 0 | AM78: 0 | AN78: 0 | AO78: 0 | AP78: 0 | AQ78: =AP78*E78 -> 0 | AR78: =AL78+AM78+AN78+AO78+AQ78 -> 0 | AS78: =AK78+AR78 -> 780.384 | AT78: =E78-AS78 -> 10459.616
B79: 04/25 | C79: emitir | D79: SAFIRA | E79: 6104 | F79: 950.61 | G79: 351.9 | H79: 1 | I79: 24 | J79: 26 | K79: =H79*I79*J79 -> 624 | L79: 0 | M79: 0 | N79: 0 | O79: =L79*M79*N79 -> 0 | P79: =K79+O79 -> 624 | Q79: 1 | R79: 44.3 | S79: 26 | T79: =Q79*R79*S79 -> 1151.8 | U79: 0 | V79: 0 | W79: 0 | X79: =U79*V79*W79 -> 0 | Y79: =T79+X79 -> 1151.8 | Z79: 1 | AA79: 90 | AB79: 2 | AC79: =Z79*AA79*AB79 -> 180 | AD79: 0 | AE79: 0 | AF79: 0 | AG79: =AD79*AE79*AF79 -> 0 | AH79: =AC79+AG79 -> 180 | AI79: =F79+G79+P79+Y79+AH79 -> 3258.31 | AJ79: =AI79/E79 -> 0.53379915 | AK79: =(E79-AI79)*$AK$15 -> 313.0259 | AL79: 0 | AM79: 0 | AN79: 0 | AO79: 0 | AP79: 0.0356 | AQ79: =AP79*E79 -> 217.3024 | AR79: =AL79+AM79+AN79+AO79+AQ79 -> 217.3024 | AS79: =AK79+AR79 -> 530.3283 | AT79: =E79-AS79 -> 5573.6717
B81: 05/25 | C81: 119 | D81: AGROBRASIL_GO | E81: =11388 -> 11388 | F81: 871.39 | G81: 534.39 | H81: 4 | I81: 24 | J81: 26 | K81: =H81*I81*J81 -> 2496 | L81: 0 | M81: 0 | N81: 0 | O81: =L81*M81*N81 -> 0 | P81: =K81+O81 -> 2496 | Q81: 4 | R81: 44.3 | S81: 26 | T81: =Q81*R81*S81 -> 4607.2 | U81: 0 | V81: 0 | W81: 0 | X81: =U81*V81*W81 -> 0 | Y81: =T81+X81 -> 4607.2 | Z81: 4 | AA81: 90 | AB81: 4 | AC81: =Z81*AA81*AB81 -> 1440 | AD81: 0 | AE81: 0 | AF81: 0 | AG81: =AD81*AE81*AF81 -> 0 | AH81: =AC81+AG81 -> 1440 | AI81: =F81+G81+P81+Y81+AH81 -> 9948.98 | AJ81: =AI81/E81 -> 0.87363716 | AK81: =(E81-AI81)*$AK$15 -> 158.2922 | AL81: 0 | AM81: 0 | AN81: 0 | AO81: 0 | AP81: 0 | AQ81: =AP81*E81 -> 0 | AR81: =AL81+AM81+AN81+AO81+AQ81 -> 0 | AS81: =AK81+AR81 -> 158.2922 | AT81: =E81-AS81 -> 11229.708
B82: 05/25 | C82: 120 | D82: SUMMER | E82: =33317 -> 33317 | F82: 5925 | G82: 2550 | H82: 2 | I82: 24 | J82: 26 | K82: =H82*I82*J82 -> 1248 | L82: 4 | M82: 20 | N82: 16 | O82: =L82*M82*N82 -> 1280 | P82: =K82+O82 -> 2528 | Q82: 2 | R82: 44.3 | S82: 26 | T82: =Q82*R82*S82 -> 2303.6 | U82: 4 | V82: 44.3 | W82: 16 | X82: =U82*V82*W82 -> 2835.2 | Y82: =T82+X82 -> 5138.8 | Z82: 2 | AA82: 40 | AB82: 2 | AC82: =Z82*AA82*AB82 -> 160 | AD82: 4 | AE82: 90 | AF82: 2 | AG82: =AD82*AE82*AF82 -> 720 | AH82: =AC82+AG82 -> 880 | AI82: =F82+G82+P82+Y82+AH82 -> 17021.8 | AJ82: =AI82/E82 -> 0.51090434 | AK82: =(E82-AI82)*$AK$15 -> 1792.472 | AL82: 0 | AM82: 0 | AN82: 0 | AO82: 0 | AP82: 0.0372 | AQ82: =AP82*E82 -> 1239.3924 | AR82: =AL82+AM82+AN82+AO82+AQ82 -> 1239.3924 | AS82: =AK82+AR82 -> 3031.8644 | AT82: =E82-AS82 -> 30285.136 | AV82: 33228.5 | AW82: =AV82-AT82 -> 2943.3644
B83: 05/25 | C83: 121 | D83: TAJ MAHAL_GO | E83: 35740 | F83: 6560.0627 | G83: 4473.6244 | H83: 5 | I83: 24 | J83: 26 | K83: =H83*I83*J83 -> 3120 | L83: 0 | M83: 0 | N83: 0 | O83: =L83*M83*N83 -> 0 | P83: =K83+O83 -> 3120 | Q83: 5 | R83: 44.3 | S83: 26 | T83: =Q83*R83*S83 -> 5759 | U83: 0 | V83: 0 | W83: 0 | X83: =U83*V83*W83 -> 0 | Y83: =T83+X83 -> 5759 | Z83: 5 | AA83: 90 | AB83: 2 | AC83: =Z83*AA83*AB83 -> 900 | AD83: 0 | AE83: 0 | AF83: 0 | AG83: =AD83*AE83*AF83 -> 0 | AH83: =AC83+AG83 -> 900 | AI83: =F83+G83+P83+Y83+AH83 -> 20812.687 | AJ83: =AI83/E83 -> 0.58233596 | AK83: =(E83-AI83)*$AK$15 -> 1642.0044 | AL83: 0 | AM83: 0 | AN83: 0 | AO83: 0 | AP83: 0 | AQ83: =AP83*E83 -> 0 | AR83: =AL83+AM83+AN83+AO83+AQ83 -> 0 | AS83: =AK83+AR83 -> 1642.0044 | AT83: =E83-AS83 -> 34097.996
B84: 05/25 | C84: 122 | D84: TAJ MAHAL CONSTRUÇÃO E INCORPORAÇÃO_GO | E84: =1562 -> 1562 | F84: 395.2 | G84: 0 | H84: 1 | I84: 24 | J84: 4 | K84: =H84*I84*J84 -> 96 | L84: 0 | M84: 0 | N84: 0 | O84: =L84*M84*N84 -> 0 | P84: =K84+O84 -> 96 | Q84: 1 | R84: 44.3 | S84: 4 | T84: =Q84*R84*S84 -> 177.2 | U84: 0 | V84: 0 | W84: 0 | X84: =U84*V84*W84 -> 0 | Y84: =T84+X84 -> 177.2 | Z84: 1 | AA84: 90 | AB84: 1 | AC84: =Z84*AA84*AB84 -> 90 | AD84: 0 | AE84: 0 | AF84: 0 | AG84: =AD84*AE84*AF84 -> 0 | AH84: =AC84+AG84 -> 90 | AI84: =F84+G84+P84+Y84+AH84 -> 758.4 | AJ84: =AI84/E84 -> 0.48553137 | AK84: =(E84-AI84)*$AK$15 -> 88.396 | AL84: 0 | AM84: 0 | AN84: 0 | AO84: 0 | AP84: 0 | AQ84: =AP84*E84 -> 0 | AR84: =AL84+AM84+AN84+AO84+AQ84 -> 0 | AS84: =AK84+AR84 -> 88.396 | AT84: =E84-AS84 -> 1473.604
B85: 05/25 | C85: 123 | D85: BELA VISTA | E85: =5964 -> 5964 | F85: 1043 | G85: 387 | H85: 1 | I85: 24 | J85: 26 | K85: =H85*I85*J85 -> 624 | L85: 0 | M85: 0 | N85: 0 | O85: =L85*M85*N85 -> 0 | P85: =K85+O85 -> 624 | Q85: 1 | R85: 44.3 | S85: 26 | T85: =Q85*R85*S85 -> 1151.8 | U85: 0 | V85: 0 | W85: 0 | X85: =U85*V85*W85 -> 0 | Y85: =T85+X85 -> 1151.8 | Z85: 1 | AA85: 90 | AB85: 2 | AC85: =Z85*AA85*AB85 -> 180 | AD85: 0 | AE85: 0 | AF85: 0 | AG85: =AD85*AE85*AF85 -> 0 | AH85: =AC85+AG85 -> 180 | AI85: =F85+G85+P85+Y85+AH85 -> 3385.8 | AJ85: =AI85/E85 -> 0.56770624 | AK85: =(E85-AI85)*$AK$15 -> 283.602 | AL85: 0 | AM85: 0 | AN85: 0 | AO85: 0 | AP85: 0.0356 | AQ85: =AP85*E85 -> 212.3184 | AR85: =AL85+AM85+AN85+AO85+AQ85 -> 212.3184 | AS85: =AK85+AR85 -> 495.9204 | AT85: =E85-AS85 -> 5468.0796
B86: 05/25 | C86: 124 | D86: VICENZA_GO | E86: =8960 -> 8960 | F86: 1190 | G86: 410 | H86: 2 | I86: 24 | J86: 16 | K86: =H86*I86*J86 -> 768 | L86: 0 | M86: 0 | N86: 0 | O86: =L86*M86*N86 -> 0 | P86: =K86+O86 -> 768 | Q86: 2 | R86: 44.3 | S86: 16 | T86: =Q86*R86*S86 -> 1417.6 | U86: 0 | V86: 0 | W86: 0 | X86: =U86*V86*W86 -> 0 | Y86: =T86+X86 -> 1417.6 | Z86: 2 | AA86: 90 | AB86: 2 | AC86: =Z86*AA86*AB86 -> 360 | AD86: 0 | AE86: 0 | AF86: 0 | AG86: =AD86*AE86*AF86 -> 0 | AH86: =AC86+AG86 -> 360 | AI86: =F86+G86+P86+Y86+AH86 -> 4145.6 | AJ86: =AI86/E86 -> 0.46267857 | AK86: =(E86-AI86)*$AK$15 -> 529.584 | AL86: 0 | AM86: 0 | AN86: 0 | AO86: 0 | AP86: 0 | AQ86: =AP86*E86 -> 0 | AR86: =AL86+AM86+AN86+AO86+AQ86 -> 0 | AS86: =AK86+AR86 -> 529.584 | AT86: =E86-AS86 -> 8430.416
B87: 05/25 | C87: 125 | D87: SAFIRA | E87: 6104 | F87: 950.61 | G87: 351.9 | H87: 1 | I87: 24 | J87: 26 | K87: =H87*I87*J87 -> 624 | L87: 0 | M87: 0 | N87: 0 | O87: =L87*M87*N87 -> 0 | P87: =K87+O87 -> 624 | Q87: 1 | R87: 44.3 | S87: 26 | T87: =Q87*R87*S87 -> 1151.8 | U87: 0 | V87: 0 | W87: 0 | X87: =U87*V87*W87 -> 0 | Y87: =T87+X87 -> 1151.8 | Z87: 1 | AA87: 90 | AB87: 2 | AC87: =Z87*AA87*AB87 -> 180 | AD87: 0 | AE87: 0 | AF87: 0 | AG87: =AD87*AE87*AF87 -> 0 | AH87: =AC87+AG87 -> 180 | AI87: =F87+G87+P87+Y87+AH87 -> 3258.31 | AJ87: =AI87/E87 -> 0.53379915 | AK87: =(E87-AI87)*$AK$15 -> 313.0259 | AL87: 0 | AM87: 0 | AN87: 0 | AO87: 0 | AP87: 0.0356 | AQ87: =AP87*E87 -> 217.3024 | AR87: =AL87+AM87+AN87+AO87+AQ87 -> 217.3024 | AS87: =AK87+AR87 -> 530.3283 | AT87: =E87-AS87 -> 5573.6717
B89: 06/25 | C89: 126 | D89: AGROBRASIL_GO | E89: =11388 -> 11388 | F89: 871.39 | G89: 534.39 | H89: 4 | I89: 24 | J89: 26 | K89: =H89*I89*J89 -> 2496 | L89: 0 | M89: 0 | N89: 0 | O89: =L89*M89*N89 -> 0 | P89: =K89+O89 -> 2496 | Q89: 4 | R89: 44.3 | S89: 26 | T89: =Q89*R89*S89 -> 4607.2 | U89: 0 | V89: 0 | W89: 0 | X89: =U89*V89*W89 -> 0 | Y89: =T89+X89 -> 4607.2 | Z89: 4 | AA89: 90 | AB89: 4 | AC89: =Z89*AA89*AB89 -> 1440 | AD89: 0 | AE89: 0 | AF89: 0 | AG89: =AD89*AE89*AF89 -> 0 | AH89: =AC89+AG89 -> 1440 | AI89: =F89+G89+P89+Y89+AH89 -> 9948.98 | AJ89: =AI89/E89 -> 0.87363716 | AK89: =(E89-AI89)*$AK$15 -> 158.2922 | AL89: 0 | AM89: 0 | AN89: 0 | AO89: 0 | AP89: 0 | AQ89: =AP89*E89 -> 0 | AR89: =AL89+AM89+AN89+AO89+AQ89 -> 0 | AS89: =AK89+AR89 -> 158.2922 | AT89: =E89-AS89 -> 11229.708
B90: 06/25 | C90: 127 | D90: TAJ MAHAL_GO | E90: 35740 | F90: 6560.0627 | G90: 4473.6244 | H90: 5 | I90: 24 | J90: 26 | K90: =H90*I90*J90 -> 3120 | L90: 0 | M90: 0 | N90: 0 | O90: =L90*M90*N90 -> 0 | P90: =K90+O90 -> 3120 | Q90: 5 | R90: 44.3 | S90: 26 | T90: =Q90*R90*S90 -> 5759 | U90: 0 | V90: 0 | W90: 0 | X90: =U90*V90*W90 -> 0 | Y90: =T90+X90 -> 5759 | Z90: 5 | AA90: 90 | AB90: 2 | AC90: =Z90*AA90*AB90 -> 900 | AD90: 0 | AE90: 0 | AF90: 0 | AG90: =AD90*AE90*AF90 -> 0 | AH90: =AC90+AG90 -> 900 | AI90: =F90+G90+P90+Y90+AH90 -> 20812.687 | AJ90: =AI90/E90 -> 0.58233596 | AK90: =(E90-AI90)*$AK$15 -> 1642.0044 | AL90: 0 | AM90: 0 | AN90: 0 | AO90: 0 | AP90: 0 | AQ90: =AP90*E90 -> 0 | AR90: =AL90+AM90+AN90+AO90+AQ90 -> 0 | AS90: =AK90+AR90 -> 1642.0044 | AT90: =E90-AS90 -> 34097.996
B91: 06/25 | C91: 128 | D91: TAJ MAHAL CONSTRUÇÃO E INCORPORAÇÃO_GO | E91: =1562 -> 1562 | F91: 395.2 | G91: 0 | H91: 1 | I91: 24 | J91: 4 | K91: =H91*I91*J91 -> 96 | L91: 0 | M91: 0 | N91: 0 | O91: =L91*M91*N91 -> 0 | P91: =K91+O91 -> 96 | Q91: 1 | R91: 44.3 | S91: 4 | T91: =Q91*R91*S91 -> 177.2 | U91: 0 | V91: 0 | W91: 0 | X91: =U91*V91*W91 -> 0 | Y91: =T91+X91 -> 177.2 | Z91: 1 | AA91: 90 | AB91: 1 | AC91: =Z91*AA91*AB91 -> 90 | AD91: 0 | AE91: 0 | AF91: 0 | AG91: =AD91*AE91*AF91 -> 0 | AH91: =AC91+AG91 -> 90 | AI91: =F91+G91+P91+Y91+AH91 -> 758.4 | AJ91: =AI91/E91 -> 0.48553137 | AK91: =(E91-AI91)*$AK$15 -> 88.396 | AL91: 0 | AM91: 0 | AN91: 0 | AO91: 0 | AP91: 0 | AQ91: =AP91*E91 -> 0 | AR91: =AL91+AM91+AN91+AO91+AQ91 -> 0 | AS91: =AK91+AR91 -> 88.396 | AT91: =E91-AS91 -> 1473.604
B92: 06/25 | C92: 129 | D92: BELA VISTA | E92: =5964 -> 5964 | F92: 1043 | G92: 387 | H92: 1 | I92: 24 | J92: 26 | K92: =H92*I92*J92 -> 624 | L92: 0 | M92: 0 | N92: 0 | O92: =L92*M92*N92 -> 0 | P92: =K92+O92 -> 624 | Q92: 1 | R92: 44.3 | S92: 26 | T92: =Q92*R92*S92 -> 1151.8 | U92: 0 | V92: 0 | W92: 0 | X92: =U92*V92*W92 -> 0 | Y92: =T92+X92 -> 1151.8 | Z92: 1 | AA92: 90 | AB92: 2 | AC92: =Z92*AA92*AB92 -> 180 | AD92: 0 | AE92: 0 | AF92: 0 | AG92: =AD92*AE92*AF92 -> 0 | AH92: =AC92+AG92 -> 180 | AI92: =F92+G92+P92+Y92+AH92 -> 3385.8 | AJ92: =AI92/E92 -> 0.56770624 | AK92: =(E92-AI92)*$AK$15 -> 283.602 | AL92: 0 | AM92: 0 | AN92: 0 | AO92: 0 | AP92: 0.04 | AQ92: =AP92*E92 -> 238.56 | AR92: =AL92+AM92+AN92+AO92+AQ92 -> 238.56 | AS92: =AK92+AR92 -> 522.162 | AT92: =E92-AS92 -> 5441.838
B93: 06/25 | C93: 130 | D93: VICENZA_GO | E93: =8960 -> 8960 | F93: 1190 | G93: 410 | H93: 2 | I93: 24 | J93: 16 | K93: =H93*I93*J93 -> 768 | L93: 0 | M93: 0 | N93: 0 | O93: =L93*M93*N93 -> 0 | P93: =K93+O93 -> 768 | Q93: 2 | R93: 44.3 | S93: 16 | T93: =Q93*R93*S93 -> 1417.6 | U93: 0 | V93: 0 | W93: 0 | X93: =U93*V93*W93 -> 0 | Y93: =T93+X93 -> 1417.6 | Z93: 2 | AA93: 90 | AB93: 2 | AC93: =Z93*AA93*AB93 -> 360 | AD93: 0 | AE93: 0 | AF93: 0 | AG93: =AD93*AE93*AF93 -> 0 | AH93: =AC93+AG93 -> 360 | AI93: =F93+G93+P93+Y93+AH93 -> 4145.6 | AJ93: =AI93/E93 -> 0.46267857 | AK93: =(E93-AI93)*$AK$15 -> 529.584 | AL93: 0 | AM93: 0 | AN93: 0 | AO93: 0 | AP93: 0 | AQ93: =AP93*E93 -> 0 | AR93: =AL93+AM93+AN93+AO93+AQ93 -> 0 | AS93: =AK93+AR93 -> 529.584 | AT93: =E93-AS93 -> 8430.416
B94: 06/25 | C94: 131 | D94: SAFIRA | E94: 6104 | F94: 950.61 | G94: 351.9 | H94: 1 | I94: 24 | J94: 26 | K94: =H94*I94*J94 -> 624 | L94: 0 | M94: 0 | N94: 0 | O94: =L94*M94*N94 -> 0 | P94: =K94+O94 -> 624 | Q94: 1 | R94: 44.3 | S94: 26 | T94: =Q94*R94*S94 -> 1151.8 | U94: 0 | V94: 0 | W94: 0 | X94: =U94*V94*W94 -> 0 | Y94: =T94+X94 -> 1151.8 | Z94: 1 | AA94: 90 | AB94: 2 | AC94: =Z94*AA94*AB94 -> 180 | AD94: 0 | AE94: 0 | AF94: 0 | AG94: =AD94*AE94*AF94 -> 0 | AH94: =AC94+AG94 -> 180 | AI94: =F94+G94+P94+Y94+AH94 -> 3258.31 | AJ94: =AI94/E94 -> 0.53379915 | AK94: =(E94-AI94)*$AK$15 -> 313.0259 | AL94: 0 | AM94: 0 | AN94: 0 | AO94: 0 | AP94: 0.04 | AQ94: =AP94*E94 -> 244.16 | AR94: =AL94+AM94+AN94+AO94+AQ94 -> 244.16 | AS94: =AK94+AR94 -> 557.1859 | AT94: =E94-AS94 -> 5546.8141
B95: 06/25 | C95: 132 | D95: RIO PARANÃ | E95: =18328 -> 18328 | F95: 2550 | G95: 703.8 | H95: 1 | I95: 24 | J95: 26 | K95: =H95*I95*J95 -> 624 | L95: 2 | M95: 16 | N95: 16 | O95: =L95*M95*N95 -> 512 | P95: =K95+O95 -> 1136 | Q95: 1 | R95: 44.3 | S95: 26 | T95: =Q95*R95*S95 -> 1151.8 | U95: 2 | V95: 44.3 | W95: 16 | X95: =U95*V95*W95 -> 1417.6 | Y95: =T95+X95 -> 2569.4 | Z95: 1 | AA95: 80 | AB95: 2 | AC95: =Z95*AA95*AB95 -> 160 | AD95: 2 | AE95: 80 | AF95: 2 | AG95: =AD95*AE95*AF95 -> 320 | AH95: =AC95+AG95 -> 480 | AI95: =F95+G95+P95+Y95+AH95 -> 7439.2 | AJ95: =AI95/E95 -> 0.40589262 | AK95: =(E95-AI95)*$AK$15 -> 1197.768 | AL95: 0 | AM95: 0 | AN95: 0 | AO95: 0 | AP95: 0.04 | AQ95: =AP95*E95 -> 733.12 | AR95: =AL95+AM95+AN95+AO95+AQ95 -> 733.12 | AS95: =AK95+AR95 -> 1930.888 | AT95: =E95-AS95 -> 16397.112
B97: 07/25 | C97: 133 | D97: AGROBRASIL_GO | E97: =11388 -> 11388 | F97: 871.39 | G97: 534.39 | H97: 4 | I97: 24 | J97: 26 | K97: =H97*I97*J97 -> 2496 | L97: 0 | M97: 0 | N97: 0 | O97: =L97*M97*N97 -> 0 | P97: =K97+O97 -> 2496 | Q97: 4 | R97: 44.3 | S97: 26 | T97: =Q97*R97*S97 -> 4607.2 | U97: 0 | V97: 0 | W97: 0 | X97: =U97*V97*W97 -> 0 | Y97: =T97+X97 -> 4607.2 | Z97: 4 | AA97: 90 | AB97: 4 | AC97: =Z97*AA97*AB97 -> 1440 | AD97: 0 | AE97: 0 | AF97: 0 | AG97: =AD97*AE97*AF97 -> 0 | AH97: =AC97+AG97 -> 1440 | AI97: =F97+G97+P97+Y97+AH97 -> 9948.98 | AJ97: =AI97/E97 -> 0.87363716 | AK97: =(E97-AI97)*$AK$15 -> 158.2922 | AL97: 0 | AM97: 0 | AN97: 0 | AO97: 0 | AP97: 0 | AQ97: =AP97*E97 -> 0 | AR97: =AL97+AM97+AN97+AO97+AQ97 -> 0 | AS97: =AK97+AR97 -> 158.2922 | AT97: =E97-AS97 -> 11229.708
B98: 07/25 | C98: 134 | D98: TAJ MAHAL_GO | E98: 35740 | F98: 6560.0627 | G98: 4473.6244 | H98: 5 | I98: 24 | J98: 26 | K98: =H98*I98*J98 -> 3120 | L98: 0 | M98: 0 | N98: 0 | O98: =L98*M98*N98 -> 0 | P98: =K98+O98 -> 3120 | Q98: 5 | R98: 44.3 | S98: 26 | T98: =Q98*R98*S98 -> 5759 | U98: 0 | V98: 0 | W98: 0 | X98: =U98*V98*W98 -> 0 | Y98: =T98+X98 -> 5759 | Z98: 5 | AA98: 90 | AB98: 2 | AC98: =Z98*AA98*AB98 -> 900 | AD98: 0 | AE98: 0 | AF98: 0 | AG98: =AD98*AE98*AF98 -> 0 | AH98: =AC98+AG98 -> 900 | AI98: =F98+G98+P98+Y98+AH98 -> 20812.687 | AJ98: =AI98/E98 -> 0.58233596 | AK98: =(E98-AI98)*$AK$15 -> 1642.0044 | AL98: 0 | AM98: 0 | AN98: 0 | AO98: 0 | AP98: 0 | AQ98: =AP98*E98 -> 0 | AR98: =AL98+AM98+AN98+AO98+AQ98 -> 0 | AS98: =AK98+AR98 -> 1642.0044 | AT98: =E98-AS98 -> 34097.996
B99: 07/25 | C99: 135 | D99: TAJ MAHAL CONSTRUÇÃO E INCORPORAÇÃO_GO | E99: =1562 -> 1562 | F99: 395.2 | G99: 0 | H99: 1 | I99: 24 | J99: 4 | K99: =H99*I99*J99 -> 96 | L99: 0 | M99: 0 | N99: 0 | O99: =L99*M99*N99 -> 0 | P99: =K99+O99 -> 96 | Q99: 1 | R99: 44.3 | S99: 4 | T99: =Q99*R99*S99 -> 177.2 | U99: 0 | V99: 0 | W99: 0 | X99: =U99*V99*W99 -> 0 | Y99: =T99+X99 -> 177.2 | Z99: 1 | AA99: 90 | AB99: 1 | AC99: =Z99*AA99*AB99 -> 90 | AD99: 0 | AE99: 0 | AF99: 0 | AG99: =AD99*AE99*AF99 -> 0 | AH99: =AC99+AG99 -> 90 | AI99: =F99+G99+P99+Y99+AH99 -> 758.4 | AJ99: =AI99/E99 -> 0.48553137 | AK99: =(E99-AI99)*$AK$15 -> 88.396 | AL99: 0 | AM99: 0 | AN99: 0 | AO99: 0 | AP99: 0 | AQ99: =AP99*E99 -> 0 | AR99: =AL99+AM99+AN99+AO99+AQ99 -> 0 | AS99: =AK99+AR99 -> 88.396 | AT99: =E99-AS99 -> 1473.604
B100: 07/25 | C100: 136 | D100: BELA VISTA | E100: =5964 -> 5964 | F100: 1043 | G100: 387 | H100: 1 | I100: 24 | J100: 26 | K100: =H100*I100*J100 -> 624 | L100: 0 | M100: 0 | N100: 0 | O100: =L100*M100*N100 -> 0 | P100: =K100+O100 -> 624 | Q100: 1 | R100: 44.3 | S100: 26 | T100: =Q100*R100*S100 -> 1151.8 | U100: 0 | V100: 0 | W100: 0 | X100: =U100*V100*W100 -> 0 | Y100: =T100+X100 -> 1151.8 | Z100: 1 | AA100: 90 | AB100: 2 | AC100: =Z100*AA100*AB100 -> 180 | AD100: 0 | AE100: 0 | AF100: 0 | AG100: =AD100*AE100*AF100 -> 0 | AH100: =AC100+AG100 -> 180 | AI100: =F100+G100+P100+Y100+AH100 -> 3385.8 | AJ100: =AI100/E100 -> 0.56770624 | AK100: =(E100-AI100)*$AK$15 -> 283.602 | AL100: 0 | AM100: 0 | AN100: 0 | AO100: 0 | AP100: 0.0407 | AQ100: =AP100*E100 -> 242.7348 | AR100: =AL100+AM100+AN100+AO100+AQ100 -> 242.7348 | AS100: =AK100+AR100 -> 526.3368 | AT100: =E100-AS100 -> 5437.6632
B101: 07/25 | C101: 137 | D101: VICENZA_GO | E101: =8960 -> 8960 | F101: 1190 | G101: 410 | H101: 2 | I101: 24 | J101: 16 | K101: =H101*I101*J101 -> 768 | L101: 0 | M101: 0 | N101: 0 | O101: =L101*M101*N101 -> 0 | P101: =K101+O101 -> 768 | Q101: 2 | R101: 44.3 | S101: 16 | T101: =Q101*R101*S101 -> 1417.6 | U101: 0 | V101: 0 | W101: 0 | X101: =U101*V101*W101 -> 0 | Y101: =T101+X101 -> 1417.6 | Z101: 2 | AA101: 90 | AB101: 2 | AC101: =Z101*AA101*AB101 -> 360 | AD101: 0 | AE101: 0 | AF101: 0 | AG101: =AD101*AE101*AF101 -> 0 | AH101: =AC101+AG101 -> 360 | AI101: =F101+G101+P101+Y101+AH101 -> 4145.6 | AJ101: =AI101/E101 -> 0.46267857 | AK101: =(E101-AI101)*$AK$15 -> 529.584 | AL101: 0 | AM101: 0 | AN101: 0 | AO101: 0 | AP101: 0 | AQ101: =AP101*E101 -> 0 | AR101: =AL101+AM101+AN101+AO101+AQ101 -> 0 | AS101: =AK101+AR101 -> 529.584 | AT101: =E101-AS101 -> 8430.416
B102: 07/25 | C102: 138 | D102: SAFIRA | E102: 6104 | F102: 950.61 | G102: 351.9 | H102: 1 | I102: 24 | J102: 26 | K102: =H102*I102*J102 -> 624 | L102: 0 | M102: 0 | N102: 0 | O102: =L102*M102*N102 -> 0 | P102: =K102+O102 -> 624 | Q102: 1 | R102: 44.3 | S102: 26 | T102: =Q102*R102*S102 -> 1151.8 | U102: 0 | V102: 0 | W102: 0 | X102: =U102*V102*W102 -> 0 | Y102: =T102+X102 -> 1151.8 | Z102: 1 | AA102: 90 | AB102: 2 | AC102: =Z102*AA102*AB102 -> 180 | AD102: 0 | AE102: 0 | AF102: 0 | AG102: =AD102*AE102*AF102 -> 0 | AH102: =AC102+AG102 -> 180 | AI102: =F102+G102+P102+Y102+AH102 -> 3258.31 | AJ102: =AI102/E102 -> 0.53379915 | AK102: =(E102-AI102)*$AK$15 -> 313.0259 | AL102: 0 | AM102: 0 | AN102: 0 | AO102: 0 | AP102: 0.0407 | AQ102: =AP102*E102 -> 248.4328 | AR102: =AL102+AM102+AN102+AO102+AQ102 -> 248.4328 | AS102: =AK102+AR102 -> 561.4587 | AT102: =E102-AS102 -> 5542.5413
B103: 07/25 | C103: 139 | D103: RIO PARANÃ | E103: =18328 -> 18328 | F103: 2550 | G103: 703.8 | H103: 1 | I103: 24 | J103: 26 | K103: =H103*I103*J103 -> 624 | L103: 2 | M103: 16 | N103: 16 | O103: =L103*M103*N103 -> 512 | P103: =K103+O103 -> 1136 | Q103: 1 | R103: 44.3 | S103: 26 | T103: =Q103*R103*S103 -> 1151.8 | U103: 2 | V103: 44.3 | W103: 16 | X103: =U103*V103*W103 -> 1417.6 | Y103: =T103+X103 -> 2569.4 | Z103: 1 | AA103: 80 | AB103: 2 | AC103: =Z103*AA103*AB103 -> 160 | AD103: 2 | AE103: 80 | AF103: 2 | AG103: =AD103*AE103*AF103 -> 320 | AH103: =AC103+AG103 -> 480 | AI103: =F103+G103+P103+Y103+AH103 -> 7439.2 | AJ103: =AI103/E103 -> 0.40589262 | AK103: =(E103-AI103)*$AK$15 -> 1197.768 | AL103: 0 | AM103: 0 | AN103: 0 | AO103: 0 | AP103: 0.0407 | AQ103: =AP103*E103 -> 745.9496 | AR103: =AL103+AM103+AN103+AO103+AQ103 -> 745.9496 | AS103: =AK103+AR103 -> 1943.7176 | AT103: =E103-AS103 -> 16384.282
B105: 08/25 | C105: 140 | D105: AGROBRASIL_GO | E105: =11388 -> 11388 | F105: 871.39 | G105: 534.39 | H105: 4 | I105: 24 | J105: 26 | K105: =H105*I105*J105 -> 2496 | L105: 0 | M105: 0 | N105: 0 | O105: =L105*M105*N105 -> 0 | P105: =K105+O105 -> 2496 | Q105: 4 | R105: 44.3 | S105: 26 | T105: =Q105*R105*S105 -> 4607.2 | U105: 0 | V105: 0 | W105: 0 | X105: =U105*V105*W105 -> 0 | Y105: =T105+X105 -> 4607.2 | Z105: 4 | AA105: 90 | AB105: 4 | AC105: =Z105*AA105*AB105 -> 1440 | AD105: 0 | AE105: 0 | AF105: 0 | AG105: =AD105*AE105*AF105 -> 0 | AH105: =AC105+AG105 -> 1440 | AI105: =F105+G105+P105+Y105+AH105 -> 9948.98 | AJ105: =AI105/E105 -> 0.87363716 | AK105: =(E105-AI105)*$AK$15 -> 158.2922 | AL105: 0 | AM105: 0 | AN105: 0 | AO105: 0 | AP105: 0 | AQ105: =AP105*E105 -> 0 | AR105: =AL105+AM105+AN105+AO105+AQ105 -> 0 | AS105: =AK105+AR105 -> 158.2922 | AT105: =E105-AS105 -> 11229.708
B106: 08/25 | C106: 141 | D106: TAJ MAHAL_GO | E106: 35740 | F106: 6560.0627 | G106: 4473.6244 | H106: 5 | I106: 24 | J106: 26 | K106: =H106*I106*J106 -> 3120 | L106: 0 | M106: 0 | N106: 0 | O106: =L106*M106*N106 -> 0 | P106: =K106+O106 -> 3120 | Q106: 5 | R106: 44.3 | S106: 26 | T106: =Q106*R106*S106 -> 5759 | U106: 0 | V106: 0 | W106: 0 | X106: =U106*V106*W106 -> 0 | Y106: =T106+X106 -> 5759 | Z106: 5 | AA106: 90 | AB106: 2 | AC106: =Z106*AA106*AB106 -> 900 | AD106: 0 | AE106: 0 | AF106: 0 | AG106: =AD106*AE106*AF106 -> 0 | AH106: =AC106+AG106 -> 900 | AI106: =F106+G106+P106+Y106+AH106 -> 20812.687 | AJ106: =AI106/E106 -> 0.58233596 | AK106: =(E106-AI106)*$AK$15 -> 1642.0044 | AL106: 0 | AM106: 0 | AN106: 0 | AO106: 0 | AP106: 0 | AQ106: =AP106*E106 -> 0 | AR106: =AL106+AM106+AN106+AO106+AQ106 -> 0 | AS106: =AK106+AR106 -> 1642.0044 | AT106: =E106-AS106 -> 34097.996
B107: 08/25 | C107: 142 | D107: TAJ MAHAL CONSTRUÇÃO E INCORPORAÇÃO_GO | E107: =1562 -> 1562 | F107: 395.2 | G107: 0 | H107: 1 | I107: 24 | J107: 4 | K107: =H107*I107*J107 -> 96 | L107: 0 | M107: 0 | N107: 0 | O107: =L107*M107*N107 -> 0 | P107: =K107+O107 -> 96 | Q107: 1 | R107: 44.3 | S107: 4 | T107: =Q107*R107*S107 -> 177.2 | U107: 0 | V107: 0 | W107: 0 | X107: =U107*V107*W107 -> 0 | Y107: =T107+X107 -> 177.2 | Z107: 1 | AA107: 90 | AB107: 1 | AC107: =Z107*AA107*AB107 -> 90 | AD107: 0 | AE107: 0 | AF107: 0 | AG107: =AD107*AE107*AF107 -> 0 | AH107: =AC107+AG107 -> 90 | AI107: =F107+G107+P107+Y107+AH107 -> 758.4 | AJ107: =AI107/E107 -> 0.48553137 | AK107: =(E107-AI107)*$AK$15 -> 88.396 | AL107: 0 | AM107: 0 | AN107: 0 | AO107: 0 | AP107: 0 | AQ107: =AP107*E107 -> 0 | AR107: =AL107+AM107+AN107+AO107+AQ107 -> 0 | AS107: =AK107+AR107 -> 88.396 | AT107: =E107-AS107 -> 1473.604
B108: 08/25 | C108: 143 | D108: BELA VISTA | E108: =5964 -> 5964 | F108: 1043 | G108: 387 | H108: 1 | I108: 24 | J108: 26 | K108: =H108*I108*J108 -> 624 | L108: 0 | M108: 0 | N108: 0 | O108: =L108*M108*N108 -> 0 | P108: =K108+O108 -> 624 | Q108: 1 | R108: 44.3 | S108: 26 | T108: =Q108*R108*S108 -> 1151.8 | U108: 0 | V108: 0 | W108: 0 | X108: =U108*V108*W108 -> 0 | Y108: =T108+X108 -> 1151.8 | Z108: 1 | AA108: 90 | AB108: 2 | AC108: =Z108*AA108*AB108 -> 180 | AD108: 0 | AE108: 0 | AF108: 0 | AG108: =AD108*AE108*AF108 -> 0 | AH108: =AC108+AG108 -> 180 | AI108: =F108+G108+P108+Y108+AH108 -> 3385.8 | AJ108: =AI108/E108 -> 0.56770624 | AK108: =(E108-AI108)*$AK$15 -> 283.602 | AL108: 0 | AM108: 0 | AN108: 0 | AO108: 0 | AP108: 0.0414 | AQ108: =AP108*E108 -> 246.9096 | AR108: =AL108+AM108+AN108+AO108+AQ108 -> 246.9096 | AS108: =AK108+AR108 -> 530.5116 | AT108: =E108-AS108 -> 5433.4884
B109: 08/25 | C109: 144 | D109: VICENZA_GO | E109: =8960 -> 8960 | F109: 1190 | G109: 410 | H109: 2 | I109: 24 | J109: 16 | K109: =H109*I109*J109 -> 768 | L109: 0 | M109: 0 | N109: 0 | O109: =L109*M109*N109 -> 0 | P109: =K109+O109 -> 768 | Q109: 2 | R109: 44.3 | S109: 16 | T109: =Q109*R109*S109 -> 1417.6 | U109: 0 | V109: 0 | W109: 0 | X109: =U109*V109*W109 -> 0 | Y109: =T109+X109 -> 1417.6 | Z109: 2 | AA109: 90 | AB109: 2 | AC109: =Z109*AA109*AB109 -> 360 | AD109: 0 | AE109: 0 | AF109: 0 | AG109: =AD109*AE109*AF109 -> 0 | AH109: =AC109+AG109 -> 360 | AI109: =F109+G109+P109+Y109+AH109 -> 4145.6 | AJ109: =AI109/E109 -> 0.46267857 | AK109: =(E109-AI109)*$AK$15 -> 529.584 | AL109: 0 | AM109: 0 | AN109: 0 | AO109: 0 | AP109: 0 | AQ109: =AP109*E109 -> 0 | AR109: =AL109+AM109+AN109+AO109+AQ109 -> 0 | AS109: =AK109+AR109 -> 529.584 | AT109: =E109-AS109 -> 8430.416
B110: 08/25 | C110: 145 | D110: SAFIRA | E110: 6104 | F110: 950.61 | G110: 351.9 | H110: 1 | I110: 24 | J110: 26 | K110: =H110*I110*J110 -> 624 | L110: 0 | M110: 0 | N110: 0 | O110: =L110*M110*N110 -> 0 | P110: =K110+O110 -> 624 | Q110: 1 | R110: 44.3 | S110: 26 | T110: =Q110*R110*S110 -> 1151.8 | U110: 0 | V110: 0 | W110: 0 | X110: =U110*V110*W110 -> 0 | Y110: =T110+X110 -> 1151.8 | Z110: 1 | AA110: 90 | AB110: 2 | AC110: =Z110*AA110*AB110 -> 180 | AD110: 0 | AE110: 0 | AF110: 0 | AG110: =AD110*AE110*AF110 -> 0 | AH110: =AC110+AG110 -> 180 | AI110: =F110+G110+P110+Y110+AH110 -> 3258.31 | AJ110: =AI110/E110 -> 0.53379915 | AK110: =(E110-AI110)*$AK$15 -> 313.0259 | AL110: 0 | AM110: 0 | AN110: 0 | AO110: 0 | AP110: 0.0414 | AQ110: =AP110*E110 -> 252.7056 | AR110: =AL110+AM110+AN110+AO110+AQ110 -> 252.7056 | AS110: =AK110+AR110 -> 565.7315 | AT110: =E110-AS110 -> 5538.2685
B111: 08/25 | C111: 146 | D111: RIO PARANÃ | E111: =18328 -> 18328 | F111: 2550 | G111: 703.8 | H111: 1 | I111: 24 | J111: 26 | K111: =H111*I111*J111 -> 624 | L111: 2 | M111: 16 | N111: 16 | O111: =L111*M111*N111 -> 512 | P111: =K111+O111 -> 1136 | Q111: 1 | R111: 44.3 | S111: 26 | T111: =Q111*R111*S111 -> 1151.8 | U111: 2 | V111: 44.3 | W111: 16 | X111: =U111*V111*W111 -> 1417.6 | Y111: =T111+X111 -> 2569.4 | Z111: 1 | AA111: 80 | AB111: 2 | AC111: =Z111*AA111*AB111 -> 160 | AD111: 2 | AE111: 80 | AF111: 2 | AG111: =AD111*AE111*AF111 -> 320 | AH111: =AC111+AG111 -> 480 | AI111: =F111+G111+P111+Y111+AH111 -> 7439.2 | AJ111: =AI111/E111 -> 0.40589262 | AK111: =(E111-AI111)*$AK$15 -> 1197.768 | AL111: 0 | AM111: 0 | AN111: 0 | AO111: 0 | AP111: 0.0414 | AQ111: =AP111*E111 -> 758.7792 | AR111: =AL111+AM111+AN111+AO111+AQ111 -> 758.7792 | AS111: =AK111+AR111 -> 1956.5472 | AT111: =E111-AS111 -> 16371.453
B112: 08/25 | C112: 147 | D112: ISLA_COMP 07/25_18/07 à 31/07 | E112: =(5924/30)*14 -> 2764.5333 | F112: =1190/2 -> 595 | G112: =410/2 -> 205 | H112: 1 | I112: 24 | J112: 14 | K112: =H112*I112*J112 -> 336 | L112: 0 | M112: 0 | N112: 0 | O112: =L112*M112*N112 -> 0 | P112: =K112+O112 -> 336 | Q112: 1 | R112: 44.3 | S112: 14 | T112: =Q112*R112*S112 -> 620.2 | U112: 0 | V112: 0 | W112: 0 | X112: =U112*V112*W112 -> 0 | Y112: =T112+X112 -> 620.2 | Z112: 1 | AA112: 90 | AB112: 2 | AC112: =Z112*AA112*AB112 -> 180 | AD112: 0 | AE112: 0 | AF112: 0 | AG112: =AD112*AE112*AF112 -> 0 | AH112: =AC112+AG112 -> 180 | AI112: =F112+G112+P112+Y112+AH112 -> 1936.2 | AJ112: =AI112/E112 -> 0.70037137 | AK112: =(E112-AI112)*$AK$15 -> 91.116667 | AL112: 0 | AM112: 0 | AN112: 0 | AO112: 0 | AP112: 0 | AQ112: =AP112*E112 -> 0 | AR112: =AL112+AM112+AN112+AO112+AQ112 -> 0 | AS112: =AK112+AR112 -> 91.116667 | AT112: =E112-AS112 -> 2673.4167
B113: 08/25 | C113: 148 | D113: ISLA_01/08 à 30/08 | E113: =5924 -> 5924 | F113: 1190 | G113: 410 | H113: 1 | I113: 24 | J113: 26 | K113: =H113*I113*J113 -> 624 | L113: 0 | M113: 0 | N113: 0 | O113: =L113*M113*N113 -> 0 | P113: =K113+O113 -> 624 | Q113: 1 | R113: 44.3 | S113: 26 | T113: =Q113*R113*S113 -> 1151.8 | U113: 0 | V113: 0 | W113: 0 | X113: =U113*V113*W113 -> 0 | Y113: =T113+X113 -> 1151.8 | Z113: 1 | AA113: 90 | AB113: 2 | AC113: =Z113*AA113*AB113 -> 180 | AD113: 0 | AE113: 0 | AF113: 0 | AG113: =AD113*AE113*AF113 -> 0 | AH113: =AC113+AG113 -> 180 | AI113: =F113+G113+P113+Y113+AH113 -> 3555.8 | AJ113: =AI113/E113 -> 0.60023633 | AK113: =(E113-AI113)*$AK$15 -> 260.502 | AL113: 0 | AM113: 0 | AN113: 0 | AO113: 0 | AP113: 0 | AQ113: =AP113*E113 -> 0 | AR113: =AL113+AM113+AN113+AO113+AQ113 -> 0 | AS113: =AK113+AR113 -> 260.502 | AT113: =E113-AS113 -> 5663.498
B114: 08/25 | C114: 149 | D114: VICENTE AMPESSAN_GO | E114: =(5707/30)*14 -> 2663.2667 | F114: =1190/2 -> 595 | G114: =410/2 -> 205 | H114: 1 | I114: 24 | J114: 14 | K114: =H114*I114*J114 -> 336 | L114: 0 | M114: 0 | N114: 0 | O114: =L114*M114*N114 -> 0 | P114: =K114+O114 -> 336 | Q114: 1 | R114: 44.3 | S114: 14 | T114: =Q114*R114*S114 -> 620.2 | U114: 0 | V114: 0 | W114: 0 | X114: =U114*V114*W114 -> 0 | Y114: =T114+X114 -> 620.2 | Z114: 1 | AA114: 90 | AB114: 2 | AC114: =Z114*AA114*AB114 -> 180 | AD114: 0 | AE114: 0 | AF114: 0 | AG114: =AD114*AE114*AF114 -> 0 | AH114: =AC114+AG114 -> 180 | AI114: =F114+G114+P114+Y114+AH114 -> 1936.2 | AJ114: =AI114/E114 -> 0.72700193 | AK114: =(E114-AI114)*$AK$15 -> 79.977333 | AL114: 0 | AM114: 0 | AN114: 0 | AO114: 0 | AP114: 0 | AQ114: =AP114*E114 -> 0 | AR114: =AL114+AM114+AN114+AO114+AQ114 -> 0 | AS114: =AK114+AR114 -> 79.977333 | AT114: =E114-AS114 -> 2583.2893
B116: 09/25 | C116: 158 | D116: AGROBRASIL_GO | E116: =11388 -> 11388 | F116: 871.39 | G116: 534.39 | H116: 4 | I116: 24 | J116: 26 | K116: =H116*I116*J116 -> 2496 | L116: 0 | M116: 0 | N116: 0 | O116: =L116*M116*N116 -> 0 | P116: =K116+O116 -> 2496 | Q116: 4 | R116: 44.3 | S116: 26 | T116: =Q116*R116*S116 -> 4607.2 | U116: 0 | V116: 0 | W116: 0 | X116: =U116*V116*W116 -> 0 | Y116: =T116+X116 -> 4607.2 | Z116: 4 | AA116: 90 | AB116: 4 | AC116: =Z116*AA116*AB116 -> 1440 | AD116: 0 | AE116: 0 | AF116: 0 | AG116: =AD116*AE116*AF116 -> 0 | AH116: =AC116+AG116 -> 1440 | AI116: =F116+G116+P116+Y116+AH116 -> 9948.98 | AJ116: =AI116/E116 -> 0.87363716 | AK116: =(E116-AI116)*$AK$15 -> 158.2922 | AL116: 0 | AM116: 0 | AN116: 0 | AO116: 0 | AP116: 0 | AQ116: =AP116*E116 -> 0 | AR116: =AL116+AM116+AN116+AO116+AQ116 -> 0 | AS116: =AK116+AR116 -> 158.2922 | AT116: =E116-AS116 -> 11229.708 | AU116: ok
B117: 09/25 | C117: 150 | D117: TAJ MAHAL_GO | E117: 35740 | F117: 6560.0627 | G117: 4473.6244 | H117: 5 | I117: 24 | J117: 26 | K117: =H117*I117*J117 -> 3120 | L117: 0 | M117: 0 | N117: 0 | O117: =L117*M117*N117 -> 0 | P117: =K117+O117 -> 3120 | Q117: 5 | R117: 44.3 | S117: 26 | T117: =Q117*R117*S117 -> 5759 | U117: 0 | V117: 0 | W117: 0 | X117: =U117*V117*W117 -> 0 | Y117: =T117+X117 -> 5759 | Z117: 5 | AA117: 90 | AB117: 2 | AC117: =Z117*AA117*AB117 -> 900 | AD117: 0 | AE117: 0 | AF117: 0 | AG117: =AD117*AE117*AF117 -> 0 | AH117: =AC117+AG117 -> 900 | AI117: =F117+G117+P117+Y117+AH117 -> 20812.687 | AJ117: =AI117/E117 -> 0.58233596 | AK117: =(E117-AI117)*$AK$15 -> 1642.0044 | AL117: 0 | AM117: 0 | AN117: 0 | AO117: 0 | AP117: 0 | AQ117: =AP117*E117 -> 0 | AR117: =AL117+AM117+AN117+AO117+AQ117 -> 0 | AS117: =AK117+AR117 -> 1642.0044 | AT117: =E117-AS117 -> 34097.996
...

Sheet 2026_RECEITA_JJB ADM
B1: JJ BARBOSA ADMINISTRAÇÃO
B2: RECEITA
B4: CNAE-Fiscal: | D4: N812140000 _ LIMPEZA EM PREDIOS E EM DOMICILIOS
B5: ATIVIDADE MUNICIPIO: | D5: 710 - 7.10 - Limpeza, manutenção e conservação de vias e logradouros
B7: ANO: | C7: 2026 | D7: VERSÃO 2024.11.20
B8: CLIENTE: | C8: JJ BARBOSA ADMINISTRAÇÃO | E8: REGIME DE TRIBUTAÇÃO: | F8: SIMPLES NACIONAL
B9: CNPJ: | C9: 41.106.556/0001-44
B10: ENDEREÇO: | C10: ÁGUAS CLARAS
B11: TOTAL | C11: =E127 -> 50761
B13: COMP | C13: NF | D13: CLIENTE | E13: VALOR TOTAL DOS SERVIÇOS | F13: MATERIAS | G13: EQUIPAMENTOS | H13: VALE TRANSPORTE | Q13: VALE ALIMENTAÇÃO | Z13: UNIFORME | AI13: TOTAL BASE RETENÇÃO INSS | AJ13: BASE CÁCULO INSS | AK13: RETENÇÃO DESTACADO NA NF | AS13: TOTAL RETENÇÃO NF | AT13: VALOR LIQUIDO DA NOTA FISCAL
H14: 44H/S | L14: 12 X 36 | P14: TOTAL | Q14: 44H/S | U14: 12 X 36 | Y14: TOTAL | Z14: 44H/S | AD14: 12 X 36 | AH14: TOTAL | AK14: GPS 2632 | AL14: IRRJ 1001 | AM14: CSLL 1002 | AN14: COFINS 1004 | AO14: PIS 1005 | AP14: ISSQN 1732 | AR14: TOTAL
H15: QTDE | I15: $ UNIT | J15: DIAS | K15: TOTAL | L15: QTDE | M15: $ UNIT | N15: DIAS | O15: TOTAL | Q15: QTDE | R15: $ UNIT | S15: DIAS | T15: TOTAL | U15: QTDE | V15: $ UNIT | W15: DIAS | X15: TOTAL | Z15: QTDE | AA15: $ UNIT | AB15: ANO | AC15: TOTAL | AD15: QTDE | AE15: $ UNIT | AF15: ANO | AG15: TOTAL | AJ15: % | AK15: 0.11 | AL15: 0 | AM15: 0 | AN15: 0 | AO15: 0 | AP15: % | AQ15: $ | AR15: =SUBTOTAL(9,AL15:AQ15) -> 0 | AS15: =AK15+AR15 -> 0.11
B17: 01/24 | C17: 63 GRENWAY | D17: PORTO SEGURO | E17: 26672 | F17: 3022.7 | G17: 5470 | H17: 2 | I17: 16 | J17: 26 | K17: =H17*I17*J17 -> 832 | L17: 4 | M17: 16 | N17: 16 | O17: =L17*M17*N17 -> 1024 | P17: =K17+O17 -> 1856 | Q17: 2 | R17: 40.5 | S17: 26 | T17: =Q17*R17*S17 -> 2106 | U17: 4 | V17: 40.5 | W17: 16 | X17: =U17*V17*W17 -> 2592 | Y17: =T17+X17 -> 4698 | Z17: 2 | AA17: 80 | AB17: 1 | AC17: =Z17*AA17*AB17 -> 160 | AD17: 4 | AE17: 90 | AF17: 1 | AG17: =AD17*AE17*AF17 -> 360 | AH17: =AC17+AG17 -> 520 | AI17: =F17+G17+P17+Y17+AH17 -> 15566.7 | AJ17: =AI17/E17 -> 0.58363452 | AK17: =(E17-AI17)*$AK$15 -> 1221.583 | AL17: 0 | AM17: 0 | AN17: 0 | AO17: 0 | AP17: 0 | AQ17: =AP17*E17 -> 0 | AR17: =AL17+AM17+AN17+AO17+AQ17 -> 0 | AS17: =AK17+AR17 -> 1221.583 | AT17: =E17-AS17 -> 25450.417
B18: 01/24 | C18: 64 GRENWAY | D18: RPR 01 | E18: 10999 | F18: 1531.4 | G18: 2040 | H18: 2 | I18: 16 | J18: 26 | K18: =H18*I18*J18 -> 832 | L18: 0 | M18: 0 | N18: 0 | O18: =L18*M18*N18 -> 0 | P18: =K18+O18 -> 832 | Q18: 2 | R18: 40.5 | S18: 26 | T18: =Q18*R18*S18 -> 2106 | U18: 0 | V18: 0 | W18: 0 | X18: =U18*V18*W18 -> 0 | Y18: =T18+X18 -> 2106 | Z18: 2 | AA18: 80 | AB18: 1 | AC18: =Z18*AA18*AB18 -> 160 | AD18: 0 | AE18: 0 | AF18: 0 | AG18: =AD18*AE18*AF18 -> 0 | AH18: =AC18+AG18 -> 160 | AI18: =F18+G18+P18+Y18+AH18 -> 6669.4 | AJ18: =AI18/E18 -> 0.60636421 | AK18: =(E18-AI18)*$AK$15 -> 476.256 | AL18: 0 | AM18: 0 | AN18: 0 | AO18: 0 | AP18: 0.05 | AQ18: =AP18*E18 -> 549.95 | AR18: =AL18+AM18+AN18+AO18+AQ18 -> 549.95 | AS18: =AK18+AR18 -> 1026.206 | AT18: =E18-AS18 -> 9972.794
B19: 01/24 | C19: 66 GRENWAY | D19: SHCES 509 BL B | E19: 4920 | F19: 0 | G19: 0 | H19: 1 | I19: 16 | J19: 26 | K19: =H19*I19*J19 -> 416 | L19: 0 | M19: 0 | N19: 0 | O19: =L19*M19*N19 -> 0 | P19: =K19+O19 -> 416 | Q19: 1 | R19: 40.5 | S19: 26 | T19: =Q19*R19*S19 -> 1053 | U19: 0 | V19: 0 | W19: 0 | X19: =U19*V19*W19 -> 0 | Y19: =T19+X19 -> 1053 | Z19: 0 | AA19: 0 | AB19: 0 | AC19: =Z19*AA19*AB19 -> 0 | AD19: 0 | AE19: 0 | AF19: 0 | AG19: =AD19*AE19*AF19 -> 0 | AH19: =AC19+AG19 -> 0 | AI19: =F19+G19+P19+Y19+AH19 -> 1469 | AJ19: =AI19/E19 -> 0.29857724 | AK19: 379.33 | AL19: 0 | AM19: 0 | AN19: 0 | AO19: 0 | AP19: 0.05 | AQ19: =AP19*E19 -> 246 | AR19: =AL19+AM19+AN19+AO19+AQ19 -> 246 | AS19: =AK19+AR19 -> 625.33 | AT19: =E19-AS19 -> 4294.67
B20: 02/24 | C20: 67 | D20: SHCES 509 BL B | E20: 5392 | F20: 0 | G20: 0 | H20: 1 | I20: 19.53 | J20: 26 | K20: =H20*I20*J20 -> 507.78 | L20: 0 | M20: 0 | N20: 0 | O20: =L20*M20*N20 -> 0 | P20: =K20+O20 -> 507.78 | Q20: 1 | R20: 42.5 | S20: 26 | T20: =Q20*R20*S20 -> 1105 | U20: 0 | V20: 0 | W20: 0 | X20: =U20*V20*W20 -> 0 | Y20: =T20+X20 -> 1105 | Z20: 0 | AA20: 0 | AB20: 0 | AC20: =Z20*AA20*AB20 -> 0 | AD20: 0 | AE20: 0 | AF20: 0 | AG20: =AD20*AE20*AF20 -> 0 | AH20: =AC20+AG20 -> 0 | AI20: =F20+G20+P20+Y20+AH20 -> 1612.78 | AJ20: =AI20/E20 -> 0.29910608 | AK20: =(E20-AI20)*$AK$15 -> 415.7142 | AL20: 0 | AM20: 0 | AN20: 0 | AO20: 0 | AP20: 0.031700668 | AQ20: =AP20*E20 -> 170.93 | AR20: =AL20+AM20+AN20+AO20+AQ20 -> 170.93 | AS20: =AK20+AR20 -> 586.6442 | AT20: =E20-AS20 -> 4805.3558
B21: 02/24 | C21: 69 | D21: RPR 01 | E21: 11906 | F21: 1977.4 | G21: 2040 | H21: 2 | I21: 16 | J21: 26 | K21: =H21*I21*J21 -> 832 | L21: 0 | M21: 0 | N21: 0 | O21: =L21*M21*N21 -> 0 | P21: =K21+O21 -> 832 | Q21: 2 | R21: 42.5 | S21: 26 | T21: =Q21*R21*S21 -> 2210 | U21: 0 | V21: 0 | W21: 0 | X21: =U21*V21*W21 -> 0 | Y21: =T21+X21 -> 2210 | Z21: 2 | AA21: 80 | AB21: 1 | AC21: =Z21*AA21*AB21 -> 160 | AD21: 0 | AE21: 0 | AF21: 0 | AG21: =AD21*AE21*AF21 -> 0 | AH21: =AC21+AG21 -> 160 | AI21: =F21+G21+P21+Y21+AH21 -> 7219.4 | AJ21: =AI21/E21 -> 0.60636654 | AK21: =(E21-AI21)*$AK$15 -> 515.526 | AL21: 0 | AM21: 0 | AN21: 0 | AO21: 0 | AP21: 0.031700668 | AQ21: =AP21*E21 -> 377.42815 | AR21: =AL21+AM21+AN21+AO21+AQ21 -> 377.42815 | AS21: =AK21+AR21 -> 892.95415 | AT21: =E21-AS21 -> 11013.046
B22: 02/24 | C22: 71 | D22: PORTO SEGURO | E22: 28822 | F22: 2042.9 | G22: 2915 | H22: 2 | I22: 24 | J22: 26 | K22: =H22*I22*J22 -> 1248 | L22: 4 | M22: 16 | N22: 16 | O22: =L22*M22*N22 -> 1024 | P22: =K22+O22 -> 2272 | Q22: 2 | R22: 42.5 | S22: 26 | T22: =Q22*R22*S22 -> 2210 | U22: 4 | V22: 42.5 | W22: 16 | X22: =U22*V22*W22 -> 2720 | Y22: =T22+X22 -> 4930 | Z22: 2 | AA22: 80 | AB22: 1 | AC22: =Z22*AA22*AB22 -> 160 | AD22: 4 | AE22: 90 | AF22: 1 | AG22: =AD22*AE22*AF22 -> 360 | AH22: =AC22+AG22 -> 520 | AI22: =F22+G22+P22+Y22+AH22 -> 12679.9 | AJ22: =AI22/E22 -> 0.43993824 | AK22: =(E22-AI22)*$AK$15 -> 1775.631 | AL22: 0 | AM22: 0 | AN22: 0 | AO22: 0 | AP22: 0.031700668 | AQ22: =AP22*E22 -> 913.67664 | AR22: =AL22+AM22+AN22+AO22+AQ22 -> 913.67664 | AS22: =AK22+AR22 -> 2689.3076 | AT22: =E22-AS22 -> 26132.692
B23: 02/24 | C23: 72 | D23: PORTO SEGURO | E23: 2150 | F23: 945.87 | G23: 0 | H23: 0 | I23: 0 | J23: 0 | K23: =H23*I23*J23 -> 0 | L23: 0 | M23: 0 | N23: 0 | O23: =L23*M23*N23 -> 0 | P23: =K23+O23 -> 0 | Q23: 0 | R23: 0 | S23: 0 | T23: =Q23*R23*S23 -> 0 | U23: 0 | V23: 0 | W23: 0 | X23: =U23*V23*W23 -> 0 | Y23: =T23+X23 -> 0 | Z23: 0 | AA23: 0 | AB23: 0 | AC23: =Z23*AA23*AB23 -> 0 | AD23: 0 | AE23: 0 | AF23: 0 | AG23: =AD23*AE23*AF23 -> 0 | AH23: =AC23+AG23 -> 0 | AI23: =F23+G23+P23+Y23+AH23 -> 945.87 | AJ23: =AI23/E23 -> 0.43993953 | AK23: =(E23-AI23)*$AK$15 -> 132.4543 | AL23: 0 | AM23: 0 | AN23: 0 | AO23: 0 | AP23: 0.031700668 | AQ23: =AP23*E23 -> 68.156435 | AR23: =AL23+AM23+AN23+AO23+AQ23 -> 68.156435 | AS23: =AK23+AR23 -> 200.61074 | AT23: =E23-AS23 -> 1949.3893
B24: 02/24 | C24: 73 | D24: RPR 01 | E24: 907 | F24: 549.97 | G24: 0 | H24: 0 | I24: 0 | J24: 0 | K24: =H24*I24*J24 -> 0 | L24: 0 | M24: 0 | N24: 0 | O24: =L24*M24*N24 -> 0 | P24: =K24+O24 -> 0 | Q24: 0 | R24: 0 | S24: 0 | T24: =Q24*R24*S24 -> 0 | U24: 0 | V24: 0 | W24: 0 | X24: =U24*V24*W24 -> 0 | Y24: =T24+X24 -> 0 | Z24: 0 | AA24: 0 | AB24: 0 | AC24: =Z24*AA24*AB24 -> 0 | AD24: 0 | AE24: 0 | AF24: 0 | AG24: =AD24*AE24*AF24 -> 0 | AH24: =AC24+AG24 -> 0 | AI24: =F24+G24+P24+Y24+AH24 -> 549.97 | AJ24: =AI24/E24 -> 0.60636163 | AK24: =(E24-AI24)*$AK$15 -> 39.2733 | AL24: 0 | AM24: 0 | AN24: 0 | AO24: 0 | AP24: 0.031700668 | AQ24: =AP24*E24 -> 28.752506 | AR24: =AL24+AM24+AN24+AO24+AQ24 -> 28.752506 | AS24: =AK24+AR24 -> 68.025806 | AT24: =E24-AS24 -> 838.97419
B25: 02/24 | C25: 74 | D25: SHCES 509 BL B | E25: 472 | F25: 141.18 | G25: 0 | H25: 0 | I25: 0 | J25: 0 | K25: =H25*I25*J25 -> 0 | L25: 0 | M25: 0 | N25: 0 | O25: =L25*M25*N25 -> 0 | P25: =K25+O25 -> 0 | Q25: 0 | R25: 0 | S25: 0 | T25: =Q25*R25*S25 -> 0 | U25: 0 | V25: 0 | W25: 0 | X25: =U25*V25*W25 -> 0 | Y25: =T25+X25 -> 0 | Z25: 0 | AA25: 0 | AB25: 0 | AC25: =Z25*AA25*AB25 -> 0 | AD25: 0 | AE25: 0 | AF25: 0 | AG25: =AD25*AE25*AF25 -> 0 | AH25: =AC25+AG25 -> 0 | AI25: =F25+G25+P25+Y25+AH25 -> 141.18 | AJ25: =AI25/E25 -> 0.29911017 | AK25: =(E25-AI25)*$AK$15 -> 36.3902 | AL25: 0 | AM25: 0 | AN25: 0 | AO25: 0 | AP25: 0.031700668 | AQ25: =AP25*E25 -> 14.962715 | AR25: =AL25+AM25+AN25+AO25+AQ25 -> 14.962715 | AS25: =AK25+AR25 -> 51.352915 | AT25: =E25-AS25 -> 420.64708
B26: 03/24 | C26: 75 | D26: SHCES 509 BL B | E26: 5392 | F26: 0 | G26: 0 | H26: 1 | I26: 19.53 | J26: 26 | K26: =H26*I26*J26 -> 507.78 | L26: 0 | M26: 0 | N26: 0 | O26: =L26*M26*N26 -> 0 | P26: =K26+O26 -> 507.78 | Q26: 1 | R26: 42.5 | S26: 26 | T26: =Q26*R26*S26 -> 1105 | U26: 0 | V26: 0 | W26: 0 | X26: =U26*V26*W26 -> 0 | Y26: =T26+X26 -> 1105 | Z26: 0 | AA26: 0 | AB26: 0 | AC26: =Z26*AA26*AB26 -> 0 | AD26: 0 | AE26: 0 | AF26: 0 | AG26: =AD26*AE26*AF26 -> 0 | AH26: =AC26+AG26 -> 0 | AI26: =F26+G26+P26+Y26+AH26 -> 1612.78 | AJ26: =AI26/E26 -> 0.29910608 | AK26: =(E26-AI26)*$AK$15 -> 415.7142 | AL26: 0 | AM26: 0 | AN26: 0 | AO26: 0 | AP26: 0.031700668 | AQ26: =AP26*E26 -> 170.93 | AR26: =AL26+AM26+AN26+AO26+AQ26 -> 170.93 | AS26: =AK26+AR26 -> 586.6442 | AT26: =E26-AS26 -> 4805.3558
B27: 03/24 | C27: 76 | D27: RPR 01 | E27: 11906 | F27: 1977.4 | G27: 2040 | H27: 2 | I27: 16 | J27: 26 | K27: =H27*I27*J27 -> 832 | L27: 0 | M27: 0 | N27: 0 | O27: =L27*M27*N27 -> 0 | P27: =K27+O27 -> 832 | Q27: 2 | R27: 42.5 | S27: 26 | T27: =Q27*R27*S27 -> 2210 | U27: 0 | V27: 0 | W27: 0 | X27: =U27*V27*W27 -> 0 | Y27: =T27+X27 -> 2210 | Z27: 2 | AA27: 80 | AB27: 1 | AC27: =Z27*AA27*AB27 -> 160 | AD27: 0 | AE27: 0 | AF27: 0 | AG27: =AD27*AE27*AF27 -> 0 | AH27: =AC27+AG27 -> 160 | AI27: =F27+G27+P27+Y27+AH27 -> 7219.4 | AJ27: =AI27/E27 -> 0.60636654 | AK27: =(E27-AI27)*$AK$15 -> 515.526 | AL27: 0 | AM27: 0 | AN27: 0 | AO27: 0 | AP27: 0.031700668 | AQ27: =AP27*E27 -> 377.42815 | AR27: =AL27+AM27+AN27+AO27+AQ27 -> 377.42815 | AS27: =AK27+AR27 -> 892.95415 | AT27: =E27-AS27 -> 11013.046
B28: 03/24 | C28: 77 | D28: PORTO SEGURO | E28: 28822 | F28: 2042.9 | G28: 2915 | H28: 2 | I28: 24 | J28: 26 | K28: =H28*I28*J28 -> 1248 | L28: 4 | M28: 16 | N28: 16 | O28: =L28*M28*N28 -> 1024 | P28: =K28+O28 -> 2272 | Q28: 2 | R28: 42.5 | S28: 26 | T28: =Q28*R28*S28 -> 2210 | U28: 4 | V28: 42.5 | W28: 16 | X28: =U28*V28*W28 -> 2720 | Y28: =T28+X28 -> 4930 | Z28: 2 | AA28: 80 | AB28: 1 | AC28: =Z28*AA28*AB28 -> 160 | AD28: 4 | AE28: 90 | AF28: 1 | AG28: =AD28*AE28*AF28 -> 360 | AH28: =AC28+AG28 -> 520 | AI28: =F28+G28+P28+Y28+AH28 -> 12679.9 | AJ28: =AI28/E28 -> 0.43993824 | AK28: =(E28-AI28)*$AK$15 -> 1775.631 | AL28: 0 | AM28: 0 | AN28: 0 | AO28: 0 | AP28: 0.031700668 | AQ28: =AP28*E28 -> 913.67664 | AR28: =AL28+AM28+AN28+AO28+AQ28 -> 913.67664 | AS28: =AK28+AR28 -> 2689.3076 | AT28: =E28-AS28 -> 26132.692
B29: 04/24 | C29: 79 | D29: SHCES 509 BL B | E29: 5392 | F29: 0 | G29: 0 | H29: 1 | I29: 19.53 | J29: 26 | K29: =H29*I29*J29 -> 507.78 | L29: 0 | M29: 0 | N29: 0 | O29: =L29*M29*N29 -> 0 | P29: =K29+O29 -> 507.78 | Q29: 1 | R29: 42.5 | S29: 26 | T29: =Q29*R29*S29 -> 1105 | U29: 0 | V29: 0 | W29: 0 | X29: =U29*V29*W29 -> 0 | Y29: =T29+X29 -> 1105 | Z29: 0 | AA29: 0 | AB29: 0 | AC29: =Z29*AA29*AB29 -> 0 | AD29: 0 | AE29: 0 | AF29: 0 | AG29: =AD29*AE29*AF29 -> 0 | AH29: =AC29+AG29 -> 0 | AI29: =F29+G29+P29+Y29+AH29 -> 1612.78 | AJ29: =AI29/E29 -> 0.29910608 | AK29: =(E29-AI29)*$AK$15 -> 415.7142 | AL29: 0 | AM29: 0 | AN29: 0 | AO29: 0 | AP29: 0.031700668 | AQ29: =AP29*E29 -> 170.93 | AR29: =AL29+AM29+AN29+AO29+AQ29 -> 170.93 | AS29: =AK29+AR29 -> 586.6442 | AT29: =E29-AS29 -> 4805.3558
B30: 04/24 | C30: 80 | D30: RPR 01 | E30: 11906 | F30: 1977.4 | G30: 2040 | H30: 2 | I30: 16 | J30: 26 | K30: =H30*I30*J30 -> 832 | L30: 0 | M30: 0 | N30: 0 | O30: =L30*M30*N30 -> 0 | P30: =K30+O30 -> 832 | Q30: 2 | R30: 42.5 | S30: 26 | T30: =Q30*R30*S30 -> 2210 | U30: 0 | V30: 0 | W30: 0 | X30: =U30*V30*W30 -> 0 | Y30: =T30+X30 -> 2210 | Z30: 2 | AA30: 80 | AB30: 1 | AC30: =Z30*AA30*AB30 -> 160 | AD30: 0 | AE30: 0 | AF30: 0 | AG30: =AD30*AE30*AF30 -> 0 | AH30: =AC30+AG30 -> 160 | AI30: =F30+G30+P30+Y30+AH30 -> 7219.4 | AJ30: =AI30/E30 -> 0.60636654 | AK30: =(E30-AI30)*$AK$15 -> 515.526 | AL30: 0 | AM30: 0 | AN30: 0 | AO30: 0 | AP30: 0.031700668 | AQ30: =AP30*E30 -> 377.42815 | AR30: =AL30+AM30+AN30+AO30+AQ30 -> 377.42815 | AS30: =AK30+AR30 -> 892.95415 | AT30: =E30-AS30 -> 11013.046
B31: 04/24 | C31: 81 | D31: PORTO SEGURO | E31: 28822 | F31: 2042.9 | G31: 2915 | H31: 2 | I31: 24 | J31: 26 | K31: =H31*I31*J31 -> 1248 | L31: 4 | M31: 16 | N31: 16 | O31: =L31*M31*N31 -> 1024 | P31: =K31+O31 -> 2272 | Q31: 2 | R31: 42.5 | S31: 26 | T31: =Q31*R31*S31 -> 2210 | U31: 4 | V31: 42.5 | W31: 16 | X31: =U31*V31*W31 -> 2720 | Y31: =T31+X31 -> 4930 | Z31: 2 | AA31: 80 | AB31: 1 | AC31: =Z31*AA31*AB31 -> 160 | AD31: 4 | AE31: 90 | AF31: 1 | AG31: =AD31*AE31*AF31 -> 360 | AH31: =AC31+AG31 -> 520 | AI31: =F31+G31+P31+Y31+AH31 -> 12679.9 | AJ31: =AI31/E31 -> 0.43993824 | AK31: =(E31-AI31)*$AK$15 -> 1775.631 | AL31: 0 | AM31: 0 | AN31: 0 | AO31: 0 | AP31: 0.031700668 | AQ31: =AP31*E31 -> 913.67664 | AR31: =AL31+AM31+AN31+AO31+AQ31 -> 913.67664 | AS31: =AK31+AR31 -> 2689.3076 | AT31: =E31-AS31 -> 26132.692
... B49: 10/24 | C49: 103 | D49: PORTO SEGURO | E49: 30822 | F49: 5625.8 | G49: 2550 | H49: 2 | I49: 24 | J49: 26 | K49: =H49*I49*J49 -> 1248 | L49: 4 | M49: 16 | N49: 16 | O49: =L49*M49*N49 -> 1024 | P49: =K49+O49 -> 2272 | Q49: 2 | R49: 42.5 | S49: 26 | T49: =Q49*R49*S49 -> 2210 | U49: 4 | V49: 42.5 | W49: 16 | X49: =U49*V49*W49 -> 2720 | Y49: =T49+X49 -> 4930 | Z49: 2 | AA49: 80 | AB49: 2 | AC49: =Z49*AA49*AB49 -> 320 | AD49: 4 | AE49: 90 | AF49: 2 | AG49: =AD49*AE49*AF49 -> 720 | AH49: =AC49+AG49 -> 1040 | AI49: =F49+G49+P49+Y49+AH49 -> 16417.8 | AJ49: =AI49/E49 -> 0.53266498 | AK49: =(E49-AI49)*$AK$15 -> 1584.462 | AL49: 0 | AM49: 0 | AN49: 0 | AO49: 0 | AP49: 0.0316 | AQ49: =AP49*E49 -> 973.9752 | AR49: =AL49+AM49+AN49+AO49+AQ49 -> 973.9752 | AS49: =AK49+AR49 -> 2558.4372 | AT49: =E49-AS49 -> 28263.563
B50: 11/24 | C50: 104 | D50: SHCES 509 BL B | E50: 5392 | F50: 0 | G50: 0 | H50: 1 | I50: 24 | J50: 26 | K50: =H50*I50*J50 -> 624 | L50: 0 | M50: 0 | N50: 0 | O50: =L50*M50*N50 -> 0 | P50: =K50+O50 -> 624 | Q50: 1 | R50: 42.5 | S50: 26 | T50: =Q50*R50*S50 -> 1105 | U50: 0 | V50: 0 | W50: 0 | X50: =U50*V50*W50 -> 0 | Y50: =T50+X50 -> 1105 | Z50: 0 | AA50: 0 | AB50: 0 | AC50: =Z50*AA50*AB50 -> 0 | AD50: 0 | AE50: 0 | AF50: 0 | AG50: =AD50*AE50*AF50 -> 0 | AH50: =AC50+AG50 -> 0 | AI50: =F50+G50+P50+Y50+AH50 -> 1729 | AJ50: =AI50/E50 -> 0.32066024 | AK50: =(E50-AI50)*$AK$15 -> 402.93 | AL50: 0 | AM50: 0 | AN50: 0 | AO50: 0 | AP50: 0.032099407 | AQ50: =AP50*E50 -> 173.08 | AR50: =AL50+AM50+AN50+AO50+AQ50 -> 173.08 | AS50: =AK50+AR50 -> 576.01 | AT50: =E50-AS50 -> 4815.99 | AV50: 173.08 | AW50: =AV50/E50 -> 0.032099407
B51: 11/24 | C51: 105 | D51: RPR 01 | E51: 11906 | F51: 1977.4 | G51: 2040 | H51: 2 | I51: 24 | J51: 26 | K51: =H51*I51*J51 -> 1248 | L51: 0 | M51: 0 | N51: 0 | O51: =L51*M51*N51 -> 0 | P51: =K51+O51 -> 1248 | Q51: 2 | R51: 42.5 | S51: 26 | T51: =Q51*R51*S51 -> 2210 | U51: 0 | V51: 0 | W51: 0 | X51: =U51*V51*W51 -> 0 | Y51: =T51+X51 -> 2210 | Z51: 2 | AA51: 80 | AB51: 2 | AC51: =Z51*AA51*AB51 -> 320 | AD51: 0 | AE51: 0 | AF51: 0 | AG51: =AD51*AE51*AF51 -> 0 | AH51: =AC51+AG51 -> 320 | AI51: =F51+G51+P51+Y51+AH51 -> 7795.4 | AJ51: =AI51/E51 -> 0.65474551 | AK51: =(E51-AI51)*$AK$15 -> 452.166 | AL51: 0 | AM51: 0 | AN51: 0 | AO51: 0 | AP51: 0.032099407 | AQ51: =AP51*E51 -> 382.17553 | AR51: =AL51+AM51+AN51+AO51+AQ51 -> 382.17553 | AS51: =AK51+AR51 -> 834.34153 | AT51: =E51-AS51 -> 11071.658
B52: 11/24 | C52: 106 | D52: PORTO SEGURO | E52: 30822 | F52: 5625.8 | G52: 2550 | H52: 2 | I52: 24 | J52: 26 | K52: =H52*I52*J52 -> 1248 | L52: 4 | M52: 16 | N52: 16 | O52: =L52*M52*N52 -> 1024 | P52: =K52+O52 -> 2272 | Q52: 2 | R52: 42.5 | S52: 26 | T52: =Q52*R52*S52 -> 2210 | U52: 4 | V52: 42.5 | W52: 16 | X52: =U52*V52*W52 -> 2720 | Y52: =T52+X52 -> 4930 | Z52: 2 | AA52: 80 | AB52: 2 | AC52: =Z52*AA52*AB52 -> 320 | AD52: 4 | AE52: 90 | AF52: 2 | AG52: =AD52*AE52*AF52 -> 720 | AH52: =AC52+AG52 -> 1040 | AI52: =F52+G52+P52+Y52+AH52 -> 16417.8 | AJ52: =AI52/E52 -> 0.53266498 | AK52: =(E52-AI52)*$AK$15 -> 1584.462 | AL52: 0 | AM52: 0 | AN52: 0 | AO52: 0 | AP52: 0.032099407 | AQ52: =AP52*E52 -> 989.36791 | AR52: =AL52+AM52+AN52+AO52+AQ52 -> 989.36791 | AS52: =AK52+AR52 -> 2573.8299 | AT52: =E52-AS52 -> 28248.17
B53: 12/24 | C53: 107 | D53: SHCES 509 BL B | E53: 5392 | F53: 0 | G53: 0 | H53: 1 | I53: 24 | J53: 26 | K53: =H53*I53*J53 -> 624 | L53: 0 | M53: 0 | N53: 0 | O53: =L53*M53*N53 -> 0 | P53: =K53+O53 -> 624 | Q53: 1 | R53: 42.5 | S53: 26 | T53: =Q53*R53*S53 -> 1105 | U53: 0 | V53: 0 | W53: 0 | X53: =U53*V53*W53 -> 0 | Y53: =T53+X53 -> 1105 | Z53: 0 | AA53: 0 | AB53: 0 | AC53: =Z53*AA53*AB53 -> 0 | AD53: 0 | AE53: 0 | AF53: 0 | AG53: =AD53*AE53*AF53 -> 0 | AH53: =AC53+AG53 -> 0 | AI53: =F53+G53+P53+Y53+AH53 -> 1729 | AJ53: =AI53/E53 -> 0.32066024 | AK53: =(E53-AI53)*$AK$15 -> 402.93 | AL53: 0 | AM53: 0 | AN53: 0 | AO53: 0 | AP53: 0.0318 | AQ53: =AP53*E53 -> 171.4656 | AR53: =AL53+AM53+AN53+AO53+AQ53 -> 171.4656 | AS53: =AK53+AR53 -> 574.3956 | AT53: =E53-AS53 -> 4817.6044 | AV53: 173.08 | AW53: =AV53/E53 -> 0.032099407
B54: 12/24 | C54: 108 | D54: RPR 01 | E54: 11906 | F54: 1977.4 | G54: 2040 | H54: 2 | I54: 24 | J54: 26 | K54: =H54*I54*J54 -> 1248 | L54: 0 | M54: 0 | N54: 0 | O54: =L54*M54*N54 -> 0 | P54: =K54+O54 -> 1248 | Q54: 2 | R54: 42.5 | S54: 26 | T54: =Q54*R54*S54 -> 2210 | U54: 0 | V54: 0 | W54: 0 | X54: =U54*V54*W54 -> 0 | Y54: =T54+X54 -> 2210 | Z54: 2 | AA54: 80 | AB54: 2 | AC54: =Z54*AA54*AB54 -> 320 | AD54: 0 | AE54: 0 | AF54: 0 | AG54: =AD54*AE54*AF54 -> 0 | AH54: =AC54+AG54 -> 320 | AI54: =F54+G54+P54+Y54+AH54 -> 7795.4 | AJ54: =AI54/E54 -> 0.65474551 | AK54: =(E54-AI54)*$AK$15 -> 452.166 | AL54: 0 | AM54: 0 | AN54: 0 | AO54: 0 | AP54: 0.0318 | AQ54: =AP54*E54 -> 378.6108 | AR54: =AL54+AM54+AN54+AO54+AQ54 -> 378.6108 | AS54: =AK54+AR54 -> 830.7768 | AT54: =E54-AS54 -> 11075.223
B55: 12/24 | C55: 109 | D55: PORTO SEGURO | E55: 30822 | F55: 5625.8 | G55: 2550 | H55: 2 | I55: 24 | J55: 26 | K55: =H55*I55*J55 -> 1248 | L55: 4 | M55: 16 | N55: 16 | O55: =L55*M55*N55 -> 1024 | P55: =K55+O55 -> 2272 | Q55: 2 | R55: 42.5 | S55: 26 | T55: =Q55*R55*S55 -> 2210 | U55: 4 | V55: 42.5 | W55: 16 | X55: =U55*V55*W55 -> 2720 | Y55: =T55+X55 -> 4930 | Z55: 2 | AA55: 80 | AB55: 2 | AC55: =Z55*AA55*AB55 -> 320 | AD55: 4 | AE55: 90 | AF55: 2 | AG55: =AD55*AE55*AF55 -> 720 | AH55: =AC55+AG55 -> 1040 | AI55: =F55+G55+P55+Y55+AH55 -> 16417.8 | AJ55: =AI55/E55 -> 0.53266498 | AK55: =(E55-AI55)*$AK$15 -> 1584.462 | AL55: 0 | AM55: 0 | AN55: 0 | AO55: 0 | AP55: 0.0318 | AQ55: =AP55*E55 -> 980.1396 | AR55: =AL55+AM55+AN55+AO55+AQ55 -> 980.1396 | AS55: =AK55+AR55 -> 2564.6016 | AT55: =E55-AS55 -> 28257.398
B57: 01/25 | C57: 110 | D57: SHCES 509 BL B | E57: 5392 | F57: 0 | G57: 0 | H57: 1 | I57: 24 | J57: 26 | K57: =H57*I57*J57 -> 624 | L57: 0 | M57: 0 | N57: 0 | O57: =L57*M57*N57 -> 0 | P57: =K57+O57 -> 624 | Q57: 1 | R57: 42.5 | S57: 26 | T57: =Q57*R57*S57 -> 1105 | U57: 0 | V57: 0 | W57: 0 | X57: =U57*V57*W57 -> 0 | Y57: =T57+X57 -> 1105 | Z57: 0 | AA57: 0 | AB57: 0 | AC57: =Z57*AA57*AB57 -> 0 | AD57: 0 | AE57: 0 | AF57: 0 | AG57: =AD57*AE57*AF57 -> 0 | AH57: =AC57+AG57 -> 0 | AI57: =F57+G57+P57+Y57+AH57 -> 1729 | AJ57: =AI57/E57 -> 0.32066024 | AK57: =(E57-AI57)*$AK$15 -> 402.93 | AL57: 0 | AM57: 0 | AN57: 0 | AO57: 0 | AP57: 0.05 | AQ57: =AP57*E57 -> 269.6 | AR57: =AL57+AM57+AN57+AO57+AQ57 -> 269.6 | AS57: =AK57+AR57 -> 672.53 | AT57: =E57-AS57 -> 4719.47
B58: 01/25 | C58: 112 | D58: RPR 01 | E58: 11906 | F58: 1977.4 | G58: 2040 | H58: 2 | I58: 24 | J58: 26 | K58: =H58*I58*J58 -> 1248 | L58: 0 | M58: 0 | N58: 0 | O58: =L58*M58*N58 -> 0 | P58: =K58+O58 -> 1248 | Q58: 2 | R58: 42.5 | S58: 26 | T58: =Q58*R58*S58 -> 2210 | U58: 0 | V58: 0 | W58: 0 | X58: =U58*V58*W58 -> 0 | Y58: =T58+X58 -> 2210 | Z58: 2 | AA58: 80 | AB58: 2 | AC58: =Z58*AA58*AB58 -> 320 | AD58: 0 | AE58: 0 | AF58: 0 | AG58: =AD58*AE58*AF58 -> 0 | AH58: =AC58+AG58 -> 320 | AI58: =F58+G58+P58+Y58+AH58 -> 7795.4 | AJ58: =AI58/E58 -> 0.65474551 | AK58: =(E58-AI58)*$AK$15 -> 452.166 | AL58: 0 | AM58: 0 | AN58: 0 | AO58: 0 | AP58: 0.05 | AQ58: =AP58*E58 -> 595.3 | AR58: =AL58+AM58+AN58+AO58+AQ58 -> 595.3 | AS58: =AK58+AR58 -> 1047.466 | AT58: =E58-AS58 -> 10858.534
B59: 01/25 | C59: 111 | D59: PORTO SEGURO | E59: 30822 | F59: 5625.8 | G59: 2550 | H59: 2 | I59: 24 | J59: 26 | K59: =H59*I59*J59 -> 1248 | L59: 4 | M59: 16 | N59: 16 | O59: =L59*M59*N59 -> 1024 | P59: =K59+O59 -> 2272 | Q59: 2 | R59: 42.5 | S59: 26 | T59: =Q59*R59*S59 -> 2210 | U59: 4 | V59: 42.5 | W59: 16 | X59: =U59*V59*W59 -> 2720 | Y59: =T59+X59 -> 4930 | Z59: 2 | AA59: 80 | AB59: 2 | AC59: =Z59*AA59*AB59 -> 320 | AD59: 4 | AE59: 90 | AF59: 2 | AG59: =AD59*AE59*AF59 -> 720 | AH59: =AC59+AG59 -> 1040 | AI59: =F59+G59+P59+Y59+AH59 -> 16417.8 | AJ59: =AI59/E59 -> 0.53266498 | AK59: =(E59-AI59)*$AK$15 -> 1584.462 | AL59: 0 | AM59: 0 | AN59: 0 | AO59: 0 | AP59: 0.05 | AQ59: =AP59*E59 -> 1541.1 | AR59: =AL59+AM59+AN59+AO59+AQ59 -> 1541.1 | AS59: =AK59+AR59 -> 3125.562 | AT59: =E59-AS59 -> 27696.438
B61: 02/25 | C61: 113 | D61: SHCES 509 BL B | E61: 5812 | F61: 0 | G61: 0 | H61: 1 | I61: 24 | J61: 26 | K61: =H61*I61*J61 -> 624 | L61: 0 | M61: 0 | N61: 0 | O61: =L61*M61*N61 -> 0 | P61: =K61+O61 -> 624 | Q61: 1 | R61: 44.3 | S61: 26 | T61: =Q61*R61*S61 -> 1151.8 | U61: 0 | V61: 0 | W61: 0 | X61: =U61*V61*W61 -> 0 | Y61: =T61+X61 -> 1151.8 | Z61: 0 | AA61: 0 | AB61: 0 | AC61: =Z61*AA61*AB61 -> 0 | AD61: 0 | AE61: 0 | AF61: 0 | AG61: =AD61*AE61*AF61 -> 0 | AH61: =AC61+AG61 -> 0 | AI61: =F61+G61+P61+Y61+AH61 -> 1775.8 | AJ61: =AI61/E61 -> 0.30554026 | AK61: =(E61-AI61)*$AK$15 -> 443.982 | AL61: 0 | AM61: 0 | AN61: 0 | AO61: 0 | AP61: 0.032 | AQ61: =AP61*E61 -> 185.984 | AR61: =AL61+AM61+AN61+AO61+AQ61 -> 185.984 | AS61: =AK61+AR61 -> 629.966 | AT61: =E61-AS61 -> 5182.034 | AV61: =AT61-AT53 -> 364.4296 | AW61: =AV61/AT53 -> 0.075645398
B62: 02/25 | C62: 114 | D62: RPR 01 | E62: 12740 | F62: 1977.4 | G62: 2040 | H62: 2 | I62: 24 | J62: 26 | K62: =H62*I62*J62 -> 1248 | L62: 0 | M62: 0 | N62: 0 | O62: =L62*M62*N62 -> 0 | P62: =K62+O62 -> 1248 | Q62: 2 | R62: 44.3 | S62: 26 | T62: =Q62*R62*S62 -> 2303.6 | U62: 0 | V62: 0 | W62: 0 | X62: =U62*V62*W62 -> 0 | Y62: =T62+X62 -> 2303.6 | Z62: 2 | AA62: 80 | AB62: 2 | AC62: =Z62*AA62*AB62 -> 320 | AD62: 0 | AE62: 0 | AF62: 0 | AG62: =AD62*AE62*AF62 -> 0 | AH62: =AC62+AG62 -> 320 | AI62: =F62+G62+P62+Y62+AH62 -> 7889 | AJ62: =AI62/E62 -> 0.61923077 | AK62: =(E62-AI62)*$AK$15 -> 533.61 | AL62: 0 | AM62: 0 | AN62: 0 | AO62: 0 | AP62: 0.032 | AQ62: =AP62*E62 -> 407.68 | AR62: =AL62+AM62+AN62+AO62+AQ62 -> 407.68 | AS62: =AK62+AR62 -> 941.29 | AT62: =E62-AS62 -> 11798.71
B63: 02/25 | C63: 115 | D63: PORTO SEGURO | E63: 33255 | F63: 5625.8 | G63: 2550 | H63: 2 | I63: 24 | J63: 26 | K63: =H63*I63*J63 -> 1248 | L63: 4 | M63: 16 | N63: 16 | O63: =L63*M63*N63 -> 1024 | P63: =K63+O63 -> 2272 | Q63: 2 | R63: 44.3 | S63: 26 | T63: =Q63*R63*S63 -> 2303.6 | U63: 4 | V63: 44.3 | W63: 16 | X63: =U63*V63*W63 -> 2835.2 | Y63: =T63+X63 -> 5138.8 | Z63: 2 | AA63: 80 | AB63: 2 | AC63: =Z63*AA63*AB63 -> 320 | AD63: 4 | AE63: 90 | AF63: 2 | AG63: =AD63*AE63*AF63 -> 720 | AH63: =AC63+AG63 -> 1040 | AI63: =F63+G63+P63+Y63+AH63 -> 16626.6 | AJ63: =AI63/E63 -> 0.49997294 | AK63: =(E63-AI63)*$AK$15 -> 1829.124 | AL63: 0 | AM63: 0 | AN63: 0 | AO63: 0 | AP63: 0.032 | AQ63: =AP63*E63 -> 1064.16 | AR63: =AL63+AM63+AN63+AO63+AQ63 -> 1064.16 | AS63: =AK63+AR63 -> 2893.284 | AT63: =E63-AS63 -> 30361.716
B64: 02/25 | C64: 116_COMPLEM | D64: PORTO SEGURO | E64: =33255-30822 -> 2433 | F64: 444.08 | G64: 201.29 | H64: 2 | I64: 24 | J64: 3 | K64: =H64*I64*J64 -> 144 | L64: 4 | M64: 16 | N64: 3 | O64: =L64*M64*N64 -> 192 | P64: =K64+O64 -> 336 | Q64: 2 | R64: 44.3 | S64: 3 | T64: =Q64*R64*S64 -> 265.8 | U64: 4 | V64: 44.3 | W64: 3 | X64: =U64*V64*W64 -> 531.6 | Y64: =T64+X64 -> 797.4 | Z64: 0 | AA64: 80 | AB64: 0 | AC64: =Z64*AA64*AB64 -> 0 | AD64: 0 | AE64: 90 | AF64: 0 | AG64: =AD64*AE64*AF64 -> 0 | AH64: =AC64+AG64 -> 0 | AI64: =F64+G64+P64+Y64+AH64 -> 1778.77 | AJ64: =AI64/E64 -> 0.73110152 | AK64: =(E64-AI64)*$AK$15 -> 71.9653 | AL64: 0 | AM64: 0 | AN64: 0 | AO64: 0 | AP64: 0.032 | AQ64: =AP64*E64 -> 77.856 | AR64: =AL64+AM64+AN64+AO64+AQ64 -> 77.856 | AS64: =AK64+AR64 -> 149.8213 | AT64: =E64-AS64 -> 2283.1787
B66: 03/25 | C66: 117 | D66: SHCES 509 BL B | E66: 5812 | F66: 0 | G66: 0 | H66: 1 | I66: 24 | J66: 26 | K66: =H66*I66*J66 -> 624 | L66: 0 | M66: 0 | N66: 0 | O66: =L66*M66*N66 -> 0 | P66: =K66+O66 -> 624 | Q66: 1 | R66: 44.3 | S66: 26 | T66: =Q66*R66*S66 -> 1151.8 | U66: 0 | V66: 0 | W66: 0 | X66: =U66*V66*W66 -> 0 | Y66: =T66+X66 -> 1151.8 | Z66: 0 | AA66: 0 | AB66: 0 | AC66: =Z66*AA66*AB66 -> 0 | AD66: 0 | AE66: 0 | AF66: 0 | AG66: =AD66*AE66*AF66 -> 0 | AH66: =AC66+AG66 -> 0 | AI66: =F66+G66+P66+Y66+AH66 -> 1775.8 | AJ66: =AI66/E66 -> 0.30554026 | AK66: =(E66-AI66)*$AK$15 -> 443.982 | AL66: 0 | AM66: 0 | AN66: 0 | AO66: 0 | AP66: 0.0322 | AQ66: =AP66*E66 -> 187.1464 | AR66: =AL66+AM66+AN66+AO66+AQ66 -> 187.1464 | AS66: =AK66+AR66 -> 631.1284 | AT66: =E66-AS66 -> 5180.8716
B67: 03/25 | C67: 118 | D67: RPR 01 | E67: 12740 | F67: 1977.4 | G67: 2040 | H67: 2 | I67: 24 | J67: 26 | K67: =H67*I67*J67 -> 1248 | L67: 0 | M67: 0 | N67: 0 | O67: =L67*M67*N67 -> 0 | P67: =K67+O67 -> 1248 | Q67: 2 | R67: 44.3 | S67: 26 | T67: =Q67*R67*S67 -> 2303.6 | U67: 0 | V67: 0 | W67: 0 | X67: =U67*V67*W67 -> 0 | Y67: =T67+X67 -> 2303.6 | Z67: 2 | AA67: 80 | AB67: 2 | AC67: =Z67*AA67*AB67 -> 320 | AD67: 0 | AE67: 0 | AF67: 0 | AG67: =AD67*AE67*AF67 -> 0 | AH67: =AC67+AG67 -> 320 | AI67: =F67+G67+P67+Y67+AH67 -> 7889 | AJ67: =AI67/E67 -> 0.61923077 | AK67: =(E67-AI67)*$AK$15 -> 533.61 | AL67: 0 | AM67: 0 | AN67: 0 | AO67: 0 | AP67: 0.0322 | AQ67: =AP67*E67 -> 410.228 | AR67: =AL67+AM67+AN67+AO67+AQ67 -> 410.228 | AS67: =AK67+AR67 -> 943.838 | AT67: =E67-AS67 -> 11796.162
B68: 03/25 | C68: 116 | D68: PORTO SEGURO | E68: 33255 | F68: 5625.8 | G68: 2550 | H68: 2 | I68: 24 | J68: 26 | K68: =H68*I68*J68 -> 1248 | L68: 4 | M68: 16 | N68: 16 | O68: =L68*M68*N68 -> 1024 | P68: =K68+O68 -> 2272 | Q68: 2 | R68: 44.3 | S68: 26 | T68: =Q68*R68*S68 -> 2303.6 | U68: 4 | V68: 44.3 | W68: 16 | X68: =U68*V68*W68 -> 2835.2 | Y68: =T68+X68 -> 5138.8 | Z68: 2 | AA68: 80 | AB68: 2 | AC68: =Z68*AA68*AB68 -> 320 | AD68: 4 | AE68: 90 | AF68: 2 | AG68: =AD68*AE68*AF68 -> 720 | AH68: =AC68+AG68 -> 1040 | AI68: =F68+G68+P68+Y68+AH68 -> 16626.6 | AJ68: =AI68/E68 -> 0.49997294 | AK68: =(E68-AI68)*$AK$15 -> 1829.124 | AL68: 0 | AM68: 0 | AN68: 0 | AO68: 0 | AP68: 0.0322 | AQ68: =AP68*E68 -> 1070.811 | AR68: =AL68+AM68+AN68+AO68+AQ68 -> 1070.811 | AS68: =AK68+AR68 -> 2899.935 | AT68: =E68-AS68 -> 30355.065
B69: 03/25 | C69: 120 | D69: VANESSA | E69: 5952 | F69: 950.61 | G69: 351.9 | H69: 1 | I69: 24 | J69: 26 | K69: =H69*I69*J69 -> 624 | L69: 0 | M69: 0 | N69: 0 | O69: =L69*M69*N69 -> 0 | P69: =K69+O69 -> 624 | Q69: 1 | R69: 44.3 | S69: 26 | T69: =Q69*R69*S69 -> 1151.8 | U69: 0 | V69: 0 | W69: 0 | X69: =U69*V69*W69 -> 0 | Y69: =T69+X69 -> 1151.8 | Z69: 1 | AA69: 90 | AB69: 2 | AC69: =Z69*AA69*AB69 -> 180 | AD69: 0 | AE69: 0 | AF69: 0 | AG69: =AD69*AE69*AF69 -> 0 | AH69: =AC69+AG69 -> 180 | AI69: =F69+G69+P69+Y69+AH69 -> 3258.31 | AJ69: =AI69/E69 -> 0.54743112 | AK69: =(E69-AI69)*$AK$15 -> 296.3059 | AL69: 0 | AM69: 0 | AN69: 0 | AO69: 0 | AP69: 0.0322 | AQ69: =AP69*E69 -> 191.6544 | AR69: =AL69+AM69+AN69+AO69+AQ69 -> 191.6544 | AS69: =AK69+AR69 -> 487.9603 | AT69: =E69-AS69 -> 5464.0397
B71: 04/25 | C71: EMITIR | D71: SHCES 509 BL B + R$ 420,00 | E71: =5812+420 -> 6232 | F71: 0 | G71: 0 | H71: 1 | I71: 24 | J71: 26 | K71: =H71*I71*J71 -> 624 | L71: 0 | M71: 0 | N71: 0 | O71: =L71*M71*N71 -> 0 | P71: =K71+O71 -> 624 | Q71: 1 | R71: 44.3 | S71: 26 | T71: =Q71*R71*S71 -> 1151.8 | U71: 0 | V71: 0 | W71: 0 | X71: =U71*V71*W71 -> 0 | Y71: =T71+X71 -> 1151.8 | Z71: 0 | AA71: 0 | AB71: 0 | AC71: =Z71*AA71*AB71 -> 0 | AD71: 0 | AE71: 0 | AF71: 0 | AG71: =AD71*AE71*AF71 -> 0 | AH71: =AC71+AG71 -> 0 | AI71: =F71+G71+P71+Y71+AH71 -> 1775.8 | AJ71: =AI71/E71 -> 0.28494865 | AK71: =(E71-AI71)*$AK$15 -> 490.182 | AL71: 0 | AM71: 0 | AN71: 0 | AO71: 0 | AP71: 0.0322 | AQ71: =AP71*E71 -> 200.6704 | AR71: =AL71+AM71+AN71+AO71+AQ71 -> 200.6704 | AS71: =AK71+AR71 -> 690.8524 | AT71: =E71-AS71 -> 5541.1476
B72: 04/25 | C72: EMITIR | D72: RPR 01 + R$ 834,00 | E72: =12740+834 -> 13574 | F72: 1977.4 | G72: 2040 | H72: 2 | I72: 24 | J72: 26 | K72: =H72*I72*J72 -> 1248 | L72: 0 | M72: 0 | N72: 0 | O72: =L72*M72*N72 -> 0 | P72: =K72+O72 -> 1248 | Q72: 2 | R72: 44.3 | S72: 26 | T72: =Q72*R72*S72 -> 2303.6 | U72: 0 | V72: 0 | W72: 0 | X72: =U72*V72*W72 -> 0 | Y72: =T72+X72 -> 2303.6 | Z72: 2 | AA72: 80 | AB72: 2 | AC72: =Z72*AA72*AB72 -> 320 | AD72: 0 | AE72: 0 | AF72: 0 | AG72: =AD72*AE72*AF72 -> 0 | AH72: =AC72+AG72 -> 320 | AI72: =F72+G72+P72+Y72+AH72 -> 7889 | AJ72: =AI72/E72 -> 0.58118462 | AK72: =(E72-AI72)*$AK$15 -> 625.35 | AL72: 0 | AM72: 0 | AN72: 0 | AO72: 0 | AP72: 0.0322 | AQ72: =AP72*E72 -> 437.0828 | AR72: =AL72+AM72+AN72+AO72+AQ72 -> 437.0828 | AS72: =AK72+AR72 -> 1062.4328 | AT72: =E72-AS72 -> 12511.567
B73: 04/25 | C73: EMITIR | D73: PORTO SEGURO | E73: 33255 | F73: 5625.8 | G73: 2550 | H73: 2 | I73: 24 | J73: 26 | K73: =H73*I73*J73 -> 1248 | L73: 4 | M73: 16 | N73: 16 | O73: =L73*M73*N73 -> 1024 | P73: =K73+O73 -> 2272 | Q73: 2 | R73: 44.3 | S73: 26 | T73: =Q73*R73*S73 -> 2303.6 | U73: 4 | V73: 44.3 | W73: 16 | X73: =U73*V73*W73 -> 2835.2 | Y73: =T73+X73 -> 5138.8 | Z73: 2 | AA73: 80 | AB73: 2 | AC73: =Z73*AA73*AB73 -> 320 | AD73: 4 | AE73: 90 | AF73: 2 | AG73: =AD73*AE73*AF73 -> 720 | AH73: =AC73+AG73 -> 1040 | AI73: =F73+G73+P73+Y73+AH73 -> 16626.6 | AJ73: =AI73/E73 -> 0.49997294 | AK73: =(E73-AI73)*$AK$15 -> 1829.124 | AL73: 0 | AM73: 0 | AN73: 0 | AO73: 0 | AP73: 0.0322 | AQ73: =AP73*E73 -> 1070.811 | AR73: =AL73+AM73+AN73+AO73+AQ73 -> 1070.811 | AS73: =AK73+AR73 -> 2899.935 | AT73: =E73-AS73 -> 30355.065
B74: 04/25 | C74: EMITIR | D74: VANESSA + R$ 390,00 | E74: =5952+390 -> 6342 | F74: 950.61 | G74: 351.9 | H74: 1 | I74: 24 | J74: 26 | K74: =H74*I74*J74 -> 624 | L74: 0 | M74: 0 | N74: 0 | O74: =L74*M74*N74 -> 0 | P74: =K74+O74 -> 624 | Q74: 1 | R74: 44.3 | S74: 26 | T74: =Q74*R74*S74 -> 1151.8 | U74: 0 | V74: 0 | W74: 0 | X74: =U74*V74*W74 -> 0 | Y74: =T74+X74 -> 1151.8 | Z74: 1 | AA74: 90 | AB74: 2 | AC74: =Z74*AA74*AB74 -> 180 | AD74: 0 | AE74: 0 | AF74: 0 | AG74: =AD74*AE74*AF74 -> 0 | AH74: =AC74+AG74 -> 180 | AI74: =F74+G74+P74+Y74+AH74 -> 3258.31 | AJ74: =AI74/E74 -> 0.51376695 | AK74: =(E74-AI74)*$AK$15 -> 339.2059 | AL74: 0 | AM74: 0 | AN74: 0 | AO74: 0 | AP74: 0.0322 | AQ74: =AP74*E74 -> 204.2124 | AR74: =AL74+AM74+AN74+AO74+AQ74 -> 204.2124 | AS74: =AK74+AR74 -> 543.4183 | AT74: =E74-AS74 -> 5798.5817
B76: 05/25 | C76: 125 | D76: SHCES 509 BL B | E76: =5812 -> 5812 | F76: 0 | G76: 0 | H76: 1 | I76: 24 | J76: 26 | K76: =H76*I76*J76 -> 624 | L76: 0 | M76: 0 | N76: 0 | O76: =L76*M76*N76 -> 0 | P76: =K76+O76 -> 624 | Q76: 1 | R76: 44.3 | S76: 26 | T76: =Q76*R76*S76 -> 1151.8 | U76: 0 | V76: 0 | W76: 0 | X76: =U76*V76*W76 -> 0 | Y76: =T76+X76 -> 1151.8 | Z76: 0 | AA76: 0 | AB76: 0 | AC76: =Z76*AA76*AB76 -> 0 | AD76: 0 | AE76: 0 | AF76: 0 | AG76: =AD76*AE76*AF76 -> 0 | AH76: =AC76+AG76 -> 0 | AI76: =F76+G76+P76+Y76+AH76 -> 1775.8 | AJ76: =AI76/E76 -> 0.30554026 | AK76: =(E76-AI76)*$AK$15 -> 443.982 | AL76: 0 | AM76: 0 | AN76: 0 | AO76: 0 | AP76: 0.0322 | AQ76: =AP76*E76 -> 187.1464 | AR76: =AL76+AM76+AN76+AO76+AQ76 -> 187.1464 | AS76: =AK76+AR76 -> 631.1284 | AT76: =E76-AS76 -> 5180.8716
B77: 05/25 | C77: 126 | D77: RPR 01 | E77: =12740 -> 12740 | F77: 1977.4 | G77: 2040 | H77: 2 | I77: 24 | J77: 26 | K77: =H77*I77*J77 -> 1248 | L77: 0 | M77: 0 | N77: 0 | O77: =L77*M77*N77 -> 0 | P77: =K77+O77 -> 1248 | Q77: 2 | R77: 44.3 | S77: 26 | T77: =Q77*R77*S77 -> 2303.6 | U77: 0 | V77: 0 | W77: 0 | X77: =U77*V77*W77 -> 0 | Y77: =T77+X77 -> 2303.6 | Z77: 2 | AA77: 80 | AB77: 2 | AC77: =Z77*AA77*AB77 -> 320 | AD77: 0 | AE77: 0 | AF77: 0 | AG77: =AD77*AE77*AF77 -> 0 | AH77: =AC77+AG77 -> 320 | AI77: =F77+G77+P77+Y77+AH77 -> 7889 | AJ77: =AI77/E77 -> 0.61923077 | AK77: =(E77-AI77)*$AK$15 -> 533.61 | AL77: 0 | AM77: 0 | AN77: 0 | AO77: 0 | AP77: 0.0322 | AQ77: =AP77*E77 -> 410.228 | AR77: =AL77+AM77+AN77+AO77+AQ77 -> 410.228 | AS77: =AK77+AR77 -> 943.838 | AT77: =E77-AS77 -> 11796.162
B78: 05/25 | C78: 127 | D78: PORTO SEGURO | E78: 33255 | F78: 5625.8 | G78: 2550 | H78: 2 | I78: 24 | J78: 26 | K78: =H78*I78*J78 -> 1248 | L78: 4 | M78: 16 | N78: 16 | O78: =L78*M78*N78 -> 1024 | P78: =K78+O78 -> 2272 | Q78: 2 | R78: 44.3 | S78: 26 | T78: =Q78*R78*S78 -> 2303.6 | U78: 4 | V78: 44.3 | W78: 16 | X78: =U78*V78*W78 -> 2835.2 | Y78: =T78+X78 -> 5138.8 | Z78: 2 | AA78: 80 | AB78: 2 | AC78: =Z78*AA78*AB78 -> 320 | AD78: 4 | AE78: 90 | AF78: 2 | AG78: =AD78*AE78*AF78 -> 720 | AH78: =AC78+AG78 -> 1040 | AI78: =F78+G78+P78+Y78+AH78 -> 16626.6 | AJ78: =AI78/E78 -> 0.49997294 | AK78: =(E78-AI78)*$AK$15 -> 1829.124 | AL78: 0 | AM78: 0 | AN78: 0 | AO78: 0 | AP78: 0.0322 | AQ78: =AP78*E78 -> 1070.811 | AR78: =AL78+AM78+AN78+AO78+AQ78 -> 1070.811 | AS78: =AK78+AR78 -> 2899.935 | AT78: =E78-AS78 -> 30355.065
B79: 05/25 | C79: 128 | D79: VANESSA | E79: =5952 -> 5952 | F79: 950.61 | G79: 351.9 | H79: 1 | I79: 24 | J79: 26 | K79: =H79*I79*J79 -> 624 | L79: 0 | M79: 0 | N79: 0 | O79: =L79*M79*N79 -> 0 | P79: =K79+O79 -> 624 | Q79: 1 | R79: 44.3 | S79: 26 | T79: =Q79*R79*S79 -> 1151.8 | U79: 0 | V79: 0 | W79: 0 | X79: =U79*V79*W79 -> 0 | Y79: =T79+X79 -> 1151.8 | Z79: 1 | AA79: 90 | AB79: 2 | AC79: =Z79*AA79*AB79 -> 180 | AD79: 0 | AE79: 0 | AF79: 0 | AG79: =AD79*AE79*AF79 -> 0 | AH79: =AC79+AG79 -> 180 | AI79: =F79+G79+P79+Y79+AH79 -> 3258.31 | AJ79: =AI79/E79 -> 0.54743112 | AK79: =(E79-AI79)*$AK$15 -> 296.3059 | AL79: 0 | AM79: 0 | AN79: 0 | AO79: 0 | AP79: 0.0322 | AQ79: =AP79*E79 -> 191.6544 | AR79: =AL79+AM79+AN79+AO79+AQ79 -> 191.6544 | AS79: =AK79+AR79 -> 487.9603 | AT79: =E79-AS79 -> 5464.0397
B81: 06/25 | C81: 129 | D81: SHCES 509 BL B | E81: =5812 -> 5812 | F81: 0 | G81: 0 | H81: 1 | I81: 24 | J81: 26 | K81: =H81*I81*J81 -> 624 | L81: 0 | M81: 0 | N81: 0 | O81: =L81*M81*N81 -> 0 | P81: =K81+O81 -> 624 | Q81: 1 | R81: 44.3 | S81: 26 | T81: =Q81*R81*S81 -> 1151.8 | U81: 0 | V81: 0 | W81: 0 | X81: =U81*V81*W81 -> 0 | Y81: =T81+X81 -> 1151.8 | Z81: 0 | AA81: 0 | AB81: 0 | AC81: =Z81*AA81*AB81 -> 0 | AD81: 0 | AE81: 0 | AF81: 0 | AG81: =AD81*AE81*AF81 -> 0 | AH81: =AC81+AG81 -> 0 | AI81: =F81+G81+P81+Y81+AH81 -> 1775.8 | AJ81: =AI81/E81 -> 0.30554026 | AK81: =(E81-AI81)*$AK$15 -> 443.982 | AL81: 0 | AM81: 0 | AN81: 0 | AO81: 0 | AP81: 0.0327 | AQ81: =AP81*E81 -> 190.0524 | AR81: =AL81+AM81+AN81+AO81+AQ81 -> 190.0524 | AS81: =AK81+AR81 -> 634.0344 | AT81: =E81-AS81 -> 5177.9656
B82: 06/25 | C82: 130 | D82: RPR 01 | E82: =12740 -> 12740 | F82: 1977.4 | G82: 2040 | H82: 2 | I82: 24 | J82: 26 | K82: =H82*I82*J82 -> 1248 | L82: 0 | M82: 0 | N82: 0 | O82: =L82*M82*N82 -> 0 | P82: =K82+O82 -> 1248 | Q82: 2 | R82: 44.3 | S82: 26 | T82: =Q82*R82*S82 -> 2303.6 | U82: 0 | V82: 0 | W82: 0 | X82: =U82*V82*W82 -> 0 | Y82: =T82+X82 -> 2303.6 | Z82: 2 | AA82: 80 | AB82: 2 | AC82: =Z82*AA82*AB82 -> 320 | AD82: 0 | AE82: 0 | AF82: 0 | AG82: =AD82*AE82*AF82 -> 0 | AH82: =AC82+AG82 -> 320 | AI82: =F82+G82+P82+Y82+AH82 -> 7889 | AJ82: =AI82/E82 -> 0.61923077 | AK82: =(E82-AI82)*$AK$15 -> 533.61 | AL82: 0 | AM82: 0 | AN82: 0 | AO82: 0 | AP82: 0.0327 | AQ82: =AP82*E82 -> 416.598 | AR82: =AL82+AM82+AN82+AO82+AQ82 -> 416.598 | AS82: =AK82+AR82 -> 950.208 | AT82: =E82-AS82 -> 11789.792
B83: 06/25 | C83: 131 | D83: PORTO SEGURO | E83: 33255 | F83: 5625.8 | G83: 2550 | H83: 2 | I83: 24 | J83: 26 | K83: =H83*I83*J83 -> 1248 | L83: 4 | M83: 16 | N83: 16 | O83: =L83*M83*N83 -> 1024 | P83: =K83+O83 -> 2272 | Q83: 2 | R83: 44.3 | S83: 26 | T83: =Q83*R83*S83 -> 2303.6 | U83: 4 | V83: 44.3 | W83: 16 | X83: =U83*V83*W83 -> 2835.2 | Y83: =T83+X83 -> 5138.8 | Z83: 2 | AA83: 80 | AB83: 2 | AC83: =Z83*AA83*AB83 -> 320 | AD83: 4 | AE83: 90 | AF83: 2 | AG83: =AD83*AE83*AF83 -> 720 | AH83: =AC83+AG83 -> 1040 | AI83: =F83+G83+P83+Y83+AH83 -> 16626.6 | AJ83: =AI83/E83 -> 0.49997294 | AK83: =(E83-AI83)*$AK$15 -> 1829.124 | AL83: 0 | AM83: 0 | AN83: 0 | AO83: 0 | AP83: 0.0327 | AQ83: =AP83*E83 -> 1087.4385 | AR83: =AL83+AM83+AN83+AO83+AQ83 -> 1087.4385 | AS83: =AK83+AR83 -> 2916.5625 | AT83: =E83-AS83 -> 30338.438
B84: 06/25 | C84: 132 | D84: VANESSA | E84: =5952 -> 5952 | F84: 950.61 | G84: 351.9 | H84: 1 | I84: 24 | J84: 26 | K84: =H84*I84*J84 -> 624 | L84: 0 | M84: 0 | N84: 0 | O84: =L84*M84*N84 -> 0 | P84: =K84+O84 -> 624 | Q84: 1 | R84: 44.3 | S84: 26 | T84: =Q84*R84*S84 -> 1151.8 | U84: 0 | V84: 0 | W84: 0 | X84: =U84*V84*W84 -> 0 | Y84: =T84+X84 -> 1151.8 | Z84: 1 | AA84: 90 | AB84: 2 | AC84: =Z84*AA84*AB84 -> 180 | AD84: 0 | AE84: 0 | AF84: 0 | AG84: =AD84*AE84*AF84 -> 0 | AH84: =AC84+AG84 -> 180 | AI84: =F84+G84+P84+Y84+AH84 -> 3258.31 | AJ84: =AI84/E84 -> 0.54743112 | AK84: =(E84-AI84)*$AK$15 -> 296.3059 | AL84: 0 | AM84: 0 | AN84: 0 | AO84: 0 | AP84: 0.0327 | AQ84: =AP84*E84 -> 194.6304 | AR84: =AL84+AM84+AN84+AO84+AQ84 -> 194.6304 | AS84: =AK84+AR84 -> 490.9363 | AT84: =E84-AS84 -> 5461.0637
B86: 07/25 | C86: 133 | D86: SHCES 509 BL B | E86: =5812 -> 5812 | F86: 0 | G86: 0 | H86: 1 | I86: 24 | J86: 26 | K86: =H86*I86*J86 -> 624 | L86: 0 | M86: 0 | N86: 0 | O86: =L86*M86*N86 -> 0 | P86: =K86+O86 -> 624 | Q86: 1 | R86: 44.3 | S86: 26 | T86: =Q86*R86*S86 -> 1151.8 | U86: 0 | V86: 0 | W86: 0 | X86: =U86*V86*W86 -> 0 | Y86: =T86+X86 -> 1151.8 | Z86: 0 | AA86: 0 | AB86: 0 | AC86: =Z86*AA86*AB86 -> 0 | AD86: 0 | AE86: 0 | AF86: 0 | AG86: =AD86*AE86*AF86 -> 0 | AH86: =AC86+AG86 -> 0 | AI86: =F86+G86+P86+Y86+AH86 -> 1775.8 | AJ86: =AI86/E86 -> 0.30554026 | AK86: =(E86-AI86)*$AK$15 -> 443.982 | AL86: 0 | AM86: 0 | AN86: 0 | AO86: 0 | AP86: 0.0326 | AQ86: =AP86*E86 -> 189.4712 | AR86: =AL86+AM86+AN86+AO86+AQ86 -> 189.4712 | AS86: =AK86+AR86 -> 633.4532 | AT86: =E86-AS86 -> 5178.5468
B87: 07/25 | C87: 134 | D87: RPR 01 | E87: =12740 -> 12740 | F87: 1977.4 | G87: 2040 | H87: 2 | I87: 24 | J87: 26 | K87: =H87*I87*J87 -> 1248 | L87: 0 | M87: 0 | N87: 0 | O87: =L87*M87*N87 -> 0 | P87: =K87+O87 -> 1248 | Q87: 2 | R87: 44.3 | S87: 26 | T87: =Q87*R87*S87 -> 2303.6 | U87: 0 | V87: 0 | W87: 0 | X87: =U87*V87*W87 -> 0 | Y87: =T87+X87 -> 2303.6 | Z87: 2 | AA87: 80 | AB87: 2 | AC87: =Z87*AA87*AB87 -> 320 | AD87: 0 | AE87: 0 | AF87: 0 | AG87: =AD87*AE87*AF87 -> 0 | AH87: =AC87+AG87 -> 320 | AI87: =F87+G87+P87+Y87+AH87 -> 7889 | AJ87: =AI87/E87 -> 0.61923077 | AK87: =(E87-AI87)*$AK$15 -> 533.61 | AL87: 0 | AM87: 0 | AN87: 0 | AO87: 0 | AP87: 0.0326 | AQ87: =AP87*E87 -> 415.324 | AR87: =AL87+AM87+AN87+AO87+AQ87 -> 415.324 | AS87: =AK87+AR87 -> 948.934 | AT87: =E87-AS87 -> 11791.066
B88: 07/25 | C88: 135 | D88: PORTO SEGURO | E88: 33255 | F88: 5625.8 | G88: 2550 | H88: 2 | I88: 24 | J88: 26 | K88: =H88*I88*J88 -> 1248 | L88: 4 | M88: 16 | N88: 16 | O88: =L88*M88*N88 -> 1024 | P88: =K88+O88 -> 2272 | Q88: 2 | R88: 44.3 | S88: 26 | T88: =Q88*R88*S88 -> 2303.6 | U88: 4 | V88: 44.3 | W88: 16 | X88: =U88*V88*W88 -> 2835.2 | Y88: =T88+X88 -> 5138.8 | Z88: 2 | AA88: 80 | AB88: 2 | AC88: =Z88*AA88*AB88 -> 320 | AD88: 4 | AE88: 90 | AF88: 2 | AG88: =AD88*AE88*AF88 -> 720 | AH88: =AC88+AG88 -> 1040 | AI88: =F88+G88+P88+Y88+AH88 -> 16626.6 | AJ88: =AI88/E88 -> 0.49997294 | AK88: =(E88-AI88)*$AK$15 -> 1829.124 | AL88: 0 | AM88: 0 | AN88: 0 | AO88: 0 | AP88: 0.0326 | AQ88: =AP88*E88 -> 1084.113 | AR88: =AL88+AM88+AN88+AO88+AQ88 -> 1084.113 | AS88: =AK88+AR88 -> 2913.237 | AT88: =E88-AS88 -> 30341.763
B89: 07/25 | C89: 136 | D89: VANESSA | E89: =5952 -> 5952 | F89: 950.61 | G89: 351.9 | H89: 1 | I89: 24 | J89: 26 | K89: =H89*I89*J89 -> 624 | L89: 0 | M89: 0 | N89: 0 | O89: =L89*M89*N89 -> 0 | P89: =K89+O89 -> 624 | Q89: 1 | R89: 44.3 | S89: 26 | T89: =Q89*R89*S89 -> 1151.8 | U89: 0 | V89: 0 | W89: 0 | X89: =U89*V89*W89 -> 0 | Y89: =T89+X89 -> 1151.8 | Z89: 1 | AA89: 90 | AB89: 2 | AC89: =Z89*AA89*AB89 -> 180 | AD89: 0 | AE89: 0 | AF89: 0 | AG89: =AD89*AE89*AF89 -> 0 | AH89: =AC89+AG89 -> 180 | AI89: =F89+G89+P89+Y89+AH89 -> 3258.31 | AJ89: =AI89/E89 -> 0.54743112 | AK89: =(E89-AI89)*$AK$15 -> 296.3059 | AL89: 0 | AM89: 0 | AN89: 0 | AO89: 0 | AP89: 0.0326 | AQ89: =AP89*E89 -> 194.0352 | AR89: =AL89+AM89+AN89+AO89+AQ89 -> 194.0352 | AS89: =AK89+AR89 -> 490.3411 | AT89: =E89-AS89 -> 5461.6589
B91: 08/25 | C91: 137 | D91: SHCES 509 BL B | E91: =5812 -> 5812 | F91: 0 | G91: 0 | H91: 1 | I91: 24 | J91: 26 | K91: =H91*I91*J91 -> 624 | L91: 0 | M91: 0 | N91: 0 | O91: =L91*M91*N91 -> 0 | P91: =K91+O91 -> 624 | Q91: 1 | R91: 44.3 | S91: 26 | T91: =Q91*R91*S91 -> 1151.8 | U91: 0 | V91: 0 | W91: 0 | X91: =U91*V91*W91 -> 0 | Y91: =T91+X91 -> 1151.8 | Z91: 0 | AA91: 0 | AB91: 0 | AC91: =Z91*AA91*AB91 -> 0 | AD91: 0 | AE91: 0 | AF91: 0 | AG91: =AD91*AE91*AF91 -> 0 | AH91: =AC91+AG91 -> 0 | AI91: =F91+G91+P91+Y91+AH91 -> 1775.8 | AJ91: =AI91/E91 -> 0.30554026 | AK91: =(E91-AI91)*$AK$15 -> 443.982 | AL91: 0 | AM91: 0 | AN91: 0 | AO91: 0 | AP91: 0.032699587 | AQ91: =AP91*E91 -> 190.05 | AR91: =AL91+AM91+AN91+AO91+AQ91 -> 190.05 | AS91: =AK91+AR91 -> 634.032 | AT91: =E91-AS91 -> 5177.968
B92: 08/25 | C92: 138 | D92: RPR 01 | E92: =12740 -> 12740 | F92: 1977.4 | G92: 2040 | H92: 2 | I92: 24 | J92: 26 | K92: =H92*I92*J92 -> 1248 | L92: 0 | M92: 0 | N92: 0 | O92: =L92*M92*N92 -> 0 | P92: =K92+O92 -> 1248 | Q92: 2 | R92: 44.3 | S92: 26 | T92: =Q92*R92*S92 -> 2303.6 | U92: 0 | V92: 0 | W92: 0 | X92: =U92*V92*W92 -> 0 | Y92: =T92+X92 -> 2303.6 | Z92: 2 | AA92: 80 | AB92: 2 | AC92: =Z92*AA92*AB92 -> 320 | AD92: 0 | AE92: 0 | AF92: 0 | AG92: =AD92*AE92*AF92 -> 0 | AH92: =AC92+AG92 -> 320 | AI92: =F92+G92+P92+Y92+AH92 -> 7889 | AJ92: =AI92/E92 -> 0.61923077 | AK92: =(E92-AI92)*$AK$15 -> 533.61 | AL92: 0 | AM92: 0 | AN92: 0 | AO92: 0 | AP92: 0.032699587 | AQ92: =AP92*E92 -> 416.59274 | AR92: =AL92+AM92+AN92+AO92+AQ92 -> 416.59274 | AS92: =AK92+AR92 -> 950.20274 | AT92: =E92-AS92 -> 11789.797
B93: 08/25 | C93: 139 | D93: PORTO SEGURO | E93: 33255 | F93: 5625.8 | G93: 2550 | H93: 2 | I93: 24 | J93: 26 | K93: =H93*I93*J93 -> 1248 | L93: 4 | M93: 16 | N93: 16 | O93: =L93*M93*N93 -> 1024 | P93: =K93+O93 -> 2272 | Q93: 2 | R93: 44.3 | S93: 26 | T93: =Q93*R93*S93 -> 2303.6 | U93: 4 | V93: 44.3 | W93: 16 | X93: =U93*V93*W93 -> 2835.2 | Y93: =T93+X93 -> 5138.8 | Z93: 2 | AA93: 80 | AB93: 2 | AC93: =Z93*AA93*AB93 -> 320 | AD93: 4 | AE93: 90 | AF93: 2 | AG93: =AD93*AE93*AF93 -> 720 | AH93: =AC93+AG93 -> 1040 | AI93: =F93+G93+P93+Y93+AH93 -> 16626.6 | AJ93: =AI93/E93 -> 0.49997294 | AK93: =(E93-AI93)*$AK$15 -> 1829.124 | AL93: 0 | AM93: 0 | AN93: 0 | AO93: 0 | AP93: 0.032699587 | AQ93: =AP93*E93 -> 1087.4248 | AR93: =AL93+AM93+AN93+AO93+AQ93 -> 1087.4248 | AS93: =AK93+AR93 -> 2916.5488 | AT93: =E93-AS93 -> 30338.451
B94: 08/25 | C94: 140 | D94: VANESSA | E94: =5952 -> 5952 | F94: 950.61 | G94: 351.9 | H94: 1 | I94: 24 | J94: 26 | K94: =H94*I94*J94 -> 624 | L94: 0 | M94: 0 | N94: 0 | O94: =L94*M94*N94 -> 0 | P94: =K94+O94 -> 624 | Q94: 1 | R94: 44.3 | S94: 26 | T94: =Q94*R94*S94 -> 1151.8 | U94: 0 | V94: 0 | W94: 0 | X94: =U94*V94*W94 -> 0 | Y94: =T94+X94 -> 1151.8 | Z94: 1 | AA94: 90 | AB94: 2 | AC94: =Z94*AA94*AB94 -> 180 | AD94: 0 | AE94: 0 | AF94: 0 | AG94: =AD94*AE94*AF94 -> 0 | AH94: =AC94+AG94 -> 180 | AI94: =F94+G94+P94+Y94+AH94 -> 3258.31 | AJ94: =AI94/E94 -> 0.54743112 | AK94: =(E94-AI94)*$AK$15 -> 296.3059 | AL94: 0 | AM94: 0 | AN94: 0 | AO94: 0 | AP94: 0.032699587 | AQ94: =AP94*E94 -> 194.62794 | AR94: =AL94+AM94+AN94+AO94+AQ94 -> 194.62794 | AS94: =AK94+AR94 -> 490.93384 | AT94: =E94-AS94 -> 5461.0662
B96: 09/25 | C96: 137 | D96: SHCES 509 BL B | E96: =5812 -> 5812 | F96: 0 | G96: 0 | H96: 1 | I96: 24 | J96: 26 | K96: =H96*I96*J96 -> 624 | L96: 0 | M96: 0 | N96: 0 | O96: =L96*M96*N96 -> 0 | P96: =K96+O96 -> 624 | Q96: 1 | R96: 44.3 | S96: 26 | T96: =Q96*R96*S96 -> 1151.8 | U96: 0 | V96: 0 | W96: 0 | X96: =U96*V96*W96 -> 0 | Y96: =T96+X96 -> 1151.8 | Z96: 0 | AA96: 0 | AB96: 0 | AC96: =Z96*AA96*AB96 -> 0 | AD96: 0 | AE96: 0 | AF96: 0 | AG96: =AD96*AE96*AF96 -> 0 | AH96: =AC96+AG96 -> 0 | AI96: =F96+G96+P96+Y96+AH96 -> 1775.8 | AJ96: =AI96/E96 -> 0.30554026 | AK96: =(E96-AI96)*$AK$15 -> 443.982 | AL96: 0 | AM96: 0 | AN96: 0 | AO96: 0 | AP96: 0.0332 | AQ96: =AP96*E96 -> 192.9584 | AR96: =AL96+AM96+AN96+AO96+AQ96 -> 192.9584 | AS96: =AK96+AR96 -> 636.9404 | AT96: =E96-AS96 -> 5175.0596 | AV96: ok
B97: 09/25 | C97: 138 | D97: RPR 01 | E97: =12740 -> 12740 | F97: 1977.4 | G97: 2040 | H97: 2 | I97: 24 | J97: 26 | K97: =H97*I97*J97 -> 1248 | L97: 0 | M97: 0 | N97: 0 | O97: =L97*M97*N97 -> 0 | P97: =K97+O97 -> 1248 | Q97: 2 | R97: 44.3 | S97: 26 | T97: =Q97*R97*S97 -> 2303.6 | U97: 0 | V97: 0 | W97: 0 | X97: =U97*V97*W97 -> 0 | Y97: =T97+X97 -> 2303.6 | Z97: 2 | AA97: 80 | AB97: 2 | AC97: =Z97*AA97*AB97 -> 320 | AD97: 0 | AE97: 0 | AF97: 0 | AG97: =AD97*AE97*AF97 -> 0 | AH97: =AC97+AG97 -> 320 | AI97: =F97+G97+P97+Y97+AH97 -> 7889 | AJ97: =AI97/E97 -> 0.61923077 | AK97: =(E97-AI97)*$AK$15 -> 533.61 | AL97: 0 | AM97: 0 | AN97: 0 | AO97: 0 | AP97: 0.0332 | AQ97: =AP97*E97 -> 422.968 | AR97: =AL97+AM97+AN97+AO97+AQ97 -> 422.968 | AS97: =AK97+AR97 -> 956.578 | AT97: =E97-AS97 -> 11783.422 | AV97: ok
B98: 09/25 | C98: 139 | D98: PORTO SEGURO | E98: 22789 | F98: 3855.2505 | G98: 1747.465 | H98: 2 | I98: 24 | J98: 26 | K98: =H98*I98*J98 -> 1248 | L98: 2 | M98: 16 | N98: 16 | O98: =L98*M98*N98 -> 512 | P98: =K98+O98 -> 1760 | Q98: 2 | R98: 44.3 | S98: 26 | T98: =Q98*R98*S98 -> 2303.6 | U98: 2 | V98: 44.3 | W98: 16 | X98: =U98*V98*W98 -> 1417.6 | Y98: =T98+X98 -> 3721.2 | Z98: 2 | AA98: 80 | AB98: 2 | AC98: =Z98*AA98*AB98 -> 320 | AD98: 2 | AE98: 90 | AF98: 2 | AG98: =AD98*AE98*AF98 -> 360 | AH98: =AC98+AG98 -> 680 | AI98: =F98+G98+P98+Y98+AH98 -> 11763.916 | AJ98: =AI98/E98 -> 0.51621026 | AK98: =(E98-AI98)*$AK$15 -> 1212.7593 | AL98: 0 | AM98: 0 | AN98: 0 | AO98: 0 | AP98: 0.0332 | AQ98: =AP98*E98 -> 756.5948 | AR98: =AL98+AM98+AN98+AO98+AQ98 -> 756.5948 | AS98: =AK98+AR98 -> 1969.3541 | AT98: =E98-AS98 -> 20819.646 | AV98: ok
B99: 09/25 | C99: 140 | D99: VANESSA | E99: =5952 -> 5952 | F99: 950.61 | G99: 351.9 | H99: 1 | I99: 24 | J99: 26 | K99: =H99*I99*J99 -> 624 | L99: 0 | M99: 0 | N99: 0 | O99: =L99*M99*N99 -> 0 | P99: =K99+O99 -> 624 | Q99: 1 | R99: 44.3 | S99: 26 | T99: =Q99*R99*S99 -> 1151.8 | U99: 0 | V99: 0 | W99: 0 | X99: =U99*V99*W99 -> 0 | Y99: =T99+X99 -> 1151.8 | Z99: 1 | AA99: 90 | AB99: 2 | AC99: =Z99*AA99*AB99 -> 180 | AD99: 0 | AE99: 0 | AF99: 0 | AG99: =AD99*AE99*AF99 -> 0 | AH99: =AC99+AG99 -> 180 | AI99: =F99+G99+P99+Y99+AH99 -> 3258.31 | AJ99: =AI99/E99 -> 0.54743112 | AK99: =(E99-AI99)*$AK$15 -> 296.3059 | AL99: 0 | AM99: 0 | AN99: 0 | AO99: 0 | AP99: 0.0332 | AQ99: =AP99*E99 -> 197.6064 | AR99: =AL99+AM99+AN99+AO99+AQ99 -> 197.6064 | AS99: =AK99+AR99 -> 493.9123 | AT99: =E99-AS99 -> 5458.0877 | AV99: ok
B101: 10/25 | C101: 145 | D101: SHCES 509 BL B | E101: =5812 -> 5812 | F101: 0 | G101: 0 | H101: 1 | I101: 24 | J101: 26 | K101: =H101*I101*J101 -> 624 | L101: 0 | M101: 0 | N101: 0 | O101: =L101*M101*N101 -> 0 | P101: =K101+O101 -> 624 | Q101: 1 | R101: 44.3 | S101: 26 | T101: =Q101*R101*S101 -> 1151.8 | U101: 0 | V101: 0 | W101: 0 | X101: =U101*V101*W101 -> 0 | Y101: =T101+X101 -> 1151.8 | Z101: 0 | AA101: 0 | AB101: 0 | AC101: =Z101*AA101*AB101 -> 0 | AD101: 0 | AE101: 0 | AF101: 0 | AG101: =AD101*AE101*AF101 -> 0 | AH101: =AC101+AG101 -> 0 | AI101: =F101+G101+P101+Y101+AH101 -> 1775.8 | AJ101: =AI101/E101 -> 0.30554026 | AK101: =(E101-AI101)*$AK$15 -> 443.982 | AL101: 0 | AM101: 0 | AN101: 0 | AO101: 0 | AP101: 0.0332 | AQ101: =AP101*E101 -> 192.9584 | AR101: =AL101+AM101+AN101+AO101+AQ101 -> 192.9584 | AS101: =AK101+AR101 -> 636.9404 | AT101: =E101-AS101 -> 5175.0596
B102: 10/25 | C102: 146 | D102: RPR 01 | E102: =12740 -> 12740 | F102: 1977.4 | G102: 2040 | H102: 2 | I102: 24 | J102: 26 | K102: =H102*I102*J102 -> 1248 | L102: 0 | M102: 0 | N102: 0 | O102: =L102*M102*N102 -> 0 | P102: =K102+O102 -> 1248 | Q102: 2 | R102: 44.3 | S102: 26 | T102: =Q102*R102*S102 -> 2303.6 | U102: 0 | V102: 0 | W102: 0 | X102: =U102*V102*W102 -> 0 | Y102: =T102+X102 -> 2303.6 | Z102: 2 | AA102: 80 | AB102: 2 | AC102: =Z102*AA102*AB102 -> 320 | AD102: 0 | AE102: 0 | AF102: 0 | AG102: =AD102*AE102*AF102 -> 0 | AH102: =AC102+AG102 -> 320 | AI102: =F102+G102+P102+Y102+AH102 -> 7889 | AJ102: =AI102/E102 -> 0.61923077 | AK102: =(E102-AI102)*$AK$15 -> 533.61 | AL102: 0 | AM102: 0 | AN102: 0 | AO102: 0 | AP102: 0.0332 | AQ102: =AP102*E102 -> 422.968 | AR102: =AL102+AM102+AN102+AO102+AQ102 -> 422.968 | AS102: =AK102+AR102 -> 956.578 | AT102: =E102-AS102 -> 11783.422
B103: 10/25 | C103: 147 | D103: PORTO SEGURO | E103: 22789 | F103: 3855.2505 | G103: 1747.465 | H103: 2 | I103: 24 | J103: 26 | K103: =H103*I103*J103 -> 1248 | L103: 2 | M103: 16 | N103: 16 | O103: =L103*M103*N103 -> 512 | P103: =K103+O103 -> 1760 | Q103: 2 | R103: 44.3 | S103: 26 | T103: =Q103*R103*S103 -> 2303.6 | U103: 2 | V103: 44.3 | W103: 16 | X103: =U103*V103*W103 -> 1417.6 | Y103: =T103+X103 -> 3721.2 | Z103: 2 | AA103: 80 | AB103: 2 | AC103: =Z103*AA103*AB103 -> 320 | AD103: 2 | AE103: 90 | AF103: 2 | AG103: =AD103*AE103*AF103 -> 360 | AH103: =AC103+AG103 -> 680 | AI103: =F103+G103+P103+Y103+AH103 -> 11763.916 | AJ103: =AI103/E103 -> 0.51621026 | AK103: =(E103-AI103)*$AK$15 -> 1212.7593 | AL103: 0 | AM103: 0 | AN103: 0 | AO103: 0 | AP103: 0.0332 | AQ103: =AP103*E103 -> 756.5948 | AR103: =AL103+AM103+AN103+AO103+AQ103 -> 756.5948 | AS103: =AK103+AR103 -> 1969.3541 | AT103: =E103-AS103 -> 20819.646
B104: 10/25 | C104: 148 | D104: VANESSA | E104: =5952 -> 5952 | F104: 950.61 | G104: 351.9 | H104: 1 | I104: 24 | J104: 26 | K104: =H104*I104*J104 -> 624 | L104: 0 | M104: 0 | N104: 0 | O104: =L104*M104*N104 -> 0 | P104: =K104+O104 -> 624 | Q104: 1 | R104: 44.3 | S104: 26 | T104: =Q104*R104*S104 -> 1151.8 | U104: 0 | V104: 0 | W104: 0 | X104: =U104*V104*W104 -> 0 | Y104: =T104+X104 -> 1151.8 | Z104: 1 | AA104: 90 | AB104: 2 | AC104: =Z104*AA104*AB104 -> 180 | AD104: 0 | AE104: 0 | AF104: 0 | AG104: =AD104*AE104*AF104 -> 0 | AH104: =AC104+AG104 -> 180 | AI104: =F104+G104+P104+Y104+AH104 -> 3258.31 | AJ104: =AI104/E104 -> 0.54743112 | AK104: =(E104-AI104)*$AK$15 -> 296.3059 | AL104: 0 | AM104: 0 | AN104: 0 | AO104: 0 | AP104: 0.0332 | AQ104: =AP104*E104 -> 197.6064 | AR104: =AL104+AM104+AN104+AO104+AQ104 -> 197.6064 | AS104: =AK104+AR104 -> 493.9123 | AT104: =E104-AS104 -> 5458.0877
B106: 11/25 | C106: 149 | D106: SHCES 509 BL B | E106: =5812 -> 5812 | F106: 0 | G106: 0 | H106: 1 | I106: 24 | J106: 26 | K106: =H106*I106*J106 -> 624 | L106: 0 | M106: 0 | N106: 0 | O106: =L106*M106*N106 -> 0 | P106: =K106+O106 -> 624 | Q106: 1 | R106: 44.3 | S106: 26 | T106: =Q106*R106*S106 -> 1151.8 | U106: 0 | V106: 0 | W106: 0 | X106: =U106*V106*W106 -> 0 | Y106: =T106+X106 -> 1151.8 | Z106: 0 | AA106: 0 | AB106: 0 | AC106: =Z106*AA106*AB106 -> 0 | AD106: 0 | AE106: 0 | AF106: 0 | AG106: =AD106*AE106*AF106 -> 0 | AH106: =AC106+AG106 -> 0 | AI106: =F106+G106+P106+Y106+AH106 -> 1775.8 | AJ106: =AI106/E106 -> 0.30554026 | AK106: =(E106-AI106)*$AK$15 -> 443.982 | AL106: 0 | AM106: 0 | AN106: 0 | AO106: 0 | AP106: 0.0332 | AQ106: =AP106*E106 -> 192.9584 | AR106: =AL106+AM106+AN106+AO106+AQ106 -> 192.9584 | AS106: =AK106+AR106 -> 636.9404 | AT106: =E106-AS106 -> 5175.0596
B107: 11/25 | C107: 150 | D107: RPR 01 | E107: =12740 -> 12740 | F107: 1977.4 | G107: 2040 | H107: 2 | I107: 24 | J107: 26 | K107: =H107*I107*J107 -> 1248 | L107: 0 | M107: 0 | N107: 0 | O107: =L107*M107*N107 -> 0 | P107: =K107+O107 -> 1248 | Q107: 2 | R107: 44.3 | S107: 26 | T107: =Q107*R107*S107 -> 2303.6 | U107: 0 | V107: 0 | W107: 0 | X107: =U107*V107*W107 -> 0 | Y107: =T107+X107 -> 2303.6 | Z107: 2 | AA107: 80 | AB107: 2 | AC107: =Z107*AA107*AB107 -> 320 | AD107: 0 | AE107: 0 | AF107: 0 | AG107: =AD107*AE107*AF107 -> 0 | AH107: =AC107+AG107 -> 320 | AI107: =F107+G107+P107+Y107+AH107 -> 7889 | AJ107: =AI107/E107 -> 0.61923077 | AK107: =(E107-AI107)*$AK$15 -> 533.61 | AL107: 0 | AM107: 0 | AN107: 0 | AO107: 0 | AP107: 0.0332 | AQ107: =AP107*E107 -> 422.968 | AR107: =AL107+AM107+AN107+AO107+AQ107 -> 422.968 | AS107: =AK107+AR107 -> 956.578 | AT107: =E107-AS107 -> 11783.422
B108: 11/25 | C108: 151 | D108: PORTO SEGURO | E108: 22789 | F108: 3855.2505 | G108: 1747.465 | H108: 2 | I108: 24 | J108: 26 | K108: =H108*I108*J108 -> 1248 | L108: 2 | M108: 16 | N108: 16 | O108: =L108*M108*N108 -> 512 | P108: =K108+O108 -> 1760 | Q108: 2 | R108: 44.3 | S108: 26 | T108: =Q108*R108*S108 -> 2303.6 | U108: 2 | V108: 44.3 | W108: 16 | X108: =U108*V108*W108 -> 1417.6 | Y108: =T108+X108 -> 3721.2 | Z108: 2 | AA108: 80 | AB108: 2 | AC108: =Z108*AA108*AB108 -> 320 | AD108: 2 | AE108: 90 | AF108: 2 | AG108: =AD108*AE108*AF108 -> 360 | AH108: =AC108+AG108 -> 680 | AI108: =F108+G108+P108+Y108+AH108 -> 11763.916 | AJ108: =AI108/E108 -> 0.51621026 | AK108: =(E108-AI108)*$AK$15 -> 1212.7593 | AL108: 0 | AM108: 0 | AN108: 0 | AO108: 0 | AP108: 0.0332 | AQ108: =AP108*E108 -> 756.5948 | AR108: =AL108+AM108+AN108+AO108+AQ108 -> 756.5948 | AS108: =AK108+AR108 -> 1969.3541 | AT108: =E108-AS108 -> 20819.646
B109: 11/25 | C109: 152 | D109: VANESSA | E109: =5952 -> 5952 | F109: 950.61 | G109: 351.9 | H109: 1 | I109: 24 | J109: 26 | K109: =H109*I109*J109 -> 624 | L109: 0 | M109: 0 | N109: 0 | O109: =L109*M109*N109 -> 0 | P109: =K109+O109 -> 624 | Q109: 1 | R109: 44.3 | S109: 26 | T109: =Q109*R109*S109 -> 1151.8 | U109: 0 | V109: 0 | W109: 0 | X109: =U109*V109*W109 -> 0 | Y109: =T109+X109 -> 1151.8 | Z109: 1 | AA109: 90 | AB109: 2 | AC109: =Z109*AA109*AB109 -> 180 | AD109: 0 | AE109: 0 | AF109: 0 | AG109: =AD109*AE109*AF109 -> 0 | AH109: =AC109+AG109 -> 180 | AI109: =F109+G109+P109+Y109+AH109 -> 3258.31 | AJ109: =AI109/E109 -> 0.54743112 | AK109: =(E109-AI109)*$AK$15 -> 296.3059 | AL109: 0 | AM109: 0 | AN109: 0 | AO109: 0 | AP109: 0.0332 | AQ109: =AP109*E109 -> 197.6064 | AR109: =AL109+AM109+AN109+AO109+AQ109 -> 197.6064 | AS109: =AK109+AR109 -> 493.9123 | AT109: =E109-AS109 -> 5458.0877
B111: 12/25 | C111: 153 | D111: SHCES 509 BL B | E111: =5812 -> 5812 | F111: 0 | G111: 0 | H111: 1 | I111: 24 | J111: 26 | K111: =H111*I111*J111 -> 624 | L111: 0 | M111: 0 | N111: 0 | O111: =L111*M111*N111 -> 0 | P111: =K111+O111 -> 624 | Q111: 1 | R111: 44.3 | S111: 26 | T111: =Q111*R111*S111 -> 1151.8 | U111: 0 | V111: 0 | W111: 0 | X111: =U111*V111*W111 -> 0 | Y111: =T111+X111 -> 1151.8 | Z111: 0 | AA111: 0 | AB111: 0 | AC111: =Z111*AA111*AB111 -> 0 | AD111: 0 | AE111: 0 | AF111: 0 | AG111: =AD111*AE111*AF111 -> 0 | AH111: =AC111+AG111 -> 0 | AI111: =F111+G111+P111+Y111+AH111 -> 1775.8 | AJ111: =AI111/E111 -> 0.30554026 | AK111: =(E111-AI111)*$AK$15 -> 443.982 | AL111: 0 | AM111: 0 | AN111: 0 | AO111: 0 | AP111: 0.0332 | AQ111: =AP111*E111 -> 192.9584 | AR111: =AL111+AM111+AN111+AO111+AQ111 -> 192.9584 | AS111: =AK111+AR111 -> 636.9404 | AT111: =E111-AS111 -> 5175.0596
B112: 12/25 | C112: 154 | D112: RPR 01 | E112: =12740 -> 12740 | F112: 1977.4 | G112: 2040 | H112: 2 | I112: 24 | J112: 26 | K112: =H112*I112*J112 -> 1248 | L112: 0 | M112: 0 | N112: 0 | O112: =L112*M112*N112 -> 0 | P112: =K112+O112 -> 1248 | Q112: 2 | R112: 44.3 | S112: 26 | T112: =Q112*R112*S112 -> 2303.6 | U112: 0 | V112: 0 | W112: 0 | X112: =U112*V112*W112 -> 0 | Y112: =T112+X112 -> 2303.6 | Z112: 2 | AA112: 80 | AB112: 2 | AC112: =Z112*AA112*AB112 -> 320 | AD112: 0 | AE112: 0 | AF112: 0 | AG112: =AD112*AE112*AF112 -> 0 | AH112: =AC112+AG112 -> 320 | AI112: =F112+G112+P112+Y112+AH112 -> 7889 | AJ112: =AI112/E112 -> 0.61923077 | AK112: =(E112-AI112)*$AK$15 -> 533.61 | AL112: 0 | AM112: 0 | AN112: 0 | AO112: 0 | AP112: 0.0332 | AQ112: =AP112*E112 -> 422.968 | AR112: =AL112+AM112+AN112+AO112+AQ112 -> 422.968 | AS112: =AK112+AR112 -> 956.578 | AT112: =E112-AS112 -> 11783.422
B113: 12/25 | C113: 155 | D113: PORTO SEGURO | E113: 22789 | F113: 3855.2505 | G113: 1747.465 | H113: 2 | I113: 24 | J113: 26 | K113: =H113*I113*J113 -> 1248 | L113: 2 | M113: 16 | N113: 16 | O113: =L113*M113*N113 -> 512 | P113: =K113+O113 -> 1760 | Q113: 2 | R113: 44.3 | S113: 26 | T113: =Q113*R113*S113 -> 2303.6 | U113: 2 | V113: 44.3 | W113: 16 | X113: =U113*V113*W113 -> 1417.6 | Y113: =T113+X113 -> 3721.2 | Z113: 2 | AA113: 80 | AB113: 2 | AC113: =Z113*AA113*AB113 -> 320 | AD113: 2 | AE113: 90 | AF113: 2 | AG113: =AD113*AE113*AF113 -> 360 | AH113: =AC113+AG113 -> 680 | AI113: =F113+G113+P113+Y113+AH113 -> 11763.916 | AJ113: =AI113/E113 -> 0.51621026 | AK113: =(E113-AI113)*$AK$15 -> 1212.7593 | AL113: 0 | AM113: 0 | AN113: 0 | AO113: 0 | AP113: 0.0332 | AQ113: =AP113*E113 -> 756.5948 | AR113: =AL113+AM113+AN113+AO113+AQ113 -> 756.5948 | AS113: =AK113+AR113 -> 1969.3541 | AT113: =E113-AS113 -> 20819.646
